Workbook

Sheet Usa Purchase
A1: Date | C1: 46082 | D1: AR-26
A2: Party Name | C2: 887544756260 Owais HT
D3: Entry Done
A4: SNo. | B4: Item Name | C4: Color | D4: Storage | E4: IMEI/Serial | F4: Comments | I4: Price USD | J4: Price AED
A5: 1 | B5: iPhone 17 Pro Max | C5: Cosmic Orange | D5: 256 GB | E5: 358051322533887 | I5: 880 | J5: =I5*3.595 -> 3163.6
A6: 2 | B6: iPhone 17 Pro Max | C6: Cosmic Orange | D6: 256 GB | E6: 353837419391642 | I6: 880 | J6: =I6*3.595 -> 3163.6
A7: 3 | B7: iPhone 17 Pro Max | C7: Cosmic Orange | D7: 256 GB | E7: 358051321265978 | F7: Active | I7: 880 | J7: =I7*3.595 -> 3163.6
A8: 4 | B8: iPhone 17 Pro Max | C8: Cosmic Orange | D8: 256 GB | E8: 356605225057831 | F8: Active | I8: 880 | J8: =I8*3.595 -> 3163.6
A9: 5 | B9: iPhone 17 Pro Max | C9: Cosmic Orange | D9: 256 GB | E9: 350889862536879 | I9: 880 | J9: =I9*3.595 -> 3163.6
A10: 6 | B10: iPhone 17 Pro Max | C10: Cosmic Orange | D10: 256 GB | E10: 353263425144000 | I10: 880 | J10: =I10*3.595 -> 3163.6
A11: 7 | B11: iPhone 17 Pro Max | C11: Cosmic Orange | D11: 256 GB | E11: 359614544687390 | I11: 880 | J11: =I11*3.595 -> 3163.6
A12: 8 | B12: iPhone 17 Pro Max | C12: Silver | D12: 256 GB | E12: 359912587219711 | I12: 900 | J12: =I12*3.595 -> 3235.5
A13: 9 | B13: iPhone 17 Pro Max | C13: Silver | D13: 256 GB | E13: 359614541610171 | I13: 900 | J13: =I13*3.595 -> 3235.5
A14: 10 | B14: iPhone 17 Pro Max | C14: Silver | D14: 256 GB | E14: 359614540060931 | I14: 900 | J14: =I14*3.595 -> 3235.5
A15: 11 | B15: iPhone 17 Pro Max | C15: Silver | D15: 512 GB | E15: 353263423932034 | I15: 980 | J15: =I15*3.595 -> 3523.1
A16: 12 | B16: iPhone 16 Pro Max | C16: Desert Ti | D16: 256 GB | E16: 355008282401839 | I16: 730 | J16: =I16*3.595 -> 2624.35
A17: 13 | B17: iPhone 16 Pro Max (FU Kit) | C17: White Ti | D17: 1 TB | E17: 355445520481381 | F17: Active Factory Unlock | I17: 620 | J17: =I17*3.595 -> 2228.9
A18: 14 | B18: iPhone 16 Pro (FU Kit) | C18: Black Ti | D18: 256 GB | E18: 357719281961635 | F18: Active Factory Unlock | I18: 620 | J18: =I18*3.595 -> 2228.9
A19: 15 | B19: iPhone 16 (FU Kit) | C19: Ultramarine | D19: 256 GB | E19: 357762265949689 | F19: Active Factory Unlock | I19: 470 | J19: =I19*3.595 -> 1689.65
A20: 16 | B20: iPhone 16 (FU Kit) | C20: Teal | D20: 128 GB | E20: 353685834007800 | F20: Active Factory Unlock | I20: 350 | J20: =I20*3.595 -> 1258.25
A21: 17 | B21: iPhone 16 | C21: White | D21: 256 GB | E21: 357985605788059 | I21: 470 | J21: =I21*3.595 -> 1689.65
A22: 18 | B22: iPhone 16e | C22: Black | D22: 128 GB | E22: 355852812209224 | F22: MDM | I22: 165 | J22: =I22*3.595 -> 593.175
A23: 19 | B23: iPhone 16e | C23: Black | D23: 128 GB | E23: 350138782777415 | I23: 205 | J23: =I23*3.595 -> 736.975
A24: 20 | B24: iPhone 16e | C24: White | D24: 128 GB | E24: 352515983937724 | F24: T-Mobile | I24: 205 | J24: =I24*3.595 -> 736.975
A25: 21 | B25: iPhone 16e | C25: White | D25: 128 GB | E25: 350304975570948 | I25: 205 | J25: =I25*3.595 -> 736.975
A26: 22 | B26: iPhone 15 | C26: Blue | D26: 128 GB | E26: 356832826585198 | F26: T-Mobile | I26: 280 | J26: =I26*3.595 -> 1006.6
A27: 23 | B27: iPhone 14 Pro Max (FU Kit) | C27: Deep Purple | D27: 128 GB | E27: 357773240293275 | F27: Active Factory Unlock | I27: 410 | J27: =I27*3.595 -> 1473.95
A28: 24 | B28: iPhone 14 Pro Max (FU Kit) | C28: Deep Purple | D28: 256 GB | E28: 357773241392274 | F28: Active Factory Unlock | I28: 420 | J28: =I28*3.595 -> 1509.9
A29: 21 | B29: iPhone 13 (FU Kit) | C29: Product Red | D29: 128 GB | E29: 358691739992588 | F29: Active Factory Unlock | I29: 200 | J29: =I29*3.595 -> 719
A30: 22 | B30: iPhone 11 Pro Max (FU Kit) | C30: Space Gray | D30: 256 GB | E30: 353894107001488 | F30: Active Factory Unlock | I30: 175 | J30: =I30*3.595 -> 629.125
A31: 23 | B31: iPhone SE | C31: Midnight | D31: 128 GB | E31: 358229303109360 | F31: Active | I31: 80 | J31: =I31*3.595 -> 287.6
A32: 24 | B32: iPad Pro M5 11" (W+C) | C32: Space Black | D32: 256 GB | E32: 358112930542452 | F32: Locked | I32: 850 | J32: =I32*3.595 -> 3055.75
A33: 25 | B33: iPad Pro M4 13" (W+C) | C33: Space Black | D33: 256 GB | E33: 356334540274274 | I33: 945 | J33: =I33*3.595 -> 3397.275
A34: 26 | B34: iPad Air M3 13" (W) | C34: Space Gray | D34: 128 GB | E34: SJ56LKQX91F | I34: 550 | J34: =I34*3.595 -> 1977.25
A35: 27 | B35: iPad Air M3 13" (W) | C35: Space Gray | D35: 128 GB | E35: SLJ2DW1GJPG | I35: 600 | J35: =I35*3.595 -> 2157
A36: 28 | B36: iPad A16 (W+C) | C36: Silver | D36: 128 GB | E36: 350094261697964 | I36: 285 | J36: =I36*3.595 -> 1024.575
A37: 29 | B37: iPad A16 (W+C) | C37: Silver | D37: 128 GB | E37: 350094261355704 | I37: 285 | J37: =I37*3.595 -> 1024.575
A38: 30 | B38: iPad Mini A17 Pro (W+C) | C38: Space Gray | D38: 128 GB | E38: 357153132623899 | I38: 430 | J38: =I38*3.595 -> 1545.85
A39: 31 | B39: iPad Mini A17 Pro (W) | C39: Purple | D39: 256 GB | E39: SM04W37XK2M | I39: 475 | J39: =I39*3.595 -> 1707.625
A40: 32 | B40: MacBook Pro M5 14" MDE14LL/A | C40: Space Black | D40: 16 GB, 1 TB | E40: SMT79VX36C5 | I40: 1550 | J40: =I40*3.595 -> 5572.25
A41: 33 | B41: MacBook Pro M5 14" MDE14LL/A | C41: Space Black | D41: 16 GB, 1 TB | E41: SMJF72R0W6K | I41: 1550 | J41: =I41*3.595 -> 5572.25
A42: 34 | B42: MacBook Pro M5 14" MDE64LL/A | C42: Silver | D42: 24 GB, 1 TB | E42: SF3W6VGQT49 | I42: 1670 | J42: =I42*3.595 -> 6003.65
A43: 35 | B43: MacBook Pro M4 Pro 14" MX2H3LL/A | C43: Space Black | D43: 24 GB, 512 GB | E43: SDF9R6G97J0 | I43: 1630 | J43: =I43*3.595 -> 5859.85
A44: 36 | B44: Apple Watch Ultra 3 | C44: Black Ti, M/L | D44: 49mm | E44: 356187982445939 | I44: 640 | J44: =I44*3.595 -> 2300.8
A45: 37 | B45: Apple Watch SE 3 | C45: Midnight | D45: 40mm | E45: 359132197678855 | I45: 180 | J45: =I45*3.595 -> 647.1
A46: 38 | B46: Apple Watch SE 3 | C46: Starlight | D46: 44mm | E46: SH6W4PFQWCW | I46: 200 | J46: =I46*3.595 -> 719
A47: 39 | B47: AirPods Pro 3 | E47: SD2WYWYFPLV | I47: 195 | J47: =I47*3.595 -> 701.025
A48: 40 | B48: AirPods Pro 3 | E48: SDX9XWFKW42 | I48: 195 | J48: =I48*3.595 -> 701.025
A49: 41 | B49: AirPods Pro 3 | E49: SL9W0J24GDM | I49: 195 | J49: =I49*3.595 -> 701.025
A50: 42 | B50: AirPods Pro 3 | E50: SM7RR6FRW7N | I50: 195 | J50: =I50*3.595 -> 701.025
A51: 43 | B51: AirPods 4 (ANC) | E51: SMT43DHJRGH | I51: 125 | J51: =I51*3.595 -> 449.375
A52: 44 | B52: AirPods 4 (ANC) | E52: SK946HW04X3 | I52: 125 | J52: =I52*3.595 -> 449.375
A53: 45 | B53: AirPods 4 (ANC) | E53: SGD4TR707KJ | I53: 125 | J53: =I53*3.595 -> 449.375
A54: 46 | B54: Galaxy Z Flip 7 | C54: Blue Shadow | D54: 256 GB | E54: 359800206266629 | F54: Return | I54: 420 | J54: =I54*3.595 -> 1509.9
A55: 47 | B55: Galaxy Z Flip 7 | C55: Jetblack | D55: 256 GB | E55: 358344510337678 | F55: Return | I55: 420 | J55: =I55*3.595 -> 1509.9
A56: 48 | B56: Galaxy Z Flip 7 | C56: Coralred | D56: 256 GB | E56: 359800204422869 | F56: Return | I56: 420 | J56: =I56*3.595 -> 1509.9
A57: 49 | B57: Meta Headliner Gen 2 | C57: Graphite Green | E57: 4V0ZH17H7X01K1 | I57: 300 | J57: =I57*3.595 -> 1078.5
A58: 50 | B58: Meta Wayfarer Gen 2 | C58: Polar Graphite | E58: 4V37W23H8Y03BB | I58: 350 | J58: =I58*3.595 -> 1258.25
A59: 51 | B59: Meta Wayfarer | C59: Clear | E59: 2Q0ZT00H9108MM | I59: 350 | J59: =I59*3.595 -> 1258.25
A60: 52 | B60: Meta Skyler Gen 2 | C60: Amethyst | E60: 4V0ZS17H8H02KD | I60: 300 | J60: =I60*3.595 -> 1078.5
A61: 53 | B61: Meta Skyler Gen 2 | C61: Clear | E61: 4V0ZS12H8M0121 | I61: 300 | J61: =I61*3.595 -> 1078.5
A62: 54 | B62: Meta Skyler | C62: Cerulean Blue | E62: 2Q0ZY01H6R0088 | I62: 300 | J62: =I62*3.595 -> 1078.5
A66: Date | C66: 12-29-2025 | D66: Invoice 44
A67: Party Name | C67: 887280868921 M
D68: Entry Done
A69: SNo. | B69: Item Name | C69: Color | D69: Storage | E69: IMEI/Serial | F69: Comments | I69: Price
A70: 1 | B70: iPhone 17 Pro Max | C70: Cosmic Orange | D70: 256 GB | E70: 359614540205064 | F70: T-Mobile | I70: 3300
A71: 2 | B71: iPhone 17 Pro Max | C71: Cosmic Orange | D71: 256 GB | E71: 353263422963410 | F71: T-Mobile | I71: 3300
A72: 3 | B72: iPhone 17 Pro Max | C72: Cosmic Orange | D72: 256 GB | E72: 356188161192995 | I72: 3300
A73: 4 | B73: iPhone 17 Pro Max | C73: Cosmic Orange | D73: 256 GB | E73: 356764179559548 | I73: 3300
A74: 5 | B74: iPhone 17 Pro Max | C74: Cosmic Orange | D74: 256 GB | E74: 358482492772130 | I74: 3300
A75: 6 | B75: iPhone 17 Pro Max | C75: Cosmic Orange | D75: 256 GB | E75: 355478877711241 | I75: 3300
A76: 7 | B76: iPhone 17 Pro Max | C76: Deep Blue | D76: 256 GB | E76: 355450218827739 | I76: 3050
A77: 8 | B77: iPhone 17 Pro Max | C77: Deep Blue | D77: 256 GB | E77: 356605220869008 | F77: T-Mobile | I77: 3050
A78: 9 | B78: iPhone 17 Pro Max | C78: Deep Blue | D78: 256 GB | E78: 355450218921904 | I78: 3050
A79: 10 | B79: iPhone 17 Pro Max | C79: Deep Blue | D79: 256 GB | E79: 358482492116395 | F79: T-Mobile | I79: 3050
A80: 11 | B80: iPhone 17 Pro Max | C80: Deep Blue | D80: 256 GB | E80: 357586344039901
A81: 12 | B81: iPhone 17 Pro Max | C81: Silver | D81: 256 GB | E81: 358482493754913 | I81: 3350
A82: 13 | B82: iPhone 17 Pro Max | C82: Silver | D82: 256 GB | E82: 358482493754913 | I82: 3350
A83: 14 | B83: iPhone 17 Pro | C83: Cosmic Orange | D83: 256 GB | E83: 355122365088007 | F83: Active
A84: 15 | B84: iPhone 17 Pro | C84: Deep Blue | D84: 256 GB | E84: 352440638029357
A85: 16 | B85: iPhone 17 Pro | C85: Deep Blue | D85: 256 GB | E85: 352440638529299 | I85: 2500
A86: 17 | B86: iPhone 17 Pro | C86: Deep Blue | D86: 256 GB | E86: 352440638658510 | I86: 2500
A87: 18 | B87: iPhone 17 Pro | C87: Deep Blue | D87: 256 GB | E87: 352190321356316 | F87: Active | I87: 2450
A88: 19 | B88: iPhone 17 Air | C88: Sky Blue | D88: 256 GB | E88: 351605721516327 | F88: Damaged Box | I88: 1900
A89: 20 | B89: iPhone 17 Air | C89: Space Black | D89: 256 GB | E89: 358302114634163 | I89: 1900
A90: 21 | B90: iPhone 17 Air | C90: Space Black | D90: 256 GB | E90: 351605725243233 | I90: 1900
A91: 22 | B91: iPhone 17 Air | C91: Space Black | D91: 256 GB | E91: 358838945453216 | I91: 1900
A92: 23 | B92: iPhone 17 Air | C92: Cloud White | D92: 256 GB | E92: 357247594841112 | I92: 1900
A93: 24 | B93: iPhone 17 | C93: Lavender | D93: 256 GB | E93: 354780907319619 | F93: T-Mobile | I93: 1900
A94: 25 | B94: iPhone 17 | C94: Lavender | D94: 256 GB | E94: 359045769498108 | F94: T-Mobile | I94: 1900
A95: 26 | B95: iPad Pro M5 11" (W+C) | C95: Space Black | D95: 256 GB | E95: 358112934982993 | I95: 3900
A96: 27 | B96: MacBook Pro M4 Pro 16" MX2X3LL/A | C96: Space Black | D96: 24 GB, 512 GB | E96: SHM4CWCLPK0
A97: 28 | B97: MacBook Pro M4 Pro 16" MX2X3LL/A | C97: Space Black | D97: 24 GB, 512 GB | E97: SCN9GQDX3F9
A98: 29 | B98: MacBook Pro M4 Pro 16" MX2X3LL/A | C98: Space Black | D98: 24 GB, 512 GB | E98: SD3KT644PHW
A99: 30 | B99: Apple Watch Ultra 3 | C99: Black Ti, Alp | D99: 49mm | E99: 356187983271318 | I99: 2380
A100: 31 | B100: Apple Watch Ultra 3 | C100: Black Ti, Alp | D100: 49mm | E100: 353938643484441
A101: 32 | B101: Apple Watch Ultra 3 | C101: Black Ti, M/L | D101: 49mm | E101: 358135793097124 | I101: 2380
A102: 33 | B102: Apple Watch Ultra 3 | C102: Black Ti, M/L | D102: 49mm | E102: 358135793204829 | I102: 2380
A103: 34 | B103: Apple Watch Ultra 3 | C103: Natural Ti, Ocean | D103: 49mm | E103: 358135793673171 | I103: 2380
...

Sheet Purchases
A3: 1 | B3: NewZeland
B4: Date | C4: Product Name | D4: Qty | E4: Per/Unit (AUD) | F4: Price (AUD) | G4: C. Rate | H4: Per/Unit (AED) | I4: Total Price (AED)
B5: 45672 | C5: Starlink v4 19Units @580 WB | D5: 19 | E5: 580 | F5: =E5*D5 -> 11020 | G5: 2.19 | H5: =E5*G5 -> 1270.2 | I5: =H5*D5 -> 24133.8 | J5: =J4+I5 -> 24133.8
H6: =E6*G6 -> 0 | I6: =H6*D6 -> 0 | J6: =J5+I6 -> 24133.8
H7: =E7*G7 -> 0 | I7: =H7*D7 -> 0 | J7: =J6+I7 -> 24133.8
H8: =E8*G8 -> 0 | I8: =H8*D8 -> 0 | J8: =J7+I8 -> 24133.8
H9: =E9*G9 -> 0 | I9: =H9*D9 -> 0 | J9: =J8+I9 -> 24133.8
H10: =E10*G10 -> 0 | I10: =H10*D10 -> 0 | J10: =J9+I10 -> 24133.8
H11: =E11*G11 -> 0 | I11: =H11*D11 -> 0 | J11: =J10+I11 -> 24133.8
H12: =E12*G12 -> 0 | I12: =H12*D12 -> 0 | J12: =J11+I12 -> 24133.8
H13: =E13*G13 -> 0 | I13: =H13*D13 -> 0 | J13: =J12+I13 -> 24133.8
A16: 2 | B16: NewZeland
B17: Date | C17: Product Name | D17: Qty | E17: Per/Unit (AUD) | F17: Price (AUD) | G17: C. Rate | H17: Per/Unit (AED) | I17: Total Price (AED) | K17: Paid
B18: 45695 | C18: Starlink Mini 500 Units $630 WB | D18: 500 | E18: 630 | F18: =E18*D18 -> 315000 | G18: 2.19 | H18: =E18*G18 -> 1379.7 | I18: =H18*D18 -> 689850 | J18: =J17+I18 -> 689850 | K18: 270000 | L18: =315000-270000 -> 45000 | N18: NewZeland
B19: 45695 | C19: JBL Charge 5 150Units $148 WB | D19: 150 | E19: 148 | F19: =E19*D19 -> 22200 | G19: 2.19 | H19: =E19*G19 -> 324.12 | I19: =H19*D19 -> 48618 | J19: =J18+I19 -> 738468 | N19: Date | O19: Product Name | P19: Qty | Q19: Per/Unit (AUD) | R19: Price (AUD) | S19: C. Rate | T19: Per/Unit (AED) | U19: Total Price (AED)
B20: 45695 | C20: JBL Charge 5 50Units $145 WB | D20: 50 | E20: 145 | F20: =E20*D20 -> 7250 | G20: 2.19 | H20: =E20*G20 -> 317.55 | I20: =H20*D20 -> 15877.5 | J20: =J19+I20 -> 754345.5 | R20: =Q20*P20 -> 0 | T20: =Q20*S20 -> 0 | U20: =T20*P20 -> 0 | V20: =V19+U20 -> 0
B21: 45695 | C21: Google Chrome Cast 250Units $149 WB | D21: 250 | E21: 149 | F21: =E21*D21 -> 37250 | G21: 2.19 | H21: =E21*G21 -> 326.31 | I21: =H21*D21 -> 81577.5 | J21: =J20+I21 -> 835923 | R21: =Q21*P21 -> 0 | T21: =Q21*S21 -> 0 | U21: =T21*P21 -> 0 | V21: =V20+U21 -> 0
F22: =E22*D22 -> 0 | H22: =E22*G22 -> 0 | I22: =H22*D22 -> 0 | J22: =J21+I22 -> 835923 | R22: =Q22*P22 -> 0 | T22: =Q22*S22 -> 0 | U22: =T22*P22 -> 0 | V22: =V21+U22 -> 0
F23: =E23*D23 -> 0 | H23: =E23*G23 -> 0 | I23: =H23*D23 -> 0 | J23: =J22+I23 -> 835923 | R23: =Q23*P23 -> 0 | T23: =Q23*S23 -> 0 | U23: =T23*P23 -> 0 | V23: =V22+U23 -> 0
F24: =E24*D24 -> 0 | H24: =E24*G24 -> 0 | I24: =H24*D24 -> 0 | J24: =J23+I24 -> 835923 | R24: =Q24*P24 -> 0 | T24: =Q24*S24 -> 0 | U24: =T24*P24 -> 0 | V24: =V23+U24 -> 0
F25: =E25*D25 -> 0 | H25: =E25*G25 -> 0 | I25: =H25*D25 -> 0 | J25: =J24+I25 -> 835923 | R25: =Q25*P25 -> 0 | T25: =Q25*S25 -> 0 | U25: =T25*P25 -> 0 | V25: =V24+U25 -> 0
F26: =E26*D26 -> 0 | H26: =E26*G26 -> 0 | I26: =H26*D26 -> 0 | J26: =J25+I26 -> 835923 | R26: =Q26*P26 -> 0 | T26: =Q26*S26 -> 0 | U26: =T26*P26 -> 0 | V26: =V25+U26 -> 0
R27: =Q27*P27 -> 0 | T27: =Q27*S27 -> 0 | U27: =T27*P27 -> 0 | V27: =V26+U27 -> 0
R28: =Q28*P28 -> 0 | T28: =Q28*S28 -> 0 | U28: =T28*P28 -> 0 | V28: =V27+U28 -> 0
A29: 3 | B29: Australia
B30: Date | C30: Product Name | D30: Qty | E30: Per/Unit (AUD) | F30: Price (AUD) | G30: C. Rate | H30: Per/Unit (AED) | I30: Total Price (AED)
B31: 45701 | C31: Instax Wide 400 5units $188 WB | D31: 5 | E31: 188 | F31: =E31*D31 -> 940 | G31: 2.32 | H31: =E31*G31 -> 436.16 | I31: =H31*D31 -> 2180.8 | J31: =J30+I31 -> 2180.8
B32: 45701 | C32: JBL Charge5 125Units $133.30 WB | D32: 125 | E32: 133.3 | F32: =E32*D32 -> 16662.5 | G32: 2.32 | H32: =E32*G32 -> 309.256 | I32: =H32*D32 -> 38657 | J32: =J31+I32 -> 40837.8 | N32: Australia
F33: =E33*D33 -> 0 | H33: =E33*G33 -> 0 | I33: =H33*D33 -> 0 | J33: =J32+I33 -> 40837.8 | N33: Date | O33: Product Name | P33: Store | Q33: Status | R33: Qty | S33: Per/Unit (AUD) | T33: Discount % | U33: Discount | V33: Per/Unit After Dis. | W33: Total AUD | X33: C.Rate | Y33: Per/unit AED | Z33: Total Price (AED)
F34: =E34*D34 -> 0 | H34: =E34*G34 -> 0 | I34: =H34*D34 -> 0 | J34: =J33+I34 -> 40837.8 | U34: =S34*T34% -> 0 | V34: =S34-U34 -> 0 | W34: =R34*V34 -> 0 | X34: 2.33 | Y34: =V34*X34 -> 0 | Z34: =R34*Y34 -> 0 | AA34: =AA33+Z34 -> 0
F35: =E35*D35 -> 0 | H35: =E35*G35 -> 0 | I35: =H35*D35 -> 0 | J35: =J34+I35 -> 40837.8 | U35: =S35*T35% -> 0 | V35: =S35-U35 -> 0 | W35: =R35*V35 -> 0 | Y35: =V35*X35 -> 0 | Z35: =R35*Y35 -> 0 | AA35: =AA34+Z35 -> 0
F36: =E36*D36 -> 0 | H36: =E36*G36 -> 0 | I36: =H36*D36 -> 0 | J36: =J35+I36 -> 40837.8 | U36: =S36*T36% -> 0 | V36: =S36-U36 -> 0 | W36: =R36*V36 -> 0 | Y36: =V36*X36 -> 0 | Z36: =R36*Y36 -> 0 | AA36: =AA35+Z36 -> 0
F37: =E37*D37 -> 0 | H37: =E37*G37 -> 0 | I37: =H37*D37 -> 0 | J37: =J36+I37 -> 40837.8 | U37: =S37*T37% -> 0 | V37: =S37-U37 -> 0 | W37: =R37*V37 -> 0 | Y37: =V37*X37 -> 0 | Z37: =R37*Y37 -> 0 | AA37: =AA36+Z37 -> 0
F38: =E38*D38 -> 0 | H38: =E38*G38 -> 0 | I38: =H38*D38 -> 0 | J38: =J37+I38 -> 40837.8 | U38: =S38*T38% -> 0 | V38: =S38-U38 -> 0 | W38: =R38*V38 -> 0 | Y38: =V38*X38 -> 0 | Z38: =R38*Y38 -> 0 | AA38: =AA37+Z38 -> 0
F39: =E39*D39 -> 0 | H39: =E39*G39 -> 0 | I39: =H39*D39 -> 0 | J39: =J38+I39 -> 40837.8 | U39: =S39*T39% -> 0 | V39: =S39-U39 -> 0 | W39: =R39*V39 -> 0 | Y39: =V39*X39 -> 0 | Z39: =R39*Y39 -> 0 | AA39: =AA38+Z39 -> 0
U40: =S40*T40% -> 0 | V40: =S40-U40 -> 0 | W40: =R40*V40 -> 0 | Y40: =V40*X40 -> 0 | Z40: =R40*Y40 -> 0 | AA40: =AA39+Z40 -> 0
U41: =S41*T41% -> 0 | V41: =S41-U41 -> 0 | W41: =R41*V41 -> 0 | Y41: =V41*X41 -> 0 | Z41: =R41*Y41 -> 0 | AA41: =AA40+Z41 -> 0
A42: 4 | B42: NewZeland | U42: =S42*T42% -> 0 | V42: =S42-U42 -> 0 | W42: =R42*V42 -> 0 | Y42: =V42*X42 -> 0 | Z42: =R42*Y42 -> 0 | AA42: =AA41+Z42 -> 0
B43: Date | C43: Product Name | D43: Qty | E43: Per/Unit (AUD) | F43: Price (AUD) | G43: C. Rate | H43: Per/Unit (AED) | I43: Total Price (AED) | U43: =S43*T43% -> 0 | V43: =S43-U43 -> 0 | W43: =R43*V43 -> 0 | Y43: =V43*X43 -> 0 | Z43: =R43*Y43 -> 0 | AA43: =AA42+Z43 -> 0
B44: 45705 | C44: Google Chrome Cast 250Units $149 WB | D44: 250 | E44: 149 | F44: =E44*D44 -> 37250 | G44: 2.19 | H44: =E44*G44 -> 326.31 | I44: =H44*D44 -> 81577.5 | J44: =J43+I44 -> 81577.5
F45: =E45*D45 -> 0 | H45: =E45*G45 -> 0 | I45: =H45*D45 -> 0 | J45: =J44+I45 -> 81577.5
F46: =E46*D46 -> 0 | H46: =E46*G46 -> 0 | I46: =H46*D46 -> 0 | J46: =J45+I46 -> 81577.5
F47: =E47*D47 -> 0 | H47: =E47*G47 -> 0 | I47: =H47*D47 -> 0 | J47: =J46+I47 -> 81577.5
F48: =E48*D48 -> 0 | H48: =E48*G48 -> 0 | I48: =H48*D48 -> 0 | J48: =J47+I48 -> 81577.5
F49: =E49*D49 -> 0 | H49: =E49*G49 -> 0 | I49: =H49*D49 -> 0 | J49: =J48+I49 -> 81577.5
F50: =E50*D50 -> 0 | H50: =E50*G50 -> 0 | I50: =H50*D50 -> 0 | J50: =J49+I50 -> 81577.5
F51: =E51*D51 -> 0 | H51: =E51*G51 -> 0 | I51: =H51*D51 -> 0 | J51: =J50+I51 -> 81577.5
F52: =E52*D52 -> 0 | H52: =E52*G52 -> 0 | I52: =H52*D52 -> 0 | J52: =J51+I52 -> 81577.5
A55: 5 | B55: NewZeland
B56: Date | C56: Product Name | D56: Qty | E56: Per/Unit (AUD) | F56: Price (AUD) | G56: C. Rate | H56: Per/Unit (AED) | I56: Total Price (AED)
B57: 45706 | C57: Starlink V4 200Units $549 WB | D57: 200 | E57: 549 | F57: =E57*D57 -> 109800 | G57: 2.19 | H57: =E57*G57 -> 1202.31 | I57: =H57*D57 -> 240462 | J57: =J56+I57 -> 240462
B58: 45706 | C58: JBL Charge.5 6Units $145 WB | D58: 6 | E58: 145 | F58: =E58*D58 -> 870 | G58: 2.19 | H58: =E58*G58 -> 317.55 | I58: =H58*D58 -> 1905.3 | J58: =J57+I58 -> 242367.3
B59: 45706 | C59: PS5 15Units $695 ARB | D59: 15 | E59: 695 | F59: =E59*D59 -> 10425 | G59: 2.19 | H59: =E59*G59 -> 1522.05 | I59: =H59*D59 -> 22830.75 | J59: =J58+I59 -> 265198.05
F60: =E60*D60 -> 0 | H60: =E60*G60 -> 0 | I60: =H60*D60 -> 0 | J60: =J59+I60 -> 265198.05
F61: =E61*D61 -> 0 | H61: =E61*G61 -> 0 | I61: =H61*D61 -> 0 | J61: =J60+I61 -> 265198.05
F62: =E62*D62 -> 0 | H62: =E62*G62 -> 0 | I62: =H62*D62 -> 0 | J62: =J61+I62 -> 265198.05
F63: =E63*D63 -> 0 | H63: =E63*G63 -> 0 | I63: =H63*D63 -> 0 | J63: =J62+I63 -> 265198.05
F64: =E64*D64 -> 0 | H64: =E64*G64 -> 0 | I64: =H64*D64 -> 0 | J64: =J63+I64 -> 265198.05
F65: =E65*D65 -> 0 | H65: =E65*G65 -> 0 | I65: =H65*D65 -> 0 | J65: =J64+I65 -> 265198.05
A70: 6 | B70: Australia
B71: Date | C71: Product Name | D71: Qty | E71: Per/Unit (AUD) | F71: Price (AUD) | G71: C. Rate | H71: Per/Unit (AED) | I71: Total Price (AED)
B72: 45709 | C72: I MAC WB CARD | D72: 1 | E72: 1919 | F72: =E72*D72 -> 1919 | G72: 2.325 | H72: =E72*G72 -> 4461.675 | I72: =H72*D72 -> 4461.675 | J72: =J71+I72 -> 4461.675
B73: 45709 | C73: I MAC WB CARD | D73: 1 | E73: 1934 | F73: =E73*D73 -> 1934 | G73: 2.325 | H73: =E73*G73 -> 4496.55 | I73: =H73*D73 -> 4496.55 | J73: =J72+I73 -> 8958.225
B74: 45709 | C74: MACBOOK M4 with Airpods 4 WB Card | D74: 7 | E74: 2349 | F74: =E74*D74 -> 16443 | G74: 2.325 | H74: =E74*G74 -> 5461.425 | I74: =H74*D74 -> 38229.975 | J74: =J73+I74 -> 47188.2
B75: 45709 | C75: MACBOOK M4 with Airpods 4 ABR Card | D75: 1 | E75: 2349 | F75: =E75*D75 -> 2349 | G75: 2.325 | H75: =E75*G75 -> 5461.425 | I75: =H75*D75 -> 5461.425 | J75: =J74+I75 -> 52649.625
B76: 45709 | C76: MACBOOK M4 with Airpods 4 WB Card(Apple Hornsby Pending Collection) | D76: 1 | E76: 2349 | F76: =E76*D76 -> 2349 | G76: 2.325 | H76: =E76*G76 -> 5461.425 | I76: =H76*D76 -> 5461.425 | J76: =J75+I76 -> 58111.05
B77: 45709 | C77: "Instax wide 400 WB Card (Harvey Norman Castle Hills Pending collection)" | D77: 10 | E77: 188 | F77: =E77*D77 -> 1880 | G77: 2.325 | H77: =E77*G77 -> 437.1 | I77: =H77*D77 -> 4371 | J77: =J76+I77 -> 62482.05 | K77: refund
B78: 45709 | C78: Innstax mini Evo 1 unit $248 HN CH | D78: 1 | E78: 248 | F78: =E78*D78 -> 248 | G78: 2.325 | H78: =E78*G78 -> 576.6 | I78: =H78*D78 -> 576.6 | J78: =J77+I78 -> 63058.65
B79: 45709 | C79: Instax Li Play 1 Unit $203 HN CH | D79: 1 | E79: 203 | F79: =E79*D79 -> 203 | G79: 2.325 | H79: =E79*G79 -> 471.975 | I79: =H79*D79 -> 471.975 | J79: =J78+I79 -> 63530.625
B80: 45709 | C80: Instax mini 40 1 unit $143 HN CH | D80: 1 | E80: 143 | F80: =E80*D80 -> 143 | G80: 2.325 | H80: =E80*G80 -> 332.475 | I80: =H80*D80 -> 332.475 | J80: =J79+I80 -> 63863.1
A81: entry | B81: 45709 | C81: Instax mini 99 Bundle 1 unit $250 JBHIFI CH | D81: 1 | E81: 250 | F81: =E81*D81 -> 250 | G81: 2.325 | H81: =E81*G81 -> 581.25 | I81: =H81*D81 -> 581.25 | J81: =J80+I81 -> 64444.35
A92: entry | B92: Australia
B93: Date | C93: Product Name | D93: Qty | E93: Per/Unit (AUD) | F93: Price (AUD) | G93: C. Rate | H93: Per/Unit (AED) | I93: Total Price (AED)
B94: 45710 | C94: Mac Book 4 Anwar Ali | D94: 1 | E94: 2364 | F94: =E94*D94 -> 2364 | G94: 2.35 | H94: =E94*G94 -> 5555.4 | I94: =H94*D94 -> 5555.4 | J94: =J93+I94 -> 5555.4
B95: 45710 | C95: Mac Book 4 Noaman Mughal | D95: 1 | E95: 2349 | F95: =E95*D95 -> 2349 | G95: 2.35 | H95: =E95*G95 -> 5520.15 | I95: =H95*D95 -> 5520.15 | J95: =J94+I95 -> 11075.55
B96: 45710 | C96: Mac Book 4 Atiya Hayat | D96: 1 | E96: 2349 | F96: =E96*D96 -> 2349 | G96: 2.35 | H96: =E96*G96 -> 5520.15 | I96: =H96*D96 -> 5520.15 | J96: =J95+I96 -> 16595.7
B97: 45710 | C97: Mac Book 4 Saleem Hayat | D97: 1 | E97: 2349 | F97: =E97*D97 -> 2349 | G97: 2.35 | H97: =E97*G97 -> 5520.15 | I97: =H97*D97 -> 5520.15 | J97: =J96+I97 -> 22115.85
B98: 45710 | C98: Mac Book 4 Noureen Mughal | D98: 1 | E98: 2349 | F98: =E98*D98 -> 2349 | G98: 2.35 | H98: =E98*G98 -> 5520.15 | I98: =H98*D98 -> 5520.15 | J98: =J97+I98 -> 27636
B99: 45710 | C99: Mac Book 4 Abdul Shahid | D99: 1 | E99: 2349 | F99: =E99*D99 -> 2349 | G99: 2.35 | H99: =E99*G99 -> 5520.15 | I99: =H99*D99 -> 5520.15 | J99: =J98+I99 -> 33156.15
B100: 45710 | C100: Mac Book 4 Talha Noaman | D100: 1 | E100: 2349 | F100: =E100*D100 -> 2349 | G100: 2.35 | H100: =E100*G100 -> 5520.15 | I100: =H100*D100 -> 5520.15 | J100: =J99+I100 -> 38676.3
B101: 45711 | C101: Mac Book 4 Talha Noaman | D101: 1 | E101: 2349 | F101: =E101*D101 -> 2349 | G101: 2.35 | H101: =E101*G101 -> 5520.15 | I101: =H101*D101 -> 5520.15 | J101: =J100+I101 -> 44196.45
B102: 45711 | C102: Mac Book 4 Noureen Mughal | D102: 1 | E102: 2349 | F102: =E102*D102 -> 2349 | G102: 2.35 | H102: =E102*G102 -> 5520.15 | I102: =H102*D102 -> 5520.15 | J102: =J101+I102 -> 49716.6
B103: 45711 | C103: Mac Book 4 Noaman Mughal | D103: 1 | E103: 2349 | F103: =E103*D103 -> 2349 | G103: 2.35 | H103: =E103*G103 -> 5520.15 | I103: =H103*D103 -> 5520.15 | J103: =J102+I103 -> 55236.75
B104: 45711 | C104: Mac Book 4 Atiya Hayat | D104: 1 | E104: 2349 | F104: =E104*D104 -> 2349 | G104: 2.35 | H104: =E104*G104 -> 5520.15 | I104: =H104*D104 -> 5520.15 | J104: =J103+I104 -> 60756.9
B105: 45711 | C105: Mac Book 4 Anwar Ali | D105: 1 | E105: 2364 | F105: =E105*D105 -> 2364 | G105: 2.35 | H105: =E105*G105 -> 5555.4 | I105: =H105*D105 -> 5555.4 | J105: =J104+I105 -> 66312.3
B106: 45711 | C106: Mac Book 4 Abdul Shahid | D106: 1 | E106: 2364 | F106: =E106*D106 -> 2364 | G106: 2.35 | H106: =E106*G106 -> 5555.4 | I106: =H106*D106 -> 5555.4 | J106: =J105+I106 -> 71867.7
F107: =E107*D107 -> 0 | H107: =E107*G107 -> 0 | I107: =H107*D107 -> 0 | J107: =J106+I107 -> 71867.7
B108: 45711 | C108: Mac Book 4 Waheed NAB CR Card | D108: 1 | E108: 2349 | F108: =E108*D108 -> 2349 | G108: 2.35 | H108: =E108*G108 -> 5520.15 | I108: =H108*D108 -> 5520.15 | J108: =J107+I108 -> 77387.85
B109: 45711 | C109: Mac Book 4 Waheed NAB CR Card | D109: 1 | E109: 2349 | F109: =E109*D109 -> 2349 | G109: 2.35 | H109: =E109*G109 -> 5520.15 | I109: =H109*D109 -> 5520.15 | J109: =J108+I109 -> 82908
B110: 45711 | C110: IMac4 Waheed NAB CR Card | D110: 1 | E110: 1919 | F110: =E110*D110 -> 1919 | G110: 2.35 | H110: =E110*G110 -> 4509.65 | I110: =H110*D110 -> 4509.65 | J110: =J109+I110 -> 87417.65
A114: entry | B114: Australia
B115: Date | C115: Product Name | D115: Qty | E115: Per/Unit (AUD) | F115: Price (AUD) | G115: C. Rate | H115: Per/Unit (AED) | I115: Total Price (AED)
B116: 45714 | C116: Mac Book 4 Saleem Hayat | D116: 1 | E116: 2349 | F116: =E116*D116 -> 2349 | G116: 2.35 | H116: =E116*G116 -> 5520.15 | I116: =H116*D116 -> 5520.15 | J116: =J115+I116 -> 5520.15
B117: 45714 | C117: Mac Book 4 Noaman Mughal | D117: 1 | E117: 2349 | F117: =E117*D117 -> 2349 | G117: 2.35 | H117: =E117*G117 -> 5520.15 | I117: =H117*D117 -> 5520.15 | J117: =J116+I117 -> 11040.3
B118: 45714 | C118: Mac Book 4 Anwar Ali | D118: 1 | E118: 2349 | F118: =E118*D118 -> 2349 | G118: 2.35 | H118: =E118*G118 -> 5520.15 | I118: =H118*D118 -> 5520.15 | J118: =J117+I118 -> 16560.45
B119: 45714 | C119: Mac Book 4 Atiya Hayat | D119: 1 | E119: 2349 | F119: =E119*D119 -> 2349 | G119: 2.35 | H119: =E119*G119 -> 5520.15 | I119: =H119*D119 -> 5520.15 | J119: =J118+I119 -> 22080.6
B120: 45714 | C120: Mac Book 4 Waheed NAB CR Card | D120: 1 | E120: 2349 | F120: =E120*D120 -> 2349 | G120: 2.35 | H120: =E120*G120 -> 5520.15 | I120: =H120*D120 -> 5520.15 | J120: =J119+I120 -> 27600.75
B121: 45714 | C121: Mac Book 4 Waheed NAB CR Card | D121: 1 | E121: 2349 | F121: =E121*D121 -> 2349 | G121: 2.35 | H121: =E121*G121 -> 5520.15 | I121: =H121*D121 -> 5520.15 | J121: =J120+I121 -> 33120.9
B122: 45714 | C122: Mac Book 4 Waheed NAB CR Card | D122: 1 | E122: 2349 | F122: =E122*D122 -> 2349 | G122: 2.35 | H122: =E122*G122 -> 5520.15 | I122: =H122*D122 -> 5520.15 | J122: =J121+I122 -> 38641.05
A126: GST | B126: Australia
...

Sheet Stock_Transactions
A1: Date | B1: Product Name | C1: Transaction Type | D1: Quantity | E1: Status
A2: 20/02/2025 | B2: STARLINK V4 | C2: Opening | D2: 220
A3: 20/02/2025 | B3: STARLINK MINI | C3: Opening | D3: 300 | N3: STARLINK V4
A4: 20/02/2025 | B4: STRALINK INSTAX CAMERA | C4: Opening | D4: 0 | F4: sell to waheed bhai | N4: STARLINK MINI
A5: 20/02/2025 | B5: JBL CHARGE 5 | C5: Opening | D5: 205 | F5: 130 purchase cancel | N5: STRALINK INSTAX CAMERA
A6: 20/02/2025 | B6: ESSENTIAL FLIP | C6: Opening | D6: 10 | N6: JBL CHARGE 5
A7: 20/02/2025 | B7: CHROME CAST | C7: Opening | D7: 309 | N7: ESSENTIAL FLIP
A8: 20/02/2025 | B8: PS5 | C8: Opening | D8: 15 | N8: CHROME CAST | O8: DONE
A9: 20/02/2025 | B9: APPLE I MAC | C9: Opening | D9: 7 | N9: PS5 | O9: DONE
A10: 20/02/2025 | B10: MACBOOK M4 | C10: Opening | D10: 4 | N10: APPLE I MAC | O10: DONE
A11: 20/02/2025 | B11: BREVILLE COFFEE MACHINE | C11: Opening | D11: 2 | N11: MACBOOK M4 | O11: DONE
A12: 20/02/2025 | B12: DELONGI COFFEE MACHINE | C12: Opening | D12: 2 | N12: AIRPODS | O12: DONE
A13: 20/02/2025 | B13: DYSON | C13: Opening | D13: 2 | N13: BREVILLE COFFEE MACHINE | O13: DONE
A14: 20/02/2025 | B14: MACBOOK M3 | C14: Opening | D14: 2 | N14: DELONGI COFFEE MACHINE | O14: DONE
A15: 20/02/2025 | B15: STARLINK HIGH.P KIT | C15: Opening | D15: 21 | N15: DYSON | O15: DONE
A16: 20/02/2025 | B16: INSTAX WIDE 400 | C16: Opening | D16: 5 | N16: MACBOOK M3 | O16: DONE
A17: 20/02/2025 | B17: APPLE WATCH ULTRA | C17: Opening | D17: 1 | N17: STARLINK HIGH.P KIT | O17: DONE
A18: 20/02/2025 | B18: PRINTER | C18: Opening | D18: 1 | N18: INSTAX WIDE 400 | O18: DONE
A19: 20/02/2025 | B19: DJI MAVIC PRO 3 DRONE | C19: Opening | D19: 2 | N19: INSTAX MINI EVO | O19: DONE
N20: INSTAX Li PLAY | O20: DONE
N21: INSTAX MINI 40 | O21: DONE
A22: 45709 | B22: MACBOOK M4 | C22: Purchase | D22: 9 | N22: INSTAX MINI 99 | O22: DONE
A23: 45709 | B23: AIRPODS | C23: Purchase | D23: 9 | N23: APPLE WATCH ULTRA | O23: DONE
A24: 45709 | B24: INSTAX WIDE 400 | C24: Purchase | D24: 10 | N24: PRINTER | O24: DONE
A25: 45709 | B25: INSTAX MINI EVO | C25: Purchase | D25: 1 | N25: DJI MAVIC PRO 3 DRONE | O25: DONE
A26: 45709 | B26: INSTAX Li PLAY | C26: Purchase | D26: 1
A27: 45709 | B27: INSTAX MINI 40 | C27: Purchase | D27: 1 | N27: Meta Quest 3 512
A28: 45709 | B28: INSTAX MINI 99 | C28: Purchase | D28: 1 | N28: iPhone16 Pro Max 256
N29: iPad Pro 11 256 Cellular Unlock
A30: 45711 | B30: MACBOOK M4 | C30: Purchase | D30: 13
A31: 45711 | B31: MACBOOK M4 | C31: Purchase | D31: 2 | N31: iPad Pro 11 256 Wifi Only
A32: 45711 | B32: AIRPODS | C32: Purchase | D32: 13 | N32: iPad Air 13 128 Wifi Only
A33: 45711 | B33: AIRPODS | C33: Purchase | D33: 2 | N33: iPad Air 13 256 Wifi Only
A34: 45711 | B34: APPLE I MAC | C34: Purchase | D34: 1
A35: 45711 | B35: AIRPODS | C35: Purchase (for Imacs) | D35: 3 | N35: iPhone16 Pro 256
N36: iPhone16 Pro 128
N37: Ps5 Controller Dual sense
N38: Beats Fit Pro
N39: Beats Studio Buds
A40: 45713 | B40: PS5 | C40: Sale | D40: -15 | N40: iPhone 15 Pro 256
A41: 45713 | B41: JBL CHARGE 5 | C41: Sale | D41: -17 | N41: iPhone 16 128
A42: 45713 | B42: STARLINK V4 | C42: Sale | D42: -5 | N42: iPhone 14 Pro Max 128
A43: 45713 | B43: STARLINK HIGH.P KIT | C43: Sale | D43: -5 | N43: Samsung Galaxy S25 Plus 256
A44: 45713 | B44: STARLINK V4 | C44: Sale | D44: -2 | N44: Macbook Pro 16/512
A45: 45713 | B45: STARLINK V4 | C45: Sale | D45: -1 | N45: Macbook Air 24/512 GB
N46: Macbook Air M4 13 inch
A47: 45714 | B47: STARLINK V4 | C47: Sale | D47: -1 | N47: INSTAX MINI CAMERA
A48: 45714 | B48: STARLINK MINI | C48: Sale | D48: -10 | N48: INSTAX MINI 99 BUNDEL
N49: APPLE AIR TAG 1 PACK
A50: 45715 | B50: STARLINK V4 | C50: Sale | D50: -10 | E50: 0.14236111 | N50: INSTAX MINI 12
A51: 45715 | B51: APPLE I MAC | C51: Sale | D51: -4 | N51: NINJA BLAST BLENDER
A52: 45715 | B52: APPLE I MAC | C52: Sale | D52: -1 | N52: Macbook Pro 16/1TB
A53: 45715 | B53: DJI MAVIC PRO 3 DRONE | C53: Sale | D53: -2 | N53: NORTON ANTIVIRUS
A54: 45715 | B54: STARLINK V4 | C54: Sale | D54: -10 | E54: 0.38402778 | N54: Macbook Air 15 24/512 GB
N55: PS5 Hard Drive
A56: 45715 | B56: STARLINK V4 | C56: Sale | D56: -10 | N56: RAYBAN GLASSES
A57: 45715 | B57: STARLINK V4 | C57: Sale | D57: -6 | N57: SONY BUDS
A58: 45715 | B58: STARLINK V4 | C58: Sale | D58: -14 | N58: PLAY STATION PORTAL
N59: PS5 SSD 2TB
A60: 45716 | B60: STARLINK MINI | C60: Sale | D60: -3 | N60: APPLE AIRPODS PRO
A61: 45716 | B61: STARLINK V4 | C61: Sale | D61: -8 | N61: Macbook Air 15 M3 24/512 GB
A62: 45716 | B62: STARLINK V4 | C62: Sale | D62: -2 | N62: Meta Quest 3s 128
A63: 45716 | B63: STARLINK V4 | C63: Sale | D63: -50 | N63: Meta Quest 3s 256
A64: 45716 | B64: STARLINK MINI | C64: Sale | D64: -50 | N64: Dragon Age Game CD
A65: 45716 | B65: STARLINK V4 | C65: Sale | D65: -30 | N65: DJI OSMO POCKET 3
A66: 45716 | B66: STARLINK V4 | C66: Sale | D66: -1 | N66: INSTAX FLIM 20 PACK
N67: Macbook Air 13 M3 24/512 GB
A68: 45717 | B68: STARLINK V4 | C68: Sale | D68: -3 | N68: DJI MAVIC PRO RC
A69: 45717 | B69: STARLINK V4 | C69: Sale | D69: -7 | N69: DJI MAVIC PRO RC COMBO
A70: 45717 | B70: STARLINK V4 | C70: Sale | D70: -10 | N70: IPHONE 13 128
A71: 45717 | B71: STARLINK V4 | C71: Sale | D71: -15 | N71: IPHONE 16 128
A72: 45717 | B72: STARLINK V4 | C72: Sale | D72: -7 | N72: DJI OSMO Action 5 pro
N73: DJI OSMO Mobile 7 P
A74: 45717 | B74: MACBOOK M4 | C74: Purchase | D74: 20
A75: 45717 | B75: AIRPODS | C75: Purchase | D75: 20 | N75: INSTAX MINI LINK 3
N76: INSTAX FLIM 10 PACK
N77: IPHONE CABLE
A78: 45718 | B78: STARLINK MINI | C78: Sale | D78: -5 | N78: GOOGLE TV STREAMER
N79: CANON CAMERA
A80: 45719 | B80: STARLINK V4 | C80: Sale | D80: -8 | N80: DJI OSMO POCKET 3 COMBO
A81: 45719 | B81: AIRPODS | C81: Sale | D81: -21 | N81: CANON GX70
A82: 45719 | B82: CHROME CAST | C82: Sale | D82: -100 | N82: CANON SX740
N83: DJI MIC 2
N84: DJI MAVIC 4 PRO COMBO
A85: 45719 | B85: Meta Quest 3 512 | C85: Purchase (Owais Houston) in Dubai | D85: 13 | N85: VR
A86: 45719 | B86: iPhone16 Pro Max 256 | C86: Purchase (Owais Houston) in Dubai | D86: 20 | N86: BEATS PRO 2
A87: 45719 | B87: iPad Pro 11 256 Cellular Unlock | C87: Purchase (Owais Houston) in Dubai | D87: 4 | N87: Meta Quest 3 256 GB
A88: 45719 | B88: AIRPODS | C88: Purchase (Owais Houston) in Dubai | D88: 4 | N88: PS5 Pro
A89: 45719 | B89: iPad Pro 11 256 Wifi Only | C89: Purchase (Owais Houston) in Dubai | D89: 14 | N89: PS5 Disc
A90: 45719 | B90: iPad Air 13 128 Wifi Only | C90: Purchase (Owais Houston) in Dubai | D90: 2 | N90: PS5 Digital
A91: 45719 | B91: iPad Air 13 256 Wifi Only | C91: Purchase (Owais Houston) in Dubai | D91: 1 | E91: entry
A93: 45722 | B93: MACBOOK M4 | C93: Sale | D93: -23
A94: 45722 | B94: iPad Pro 11 256 Wifi Only | C94: Sale | D94: -13
A95: 45722 | B95: iPad Pro 11 256 Cellular Unlock | C95: Sale | D95: -4
A96: 45722 | B96: iPhone16 Pro Max 256 | C96: Sale | D96: -19 | E96: entry
A97: 45722 | B97: STARLINK MINI | C97: Sale | D97: -50 | E97: entry
A99: 45723 | B99: STARLINK MINI | C99: Sale | D99: -44
A100: 45723 | B100: BREVILLE COFFEE MACHINE | C100: Sale | D100: -1 | E100: entry
A101: 45723 | B101: CHROME CAST | C101: Sale | D101: -20 | E101: entry
A102: 45723 | B102: CHROME CAST | C102: Sale | D102: -102 | E102: entry
...

Sheet Product_Master
F1: Australia | H1: NewZeland | I1: Stock in Dubai
A2: S.No | B2: Product Name) | C2: Total Purchased | D2: Total Sold | E2: Total in Stock | F2: (Currently Present) | G2: Pending | H2: Pending | I2: (Currently Present) | J2: In Shipping | K2: Pending in Dubai | N2: Currently in shipping
A3: 1 | B3: STARLINK V4 | C3: =SUMIFS(Stock_Transactions!D:D, Stock_Transactions!B:B, B3, Stock_Transactions!D:D, ">0") -> 6023 | D3: =SUMIFS(Stock_Transactions!D:D, Stock_Transactions!B:B, B3, Stock_Transactions!D:D, "<0") * -1 -> 6076 | E3: =C3-D3 -> -53 | F3: =E3-G3-H3-I3-J3 -> -58 | G3: =SUMIF(Pending_Stock!C:C, B3, Pending_Stock!F:F) -> 0 | H3: =SUMIF(Pending_Stock!I:I, B3, Pending_Stock!L:L) -> 0 | I3: =SUMIF(ShipToDubai!C:C, B3, ShipToDubai!F:F) - (SUMIFS(Stock_Transactions!D:D, Stock_Transactions!B:B, B3, Stock_Transactions!D:D, "<0") * -1) -> 5 | J3: =SUMIF(ShipToDubai!C:C, B3, ShipToDubai!G:G) -> 0 | L3: 2 problem | N3: "=SUMIF(ShipToDubai!C:C, A3, ShipToDubai!G:G)"
A4: =A3+1 -> 2 | B4: STARLINK MINI | C4: =SUMIFS(Stock_Transactions!D:D, Stock_Transactions!B:B, B4, Stock_Transactions!D:D, ">0") -> 1204 | D4: =SUMIFS(Stock_Transactions!D:D, Stock_Transactions!B:B, B4, Stock_Transactions!D:D, "<0") * -1 -> 1203 | E4: =C4-D4 -> 1 | F4: =E4-G4-H4-I4-J4 -> 0 | G4: =SUMIF(Pending_Stock!C:C, B4, Pending_Stock!F:F) -> 0 | H4: =SUMIF(Pending_Stock!I:I, B4, Pending_Stock!L:L) -> 0 | I4: =SUMIF(ShipToDubai!C:C, B4, ShipToDubai!F:F) - (SUMIFS(Stock_Transactions!D:D, Stock_Transactions!B:B, B4, Stock_Transactions!D:D, "<0") * -1) -> 1 | J4: =SUMIF(ShipToDubai!C:C, B4, ShipToDubai!G:G) -> 0 | L4: 30ok
A5: =A4+1 -> 3 | B5: AIRPODS | C5: =SUMIFS(Stock_Transactions!D:D, Stock_Transactions!B:B, B5, Stock_Transactions!D:D, ">0") -> 138 | D5: =SUMIFS(Stock_Transactions!D:D, Stock_Transactions!B:B, B5, Stock_Transactions!D:D, "<0") * -1 -> 138 | E5: =C5-D5 -> 0 | F5: =E5-G5-H5-I5-J5 -> 0 | G5: =SUMIF(Pending_Stock!C:C, B5, Pending_Stock!F:F) -> 0 | H5: =SUMIF(Pending_Stock!I:I, B5, Pending_Stock!L:L) -> 0 | I5: =SUMIF(ShipToDubai!C:C, B5, ShipToDubai!F:F) - (SUMIFS(Stock_Transactions!D:D, Stock_Transactions!B:B, B5, Stock_Transactions!D:D, "<0") * -1) -> 0 | J5: =SUMIF(ShipToDubai!C:C, B5, ShipToDubai!G:G) -> 0 | N5: Pending in Newzelnd
A6: =A5+1 -> 4 | B6: JBL CHARGE 5 | C6: =SUMIFS(Stock_Transactions!D:D, Stock_Transactions!B:B, B6, Stock_Transactions!D:D, ">0") -> 205 | D6: =SUMIFS(Stock_Transactions!D:D, Stock_Transactions!B:B, B6, Stock_Transactions!D:D, "<0") * -1 -> 205 | E6: =C6-D6 -> 0 | F6: =E6-G6-H6-I6-J6 -> 0 | G6: =SUMIF(Pending_Stock!C:C, B6, Pending_Stock!F:F) -> 0 | H6: =SUMIF(Pending_Stock!I:I, B6, Pending_Stock!L:L) -> 0 | I6: =SUMIF(ShipToDubai!C:C, B6, ShipToDubai!F:F) - (SUMIFS(Stock_Transactions!D:D, Stock_Transactions!B:B, B6, Stock_Transactions!D:D, "<0") * -1) -> 0 | J6: =SUMIF(ShipToDubai!C:C, B6, ShipToDubai!G:G) -> 0 | N6: "=SUMIF(Pending_Stock!I:I, A3, Pending_Stock!L:L)"
A7: =A6+1 -> 5 | B7: ESSENTIAL FLIP | C7: =SUMIFS(Stock_Transactions!D:D, Stock_Transactions!B:B, B7, Stock_Transactions!D:D, ">0") -> 10 | D7: =SUMIFS(Stock_Transactions!D:D, Stock_Transactions!B:B, B7, Stock_Transactions!D:D, "<0") * -1 -> 10 | E7: =C7-D7 -> 0 | F7: =E7-G7-H7-I7-J7 -> 0 | G7: =SUMIF(Pending_Stock!C:C, B7, Pending_Stock!F:F) -> 0 | H7: =SUMIF(Pending_Stock!I:I, B7, Pending_Stock!L:L) -> 0 | I7: =SUMIF(ShipToDubai!C:C, B7, ShipToDubai!F:F) - (SUMIFS(Stock_Transactions!D:D, Stock_Transactions!B:B, B7, Stock_Transactions!D:D, "<0") * -1) -> 0 | J7: =SUMIF(ShipToDubai!C:C, B7, ShipToDubai!G:G) -> 0 | L7: ok
A8: =A7+1 -> 6 | B8: CHROME CAST | C8: =SUMIFS(Stock_Transactions!D:D, Stock_Transactions!B:B, B8, Stock_Transactions!D:D, ">0") -> 559 | D8: =SUMIFS(Stock_Transactions!D:D, Stock_Transactions!B:B, B8, Stock_Transactions!D:D, "<0") * -1 -> 559 | E8: =C8-D8 -> 0 | F8: =E8-G8-H8-I8-J8 -> 0 | G8: =SUMIF(Pending_Stock!C:C, B8, Pending_Stock!F:F) -> 0 | H8: =SUMIF(Pending_Stock!I:I, B8, Pending_Stock!L:L) -> 0 | I8: =SUMIF(ShipToDubai!C:C, B8, ShipToDubai!F:F) - (SUMIFS(Stock_Transactions!D:D, Stock_Transactions!B:B, B8, Stock_Transactions!D:D, "<0") * -1) -> 0 | J8: =SUMIF(ShipToDubai!C:C, B8, ShipToDubai!G:G) -> 0 | L8: ok | N8: Pending in Australia
A9: =A8+1 -> 7 | B9: PS5 | C9: =SUMIFS(Stock_Transactions!D:D, Stock_Transactions!B:B, B9, Stock_Transactions!D:D, ">0") -> 438 | D9: =SUMIFS(Stock_Transactions!D:D, Stock_Transactions!B:B, B9, Stock_Transactions!D:D, "<0") * -1 -> 437 | E9: =C9-D9 -> 1 | F9: =E9-G9-H9-I9-J9 -> 1 | G9: =SUMIF(Pending_Stock!C:C, B9, Pending_Stock!F:F) -> 0 | H9: =SUMIF(Pending_Stock!I:I, B9, Pending_Stock!L:L) -> 0 | I9: =SUMIF(ShipToDubai!C:C, B9, ShipToDubai!F:F) - (SUMIFS(Stock_Transactions!D:D, Stock_Transactions!B:B, B9, Stock_Transactions!D:D, "<0") * -1) -> 0 | J9: =SUMIF(ShipToDubai!C:C, B9, ShipToDubai!G:G) -> 0 | N9: "=SUMIF(Pending_Stock!C:C, A3, Pending_Stock!F:F)"
A10: =A9+1 -> 8 | B10: APPLE I MAC | C10: =SUMIFS(Stock_Transactions!D:D, Stock_Transactions!B:B, B10, Stock_Transactions!D:D, ">0") -> 11 | D10: =SUMIFS(Stock_Transactions!D:D, Stock_Transactions!B:B, B10, Stock_Transactions!D:D, "<0") * -1 -> 10 | E10: =C10-D10 -> 1 | F10: =E10-G10-H10-I10-J10 -> 0 | G10: =SUMIF(Pending_Stock!C:C, B10, Pending_Stock!F:F) -> 0 | H10: =SUMIF(Pending_Stock!I:I, B10, Pending_Stock!L:L) -> 0 | I10: =SUMIF(ShipToDubai!C:C, B10, ShipToDubai!F:F) - (SUMIFS(Stock_Transactions!D:D, Stock_Transactions!B:B, B10, Stock_Transactions!D:D, "<0") * -1) -> 1 | J10: =SUMIF(ShipToDubai!C:C, B10, ShipToDubai!G:G) -> 0
A11: =A10+1 -> 9 | B11: MACBOOK M4 | C11: =SUMIFS(Stock_Transactions!D:D, Stock_Transactions!B:B, B11, Stock_Transactions!D:D, ">0") -> 92 | D11: =SUMIFS(Stock_Transactions!D:D, Stock_Transactions!B:B, B11, Stock_Transactions!D:D, "<0") * -1 -> 92 | E11: =C11-D11 -> 0 | F11: =E11-G11-H11-I11-J11 -> 0 | G11: =SUMIF(Pending_Stock!C:C, B11, Pending_Stock!F:F) -> 0 | H11: =SUMIF(Pending_Stock!I:I, B11, Pending_Stock!L:L) -> 0 | I11: =SUMIF(ShipToDubai!C:C, B11, ShipToDubai!F:F) - (SUMIFS(Stock_Transactions!D:D, Stock_Transactions!B:B, B11, Stock_Transactions!D:D, "<0") * -1) -> 0 | J11: =SUMIF(ShipToDubai!C:C, B11, ShipToDubai!G:G) -> 0
A12: =A11+1 -> 10 | B12: Macbook Pro 16/512 | C12: =SUMIFS(Stock_Transactions!D:D, Stock_Transactions!B:B, B12, Stock_Transactions!D:D, ">0") -> 6 | D12: =SUMIFS(Stock_Transactions!D:D, Stock_Transactions!B:B, B12, Stock_Transactions!D:D, "<0") * -1 -> 6 | E12: =C12-D12 -> 0 | F12: =E12-G12-H12-I12-J12 -> 0 | G12: =SUMIF(Pending_Stock!C:C, B12, Pending_Stock!F:F) -> 0 | H12: =SUMIF(Pending_Stock!I:I, B12, Pending_Stock!L:L) -> 0 | I12: =SUMIF(ShipToDubai!C:C, B12, ShipToDubai!F:F) - (SUMIFS(Stock_Transactions!D:D, Stock_Transactions!B:B, B12, Stock_Transactions!D:D, "<0") * -1) -> 0 | J12: =SUMIF(ShipToDubai!C:C, B12, ShipToDubai!G:G) -> 0 | N12: Delivered to Dubai
A13: =A12+1 -> 11 | B13: BREVILLE COFFEE MACHINE | C13: =SUMIFS(Stock_Transactions!D:D, Stock_Transactions!B:B, B13, Stock_Transactions!D:D, ">0") -> 2 | D13: =SUMIFS(Stock_Transactions!D:D, Stock_Transactions!B:B, B13, Stock_Transactions!D:D, "<0") * -1 -> 2 | E13: =C13-D13 -> 0 | F13: =E13-G13-H13-I13-J13 -> 0 | G13: =SUMIF(Pending_Stock!C:C, B13, Pending_Stock!F:F) -> 0 | H13: =SUMIF(Pending_Stock!I:I, B13, Pending_Stock!L:L) -> 0 | I13: =SUMIF(ShipToDubai!C:C, B13, ShipToDubai!F:F) - (SUMIFS(Stock_Transactions!D:D, Stock_Transactions!B:B, B13, Stock_Transactions!D:D, "<0") * -1) -> 0 | J13: =SUMIF(ShipToDubai!C:C, B13, ShipToDubai!G:G) -> 0 | N13: "=SUMIF(ShipToDubai!C:C, A3, ShipToDubai!F:F)"
A14: =A13+1 -> 12 | B14: DELONGI COFFEE MACHINE | C14: =SUMIFS(Stock_Transactions!D:D, Stock_Transactions!B:B, B14, Stock_Transactions!D:D, ">0") -> 2 | D14: =SUMIFS(Stock_Transactions!D:D, Stock_Transactions!B:B, B14, Stock_Transactions!D:D, "<0") * -1 -> 2 | E14: =C14-D14 -> 0 | F14: =E14-G14-H14-I14-J14 -> 0 | G14: =SUMIF(Pending_Stock!C:C, B14, Pending_Stock!F:F) -> 0 | H14: =SUMIF(Pending_Stock!I:I, B14, Pending_Stock!L:L) -> 0 | I14: =SUMIF(ShipToDubai!C:C, B14, ShipToDubai!F:F) - (SUMIFS(Stock_Transactions!D:D, Stock_Transactions!B:B, B14, Stock_Transactions!D:D, "<0") * -1) -> 0 | J14: =SUMIF(ShipToDubai!C:C, B14, ShipToDubai!G:G) -> 0
A15: =A14+1 -> 13 | B15: DYSON | C15: =SUMIFS(Stock_Transactions!D:D, Stock_Transactions!B:B, B15, Stock_Transactions!D:D, ">0") -> 2 | D15: =SUMIFS(Stock_Transactions!D:D, Stock_Transactions!B:B, B15, Stock_Transactions!D:D, "<0") * -1 -> 2 | E15: =C15-D15 -> 0 | F15: =E15-G15-H15-I15-J15 -> 0 | G15: =SUMIF(Pending_Stock!C:C, B15, Pending_Stock!F:F) -> 0 | H15: =SUMIF(Pending_Stock!I:I, B15, Pending_Stock!L:L) -> 0 | I15: =SUMIF(ShipToDubai!C:C, B15, ShipToDubai!F:F) - (SUMIFS(Stock_Transactions!D:D, Stock_Transactions!B:B, B15, Stock_Transactions!D:D, "<0") * -1) -> 0 | J15: =SUMIF(ShipToDubai!C:C, B15, ShipToDubai!G:G) -> 0 | L15: ok | N15: Delivered to Dubai minus Sold in Dubai
A16: =A15+1 -> 14 | B16: MACBOOK M3 | C16: =SUMIFS(Stock_Transactions!D:D, Stock_Transactions!B:B, B16, Stock_Transactions!D:D, ">0") -> 2 | D16: =SUMIFS(Stock_Transactions!D:D, Stock_Transactions!B:B, B16, Stock_Transactions!D:D, "<0") * -1 -> 2 | E16: =C16-D16 -> 0 | F16: =E16-G16-H16-I16-J16 -> 0 | G16: =SUMIF(Pending_Stock!C:C, B16, Pending_Stock!F:F) -> 0 | H16: =SUMIF(Pending_Stock!I:I, B16, Pending_Stock!L:L) -> 0 | I16: =SUMIF(ShipToDubai!C:C, B16, ShipToDubai!F:F) - (SUMIFS(Stock_Transactions!D:D, Stock_Transactions!B:B, B16, Stock_Transactions!D:D, "<0") * -1) -> 0 | J16: =SUMIF(ShipToDubai!C:C, B16, ShipToDubai!G:G) -> 0 | L16: ok | N16: "=SUMIF(ShipToDubai!C:C, A3, ShipToDubai!F:F) - (SUMIFS(Stock_Transactions!D:D, Stock_Transactions!B:B, A3, Stock_Transactions!D:D, "<0") * -1)"
A17: =A16+1 -> 15 | B17: STARLINK HIGH.P KIT | C17: =SUMIFS(Stock_Transactions!D:D, Stock_Transactions!B:B, B17, Stock_Transactions!D:D, ">0") -> 23 | D17: =SUMIFS(Stock_Transactions!D:D, Stock_Transactions!B:B, B17, Stock_Transactions!D:D, "<0") * -1 -> 23 | E17: =C17-D17 -> 0 | F17: =E17-G17-H17-I17-J17 -> 0 | G17: =SUMIF(Pending_Stock!C:C, B17, Pending_Stock!F:F) -> 0 | H17: =SUMIF(Pending_Stock!I:I, B17, Pending_Stock!L:L) -> 0 | I17: =SUMIF(ShipToDubai!C:C, B17, ShipToDubai!F:F) - (SUMIFS(Stock_Transactions!D:D, Stock_Transactions!B:B, B17, Stock_Transactions!D:D, "<0") * -1) -> 0 | J17: =SUMIF(ShipToDubai!C:C, B17, ShipToDubai!G:G) -> 0 | L17: ok
A18: =A17+1 -> 16 | B18: INSTAX WIDE 400 | C18: =SUMIFS(Stock_Transactions!D:D, Stock_Transactions!B:B, B18, Stock_Transactions!D:D, ">0") -> 117 | D18: =SUMIFS(Stock_Transactions!D:D, Stock_Transactions!B:B, B18, Stock_Transactions!D:D, "<0") * -1 -> 117 | E18: =C18-D18 -> 0 | F18: =E18-G18-H18-I18-J18 -> 0 | G18: =SUMIF(Pending_Stock!C:C, B18, Pending_Stock!F:F) -> 0 | H18: =SUMIF(Pending_Stock!I:I, B18, Pending_Stock!L:L) -> 0 | I18: =SUMIF(ShipToDubai!C:C, B18, ShipToDubai!F:F) - (SUMIFS(Stock_Transactions!D:D, Stock_Transactions!B:B, B18, Stock_Transactions!D:D, "<0") * -1) -> 0 | J18: =SUMIF(ShipToDubai!C:C, B18, ShipToDubai!G:G) -> 0 | L18: ok
A19: =A18+1 -> 17 | B19: INSTAX MINI EVO | C19: =SUMIFS(Stock_Transactions!D:D, Stock_Transactions!B:B, B19, Stock_Transactions!D:D, ">0") -> 843 | D19: =SUMIFS(Stock_Transactions!D:D, Stock_Transactions!B:B, B19, Stock_Transactions!D:D, "<0") * -1 -> 843 | E19: =C19-D19 -> 0 | F19: =E19-G19-H19-I19-J19 -> 0 | G19: =SUMIF(Pending_Stock!C:C, B19, Pending_Stock!F:F) -> 0 | H19: =SUMIF(Pending_Stock!I:I, B19, Pending_Stock!L:L) -> 0 | I19: =SUMIF(ShipToDubai!C:C, B19, ShipToDubai!F:F) - (SUMIFS(Stock_Transactions!D:D, Stock_Transactions!B:B, B19, Stock_Transactions!D:D, "<0") * -1) -> 0 | J19: =SUMIF(ShipToDubai!C:C, B19, ShipToDubai!G:G) -> 0 | N19: Total purchase quantity of a particular Product
A20: =A19+1 -> 18 | B20: INSTAX MINI 12 | C20: =SUMIFS(Stock_Transactions!D:D, Stock_Transactions!B:B, B20, Stock_Transactions!D:D, ">0") -> 57 | D20: =SUMIFS(Stock_Transactions!D:D, Stock_Transactions!B:B, B20, Stock_Transactions!D:D, "<0") * -1 -> 57 | E20: =C20-D20 -> 0 | F20: =E20-G20-H20-I20-J20 -> 0 | G20: =SUMIF(Pending_Stock!C:C, B20, Pending_Stock!F:F) -> 0 | H20: =SUMIF(Pending_Stock!I:I, B20, Pending_Stock!L:L) -> 0 | I20: =SUMIF(ShipToDubai!C:C, B20, ShipToDubai!F:F) - (SUMIFS(Stock_Transactions!D:D, Stock_Transactions!B:B, B20, Stock_Transactions!D:D, "<0") * -1) -> 0 | J20: =SUMIF(ShipToDubai!C:C, B20, ShipToDubai!G:G) -> 0 | L20: ok | N20: "=SUMIFS(Stock_Transactions!D:D, Stock_Transactions!B:B, A3, Stock_Transactions!D:D, ">0")"
A21: =A20+1 -> 19 | B21: INSTAX MINI 99 BUNDEL | C21: =SUMIFS(Stock_Transactions!D:D, Stock_Transactions!B:B, B21, Stock_Transactions!D:D, ">0") -> 30 | D21: =SUMIFS(Stock_Transactions!D:D, Stock_Transactions!B:B, B21, Stock_Transactions!D:D, "<0") * -1 -> 30 | E21: =C21-D21 -> 0 | F21: =E21-G21-H21-I21-J21 -> 0 | G21: =SUMIF(Pending_Stock!C:C, B21, Pending_Stock!F:F) -> 0 | H21: =SUMIF(Pending_Stock!I:I, B21, Pending_Stock!L:L) -> 0 | I21: =SUMIF(ShipToDubai!C:C, B21, ShipToDubai!F:F) - (SUMIFS(Stock_Transactions!D:D, Stock_Transactions!B:B, B21, Stock_Transactions!D:D, "<0") * -1) -> 0 | J21: =SUMIF(ShipToDubai!C:C, B21, ShipToDubai!G:G) -> 0
A22: =A21+1 -> 20 | B22: INSTAX MINI 99 | C22: =SUMIFS(Stock_Transactions!D:D, Stock_Transactions!B:B, B22, Stock_Transactions!D:D, ">0") -> 3 | D22: =SUMIFS(Stock_Transactions!D:D, Stock_Transactions!B:B, B22, Stock_Transactions!D:D, "<0") * -1 -> 3 | E22: =C22-D22 -> 0 | F22: =E22-G22-H22-I22-J22 -> 0 | G22: =SUMIF(Pending_Stock!C:C, B22, Pending_Stock!F:F) -> 0 | H22: =SUMIF(Pending_Stock!I:I, B22, Pending_Stock!L:L) -> 0 | I22: =SUMIF(ShipToDubai!C:C, B22, ShipToDubai!F:F) - (SUMIFS(Stock_Transactions!D:D, Stock_Transactions!B:B, B22, Stock_Transactions!D:D, "<0") * -1) -> 0 | J22: =SUMIF(ShipToDubai!C:C, B22, ShipToDubai!G:G) -> 0 | N22: Total Sale quantity of a particular Product
A23: =A22+1 -> 21 | B23: APPLE WATCH ULTRA | C23: =SUMIFS(Stock_Transactions!D:D, Stock_Transactions!B:B, B23, Stock_Transactions!D:D, ">0") -> 1 | D23: =SUMIFS(Stock_Transactions!D:D, Stock_Transactions!B:B, B23, Stock_Transactions!D:D, "<0") * -1 -> 1 | E23: =C23-D23 -> 0 | F23: =E23-G23-H23-I23-J23 -> 0 | G23: =SUMIF(Pending_Stock!C:C, B23, Pending_Stock!F:F) -> 0 | H23: =SUMIF(Pending_Stock!I:I, B23, Pending_Stock!L:L) -> 0 | I23: =SUMIF(ShipToDubai!C:C, B23, ShipToDubai!F:F) - (SUMIFS(Stock_Transactions!D:D, Stock_Transactions!B:B, B23, Stock_Transactions!D:D, "<0") * -1) -> 0 | J23: =SUMIF(ShipToDubai!C:C, B23, ShipToDubai!G:G) -> 0 | N23: "=SUMIFS(Stock_Transactions!D:D, Stock_Transactions!B:B, A3, Stock_Transactions!D:D, "<0") * -1"
A24: =A23+1 -> 22 | B24: PRINTER | C24: =SUMIFS(Stock_Transactions!D:D, Stock_Transactions!B:B, B24, Stock_Transactions!D:D, ">0") -> 1 | D24: =SUMIFS(Stock_Transactions!D:D, Stock_Transactions!B:B, B24, Stock_Transactions!D:D, "<0") * -1 -> 1 | E24: =C24-D24 -> 0 | F24: =E24-G24-H24-I24-J24 -> 0 | G24: =SUMIF(Pending_Stock!C:C, B24, Pending_Stock!F:F) -> 0 | H24: =SUMIF(Pending_Stock!I:I, B24, Pending_Stock!L:L) -> 0 | I24: =SUMIF(ShipToDubai!C:C, B24, ShipToDubai!F:F) - (SUMIFS(Stock_Transactions!D:D, Stock_Transactions!B:B, B24, Stock_Transactions!D:D, "<0") * -1) -> 0 | J24: =SUMIF(ShipToDubai!C:C, B24, ShipToDubai!G:G) -> 0 | L24: ok
A25: =A24+1 -> 23 | B25: DJI MAVIC PRO 3 DRONE | C25: =SUMIFS(Stock_Transactions!D:D, Stock_Transactions!B:B, B25, Stock_Transactions!D:D, ">0") -> 2 | D25: =SUMIFS(Stock_Transactions!D:D, Stock_Transactions!B:B, B25, Stock_Transactions!D:D, "<0") * -1 -> 2 | E25: =C25-D25 -> 0 | F25: =E25-G25-H25-I25-J25 -> 0 | G25: =SUMIF(Pending_Stock!C:C, B25, Pending_Stock!F:F) -> 0 | H25: =SUMIF(Pending_Stock!I:I, B25, Pending_Stock!L:L) -> 0 | I25: =SUMIF(ShipToDubai!C:C, B25, ShipToDubai!F:F) - (SUMIFS(Stock_Transactions!D:D, Stock_Transactions!B:B, B25, Stock_Transactions!D:D, "<0") * -1) -> 0 | J25: =SUMIF(ShipToDubai!C:C, B25, ShipToDubai!G:G) -> 0 | N25: Total Quantity of a product(total purchase - total sale)
A26: =A25+1 -> 24 | B26: Meta Quest 3 512 | C26: =SUMIFS(Stock_Transactions!D:D, Stock_Transactions!B:B, B26, Stock_Transactions!D:D, ">0") -> 389 | D26: =SUMIFS(Stock_Transactions!D:D, Stock_Transactions!B:B, B26, Stock_Transactions!D:D, "<0") * -1 -> 388 | E26: =C26-D26 -> 1 | F26: =E26-G26-H26-I26-J26 -> 0 | G26: =SUMIF(Pending_Stock!C:C, B26, Pending_Stock!F:F) -> 0 | H26: =SUMIF(Pending_Stock!I:I, B26, Pending_Stock!L:L) -> 0 | I26: =SUMIF(ShipToDubai!C:C, B26, ShipToDubai!F:F) - (SUMIFS(Stock_Transactions!D:D, Stock_Transactions!B:B, B26, Stock_Transactions!D:D, "<0") * -1) -> 1 | J26: =SUMIF(ShipToDubai!C:C, B26, ShipToDubai!G:G) -> 0
A27: =A26+1 -> 25 | B27: Meta Quest 3s 128 | C27: =SUMIFS(Stock_Transactions!D:D, Stock_Transactions!B:B, B27, Stock_Transactions!D:D, ">0") -> 366 | D27: =SUMIFS(Stock_Transactions!D:D, Stock_Transactions!B:B, B27, Stock_Transactions!D:D, "<0") * -1 -> 366 | E27: =C27-D27 -> 0 | F27: =E27-G27-H27-I27-J27 -> 0 | G27: =SUMIF(Pending_Stock!C:C, B27, Pending_Stock!F:F) -> 0 | H27: =SUMIF(Pending_Stock!I:I, B27, Pending_Stock!L:L) -> 0 | I27: =SUMIF(ShipToDubai!C:C, B27, ShipToDubai!F:F) - (SUMIFS(Stock_Transactions!D:D, Stock_Transactions!B:B, B27, Stock_Transactions!D:D, "<0") * -1) -> 0 | J27: =SUMIF(ShipToDubai!C:C, B27, ShipToDubai!G:G) -> 0
A28: =A27+1 -> 26 | B28: Meta Quest 3s 512 | C28: =SUMIFS(Stock_Transactions!D:D, Stock_Transactions!B:B, B28, Stock_Transactions!D:D, ">0") -> 46 | D28: =SUMIFS(Stock_Transactions!D:D, Stock_Transactions!B:B, B28, Stock_Transactions!D:D, "<0") * -1 -> 46 | E28: =C28-D28 -> 0 | F28: =E28-G28-H28-I28-J28 -> 0 | G28: =SUMIF(Pending_Stock!C:C, B28, Pending_Stock!F:F) -> 0 | H28: =SUMIF(Pending_Stock!I:I, B28, Pending_Stock!L:L) -> 0 | I28: =SUMIF(ShipToDubai!C:C, B28, ShipToDubai!F:F) - (SUMIFS(Stock_Transactions!D:D, Stock_Transactions!B:B, B28, Stock_Transactions!D:D, "<0") * -1) -> 0 | J28: =SUMIF(ShipToDubai!C:C, B28, ShipToDubai!G:G) -> 0
A29: =A28+1 -> 27 | B29: iPad Pro 11 256 Wifi Only | C29: =SUMIFS(Stock_Transactions!D:D, Stock_Transactions!B:B, B29, Stock_Transactions!D:D, ">0") -> 15 | D29: =SUMIFS(Stock_Transactions!D:D, Stock_Transactions!B:B, B29, Stock_Transactions!D:D, "<0") * -1 -> 14 | E29: =C29-D29 -> 1 | F29: =E29-G29-H29-I29-J29 -> 0 | G29: =SUMIF(Pending_Stock!C:C, B29, Pending_Stock!F:F) -> 0 | H29: =SUMIF(Pending_Stock!I:I, B29, Pending_Stock!L:L) -> 0 | I29: =SUMIF(ShipToDubai!C:C, B29, ShipToDubai!F:F) - (SUMIFS(Stock_Transactions!D:D, Stock_Transactions!B:B, B29, Stock_Transactions!D:D, "<0") * -1) -> 1 | J29: =SUMIF(ShipToDubai!C:C, B29, ShipToDubai!G:G) -> 0 | L29: loss
A30: =A29+1 -> 28 | B30: iPad Air 13 128 Wifi Only | C30: =SUMIFS(Stock_Transactions!D:D, Stock_Transactions!B:B, B30, Stock_Transactions!D:D, ">0") -> 3 | D30: =SUMIFS(Stock_Transactions!D:D, Stock_Transactions!B:B, B30, Stock_Transactions!D:D, "<0") * -1 -> 3 | E30: =C30-D30 -> 0 | F30: =E30-G30-H30-I30-J30 -> 0 | G30: =SUMIF(Pending_Stock!C:C, B30, Pending_Stock!F:F) -> 0 | H30: =SUMIF(Pending_Stock!I:I, B30, Pending_Stock!L:L) -> 0 | I30: =SUMIF(ShipToDubai!C:C, B30, ShipToDubai!F:F) - (SUMIFS(Stock_Transactions!D:D, Stock_Transactions!B:B, B30, Stock_Transactions!D:D, "<0") * -1) -> 0 | J30: =SUMIF(ShipToDubai!C:C, B30, ShipToDubai!G:G) -> 0
A31: =A30+1 -> 29 | B31: iPad Air 13 256 Wifi Only | C31: =SUMIFS(Stock_Transactions!D:D, Stock_Transactions!B:B, B31, Stock_Transactions!D:D, ">0") -> 1 | D31: =SUMIFS(Stock_Transactions!D:D, Stock_Transactions!B:B, B31, Stock_Transactions!D:D, "<0") * -1 -> 1 | E31: =C31-D31 -> 0 | F31: =E31-G31-H31-I31-J31 -> 0 | G31: =SUMIF(Pending_Stock!C:C, B31, Pending_Stock!F:F) -> 0 | H31: =SUMIF(Pending_Stock!I:I, B31, Pending_Stock!L:L) -> 0 | I31: =SUMIF(ShipToDubai!C:C, B31, ShipToDubai!F:F) - (SUMIFS(Stock_Transactions!D:D, Stock_Transactions!B:B, B31, Stock_Transactions!D:D, "<0") * -1) -> 0 | J31: =SUMIF(ShipToDubai!C:C, B31, ShipToDubai!G:G) -> 0
A32: =A31+1 -> 30 | C32: =SUMIFS(Stock_Transactions!D:D, Stock_Transactions!B:B, B32, Stock_Transactions!D:D, ">0") -> 0 | D32: =SUMIFS(Stock_Transactions!D:D, Stock_Transactions!B:B, B32, Stock_Transactions!D:D, "<0") * -1 -> 0 | E32: =C32-D32 -> 0 | F32: =E32-G32-H32-I32-J32 -> 0 | G32: =SUMIF(Pending_Stock!C:C, B32, Pending_Stock!F:F) -> 0 | H32: =SUMIF(Pending_Stock!I:I, B32, Pending_Stock!L:L) -> 0 | I32: =SUMIF(ShipToDubai!C:C, B32, ShipToDubai!F:F) - (SUMIFS(Stock_Transactions!D:D, Stock_Transactions!B:B, B32, Stock_Transactions!D:D, "<0") * -1) -> 0 | J32: =SUMIF(ShipToDubai!C:C, B32, ShipToDubai!G:G) -> 0 | M32: iPad Air 13 128 Wifi Only | N32: -1
A33: =A32+1 -> 31 | C33: =SUMIFS(Stock_Transactions!D:D, Stock_Transactions!B:B, B33, Stock_Transactions!D:D, ">0") -> 0 | D33: =SUMIFS(Stock_Transactions!D:D, Stock_Transactions!B:B, B33, Stock_Transactions!D:D, "<0") * -1 -> 0 | E33: =C33-D33 -> 0 | F33: =E33-G33-H33-I33-J33 -> 0 | G33: =SUMIF(Pending_Stock!C:C, B33, Pending_Stock!F:F) -> 0 | H33: =SUMIF(Pending_Stock!I:I, B33, Pending_Stock!L:L) -> 0 | I33: =SUMIF(ShipToDubai!C:C, B33, ShipToDubai!F:F) - (SUMIFS(Stock_Transactions!D:D, Stock_Transactions!B:B, B33, Stock_Transactions!D:D, "<0") * -1) -> 0 | J33: =SUMIF(ShipToDubai!C:C, B33, ShipToDubai!G:G) -> 0 | K33: Pakistan | M33: CANON SX740 | N33: -2
A34: =A33+1 -> 32 | B34: Ps5 Controller Dual sense | C34: =SUMIFS(Stock_Transactions!D:D, Stock_Transactions!B:B, B34, Stock_Transactions!D:D, ">0") -> 170 | D34: =SUMIFS(Stock_Transactions!D:D, Stock_Transactions!B:B, B34, Stock_Transactions!D:D, "<0") * -1 -> 170 | E34: =C34-D34 -> 0 | F34: =E34-G34-H34-I34-J34 -> 0 | G34: =SUMIF(Pending_Stock!C:C, B34, Pending_Stock!F:F) -> 0 | H34: =SUMIF(Pending_Stock!I:I, B34, Pending_Stock!L:L) -> 0 | I34: =SUMIF(ShipToDubai!C:C, B34, ShipToDubai!F:F) - (SUMIFS(Stock_Transactions!D:D, Stock_Transactions!B:B, B34, Stock_Transactions!D:D, "<0") * -1) -> 0 | J34: =SUMIF(ShipToDubai!C:C, B34, ShipToDubai!G:G) -> 0 | L34: ok | M34: Ipad Pro 13" W+C Black 512gb | N34: -1
A35: =A34+1 -> 33 | B35: Beats Fit Pro | C35: =SUMIFS(Stock_Transactions!D:D, Stock_Transactions!B:B, B35, Stock_Transactions!D:D, ">0") -> 17 | D35: =SUMIFS(Stock_Transactions!D:D, Stock_Transactions!B:B, B35, Stock_Transactions!D:D, "<0") * -1 -> 17 | E35: =C35-D35 -> 0 | F35: =E35-G35-H35-I35-J35 -> 0 | G35: =SUMIF(Pending_Stock!C:C, B35, Pending_Stock!F:F) -> 0 | H35: =SUMIF(Pending_Stock!I:I, B35, Pending_Stock!L:L) -> 0 | I35: =SUMIF(ShipToDubai!C:C, B35, ShipToDubai!F:F) - (SUMIFS(Stock_Transactions!D:D, Stock_Transactions!B:B, B35, Stock_Transactions!D:D, "<0") * -1) -> 0 | J35: =SUMIF(ShipToDubai!C:C, B35, ShipToDubai!G:G) -> 0 | M35: Samsung Galaxy S25 plus 256 | N35: -1
A36: =A35+1 -> 34 | B36: Beats Pill Speaker | C36: =SUMIFS(Stock_Transactions!D:D, Stock_Transactions!B:B, B36, Stock_Transactions!D:D, ">0") -> 2 | D36: =SUMIFS(Stock_Transactions!D:D, Stock_Transactions!B:B, B36, Stock_Transactions!D:D, "<0") * -1 -> 0 | E36: =C36-D36 -> 2 | F36: =E36-G36-H36-I36-J36 -> 0 | G36: =SUMIF(Pending_Stock!C:C, B36, Pending_Stock!F:F) -> 0 | H36: =SUMIF(Pending_Stock!I:I, B36, Pending_Stock!L:L) -> 0 | I36: =SUMIF(ShipToDubai!C:C, B36, ShipToDubai!F:F) - (SUMIFS(Stock_Transactions!D:D, Stock_Transactions!B:B, B36, Stock_Transactions!D:D, "<0") * -1) -> 2 | J36: =SUMIF(ShipToDubai!C:C, B36, ShipToDubai!G:G) -> 0 | L36: ok | M36: Iphone 16 PM 1TB | N36: -1
A37: =A36+1 -> 35 | B37: iPhone 15 Pro 256 | C37: =SUMIFS(Stock_Transactions!D:D, Stock_Transactions!B:B, B37, Stock_Transactions!D:D, ">0") -> 1 | D37: =SUMIFS(Stock_Transactions!D:D, Stock_Transactions!B:B, B37, Stock_Transactions!D:D, "<0") * -1 -> 1 | E37: =C37-D37 -> 0 | F37: =E37-G37-H37-I37-J37 -> 0 | G37: =SUMIF(Pending_Stock!C:C, B37, Pending_Stock!F:F) -> 0 | H37: =SUMIF(Pending_Stock!I:I, B37, Pending_Stock!L:L) -> 0 | I37: =SUMIF(ShipToDubai!C:C, B37, ShipToDubai!F:F) - (SUMIFS(Stock_Transactions!D:D, Stock_Transactions!B:B, B37, Stock_Transactions!D:D, "<0") * -1) -> 0 | J37: =SUMIF(ShipToDubai!C:C, B37, ShipToDubai!G:G) -> 0 | M37: Ipad A16 WIFI Only | N37: -1
A38: =A37+1 -> 36 | B38: iPhone 16 128 | C38: =SUMIFS(Stock_Transactions!D:D, Stock_Transactions!B:B, B38, Stock_Transactions!D:D, ">0") -> 49 | D38: =SUMIFS(Stock_Transactions!D:D, Stock_Transactions!B:B, B38, Stock_Transactions!D:D, "<0") * -1 -> 49 | E38: =C38-D38 -> 0 | F38: =E38-G38-H38-I38-J38 -> 0 | G38: =SUMIF(Pending_Stock!C:C, B38, Pending_Stock!F:F) -> 0 | H38: =SUMIF(Pending_Stock!I:I, B38, Pending_Stock!L:L) -> 0 | I38: =SUMIF(ShipToDubai!C:C, B38, ShipToDubai!F:F) - (SUMIFS(Stock_Transactions!D:D, Stock_Transactions!B:B, B38, Stock_Transactions!D:D, "<0") * -1) -> 0 | J38: =SUMIF(ShipToDubai!C:C, B38, ShipToDubai!G:G) -> 0 | M38: Ipad Pro 13'' M4 256gb wifi | N38: -2
A39: =A38+1 -> 37 | B39: iPhone 14 Pro Max 128 | C39: =SUMIFS(Stock_Transactions!D:D, Stock_Transactions!B:B, B39, Stock_Transactions!D:D, ">0") -> 5 | D39: =SUMIFS(Stock_Transactions!D:D, Stock_Transactions!B:B, B39, Stock_Transactions!D:D, "<0") * -1 -> 3 | E39: =C39-D39 -> 2 | F39: =E39-G39-H39-I39-J39 -> 0 | G39: =SUMIF(Pending_Stock!C:C, B39, Pending_Stock!F:F) -> 0 | H39: =SUMIF(Pending_Stock!I:I, B39, Pending_Stock!L:L) -> 0 | I39: =SUMIF(ShipToDubai!C:C, B39, ShipToDubai!F:F) - (SUMIFS(Stock_Transactions!D:D, Stock_Transactions!B:B, B39, Stock_Transactions!D:D, "<0") * -1) -> 2 | J39: =SUMIF(ShipToDubai!C:C, B39, ShipToDubai!G:G) -> 0 | M39: Iphone Air 17 256gb | N39: -4
A40: =A39+1 -> 38 | C40: =SUMIFS(Stock_Transactions!D:D, Stock_Transactions!B:B, B40, Stock_Transactions!D:D, ">0") -> 0 | D40: =SUMIFS(Stock_Transactions!D:D, Stock_Transactions!B:B, B40, Stock_Transactions!D:D, "<0") * -1 -> 0 | E40: =C40-D40 -> 0 | F40: =E40-G40-H40-I40-J40 -> 0 | G40: =SUMIF(Pending_Stock!C:C, B40, Pending_Stock!F:F) -> 0 | H40: =SUMIF(Pending_Stock!I:I, B40, Pending_Stock!L:L) -> 0 | I40: =SUMIF(ShipToDubai!C:C, B40, ShipToDubai!F:F) - (SUMIFS(Stock_Transactions!D:D, Stock_Transactions!B:B, B40, Stock_Transactions!D:D, "<0") * -1) -> 0 | J40: =SUMIF(ShipToDubai!C:C, B40, ShipToDubai!G:G) -> 0 | M40: Ipad Air 11'' M3 256gb | N40: -1
A41: =A40+1 -> 39 | B41: APPLE AIR TAG 1 PACK | C41: =SUMIFS(Stock_Transactions!D:D, Stock_Transactions!B:B, B41, Stock_Transactions!D:D, ">0") -> 274 | D41: =SUMIFS(Stock_Transactions!D:D, Stock_Transactions!B:B, B41, Stock_Transactions!D:D, "<0") * -1 -> 274 | E41: =C41-D41 -> 0 | F41: =E41-G41-H41-I41-J41 -> 0 | G41: =SUMIF(Pending_Stock!C:C, B41, Pending_Stock!F:F) -> 0 | H41: =SUMIF(Pending_Stock!I:I, B41, Pending_Stock!L:L) -> 0 | I41: =SUMIF(ShipToDubai!C:C, B41, ShipToDubai!F:F) - (SUMIFS(Stock_Transactions!D:D, Stock_Transactions!B:B, B41, Stock_Transactions!D:D, "<0") * -1) -> 0 | J41: =SUMIF(ShipToDubai!C:C, B41, ShipToDubai!G:G) -> 0 | M41: Apple Watch SE 3 40mm | N41: -1
A42: =A41+1 -> 40 | B42: Macbook Air 13 M3 24/512 GB | C42: =SUMIFS(Stock_Transactions!D:D, Stock_Transactions!B:B, B42, Stock_Transactions!D:D, ">0") -> 0 | D42: =SUMIFS(Stock_Transactions!D:D, Stock_Transactions!B:B, B42, Stock_Transactions!D:D, "<0") * -1 -> 0 | E42: =C42-D42 -> 0 | F42: =E42-G42-H42-I42-J42 -> 0 | G42: =SUMIF(Pending_Stock!C:C, B42, Pending_Stock!F:F) -> 0 | H42: =SUMIF(Pending_Stock!I:I, B42, Pending_Stock!L:L) -> 0 | I42: =SUMIF(ShipToDubai!C:C, B42, ShipToDubai!F:F) - (SUMIFS(Stock_Transactions!D:D, Stock_Transactions!B:B, B42, Stock_Transactions!D:D, "<0") * -1) -> 0 | J42: =SUMIF(ShipToDubai!C:C, B42, ShipToDubai!G:G) -> 0 | M42: Sandisk Portable G-Drive 6TB | N42: -1
A43: =A42+1 -> 41 | B43: Macbook Air 24/512 GB | C43: =SUMIFS(Stock_Transactions!D:D, Stock_Transactions!B:B, B43, Stock_Transactions!D:D, ">0") -> 125 | D43: =SUMIFS(Stock_Transactions!D:D, Stock_Transactions!B:B, B43, Stock_Transactions!D:D, "<0") * -1 -> 133 | E43: =C43-D43 -> -8 | F43: =E43-G43-H43-I43-J43 -> 1 | G43: =SUMIF(Pending_Stock!C:C, B43, Pending_Stock!F:F) -> 0 | H43: =SUMIF(Pending_Stock!I:I, B43, Pending_Stock!L:L) -> 0 | I43: =SUMIF(ShipToDubai!C:C, B43, ShipToDubai!F:F) - (SUMIFS(Stock_Transactions!D:D, Stock_Transactions!B:B, B43, Stock_Transactions!D:D, "<0") * -1) -> -9 | J43: =SUMIF(ShipToDubai!C:C, B43, ShipToDubai!G:G) -> 0 | L43: ok | M43: WD-Black P10 G-Drive 4TB | N43: -1
A44: =A43+1 -> 42 | B44: Macbook Air 15 M3 24/512 GB | C44: =SUMIFS(Stock_Transactions!D:D, Stock_Transactions!B:B, B44, Stock_Transactions!D:D, ">0") -> 14 | D44: =SUMIFS(Stock_Transactions!D:D, Stock_Transactions!B:B, B44, Stock_Transactions!D:D, "<0") * -1 -> 5 | E44: =C44-D44 -> 9 | F44: =E44-G44-H44-I44-J44 -> 0 | G44: =SUMIF(Pending_Stock!C:C, B44, Pending_Stock!F:F) -> 0 | H44: =SUMIF(Pending_Stock!I:I, B44, Pending_Stock!L:L) -> 0 | I44: =SUMIF(ShipToDubai!C:C, B44, ShipToDubai!F:F) - (SUMIFS(Stock_Transactions!D:D, Stock_Transactions!B:B, B44, Stock_Transactions!D:D, "<0") * -1) -> 9 | J44: =SUMIF(ShipToDubai!C:C, B44, ShipToDubai!G:G) -> 0 | L44: ok | M44: WD-Black P10 G-Drive 5TB | N44: -4
A45: =A44+1 -> 43 | B45: Macbook Air 15 24/512 GB | C45: =SUMIFS(Stock_Transactions!D:D, Stock_Transactions!B:B, B45, Stock_Transactions!D:D, ">0") -> 33 | D45: =SUMIFS(Stock_Transactions!D:D, Stock_Transactions!B:B, B45, Stock_Transactions!D:D, "<0") * -1 -> 32 | E45: =C45-D45 -> 1 | F45: =E45-G45-H45-I45-J45 -> 1 | G45: =SUMIF(Pending_Stock!C:C, B45, Pending_Stock!F:F) -> 0 | H45: =SUMIF(Pending_Stock!I:I, B45, Pending_Stock!L:L) -> 0 | I45: =SUMIF(ShipToDubai!C:C, B45, ShipToDubai!F:F) - (SUMIFS(Stock_Transactions!D:D, Stock_Transactions!B:B, B45, Stock_Transactions!D:D, "<0") * -1) -> 0 | J45: =SUMIF(ShipToDubai!C:C, B45, ShipToDubai!G:G) -> 0 | L45: ok | M45: Rad 700i Radar & Detector | N45: -2
A46: =A45+1 -> 44 | C46: =SUMIFS(Stock_Transactions!D:D, Stock_Transactions!B:B, B46, Stock_Transactions!D:D, ">0") -> 0 | D46: =SUMIFS(Stock_Transactions!D:D, Stock_Transactions!B:B, B46, Stock_Transactions!D:D, "<0") * -1 -> 0 | E46: =C46-D46 -> 0 | F46: =E46-G46-H46-I46-J46 -> 0 | G46: =SUMIF(Pending_Stock!C:C, B46, Pending_Stock!F:F) -> 0 | H46: =SUMIF(Pending_Stock!I:I, B46, Pending_Stock!L:L) -> 0 | I46: =SUMIF(ShipToDubai!C:C, B46, ShipToDubai!F:F) - (SUMIFS(Stock_Transactions!D:D, Stock_Transactions!B:B, B46, Stock_Transactions!D:D, "<0") * -1) -> 0 | J46: =SUMIF(ShipToDubai!C:C, B46, ShipToDubai!G:G) -> 0 | M46: Ipad pro 11'' M4 256gb wifi | N46: -1
A47: =A46+1 -> 45 | B47: Macbook Pro 16/1TB | C47: =SUMIFS(Stock_Transactions!D:D, Stock_Transactions!B:B, B47, Stock_Transactions!D:D, ">0") -> 8 | D47: =SUMIFS(Stock_Transactions!D:D, Stock_Transactions!B:B, B47, Stock_Transactions!D:D, "<0") * -1 -> 8 | E47: =C47-D47 -> 0 | F47: =E47-G47-H47-I47-J47 -> 0 | G47: =SUMIF(Pending_Stock!C:C, B47, Pending_Stock!F:F) -> 0 | H47: =SUMIF(Pending_Stock!I:I, B47, Pending_Stock!L:L) -> 0 | I47: =SUMIF(ShipToDubai!C:C, B47, ShipToDubai!F:F) - (SUMIFS(Stock_Transactions!D:D, Stock_Transactions!B:B, B47, Stock_Transactions!D:D, "<0") * -1) -> 0 | J47: =SUMIF(ShipToDubai!C:C, B47, ShipToDubai!G:G) -> 0 | M47: Ipad pro 11'' M4 512gb wifi | N47: -1
A48: =A47+1 -> 46 | B48: RAYBAN GLASSES | C48: =SUMIFS(Stock_Transactions!D:D, Stock_Transactions!B:B, B48, Stock_Transactions!D:D, ">0") -> 335 | D48: =SUMIFS(Stock_Transactions!D:D, Stock_Transactions!B:B, B48, Stock_Transactions!D:D, "<0") * -1 -> 320 | E48: =C48-D48 -> 15 | F48: =E48-G48-H48-I48-J48 -> 4 | G48: =SUMIF(Pending_Stock!C:C, B48, Pending_Stock!F:F) -> 0 | H48: =SUMIF(Pending_Stock!I:I, B48, Pending_Stock!L:L) -> 0 | I48: =SUMIF(ShipToDubai!C:C, B48, ShipToDubai!F:F) - (SUMIFS(Stock_Transactions!D:D, Stock_Transactions!B:B, B48, Stock_Transactions!D:D, "<0") * -1) -> 11 | J48: =SUMIF(ShipToDubai!C:C, B48, ShipToDubai!G:G) -> 0
A49: =A48+1 -> 47 | B49: SONY BUDS | C49: =SUMIFS(Stock_Transactions!D:D, Stock_Transactions!B:B, B49, Stock_Transactions!D:D, ">0") -> 29 | D49: =SUMIFS(Stock_Transactions!D:D, Stock_Transactions!B:B, B49, Stock_Transactions!D:D, "<0") * -1 -> 29 | E49: =C49-D49 -> 0 | F49: =E49-G49-H49-I49-J49 -> 0 | G49: =SUMIF(Pending_Stock!C:C, B49, Pending_Stock!F:F) -> 0 | H49: =SUMIF(Pending_Stock!I:I, B49, Pending_Stock!L:L) -> 0 | I49: =SUMIF(ShipToDubai!C:C, B49, ShipToDubai!F:F) - (SUMIFS(Stock_Transactions!D:D, Stock_Transactions!B:B, B49, Stock_Transactions!D:D, "<0") * -1) -> 0 | J49: =SUMIF(ShipToDubai!C:C, B49, ShipToDubai!G:G) -> 0
A50: =A49+1 -> 48 | B50: PLAY STATION PORTAL | C50: =SUMIFS(Stock_Transactions!D:D, Stock_Transactions!B:B, B50, Stock_Transactions!D:D, ">0") -> 13 | D50: =SUMIFS(Stock_Transactions!D:D, Stock_Transactions!B:B, B50, Stock_Transactions!D:D, "<0") * -1 -> 13 | E50: =C50-D50 -> 0 | F50: =E50-G50-H50-I50-J50 -> 0 | G50: =SUMIF(Pending_Stock!C:C, B50, Pending_Stock!F:F) -> 0 | H50: =SUMIF(Pending_Stock!I:I, B50, Pending_Stock!L:L) -> 0 | I50: =SUMIF(ShipToDubai!C:C, B50, ShipToDubai!F:F) - (SUMIFS(Stock_Transactions!D:D, Stock_Transactions!B:B, B50, Stock_Transactions!D:D, "<0") * -1) -> 0 | J50: =SUMIF(ShipToDubai!C:C, B50, ShipToDubai!G:G) -> 0
A51: =A50+1 -> 49 | B51: PS5 SSD 2TB | C51: =SUMIFS(Stock_Transactions!D:D, Stock_Transactions!B:B, B51, Stock_Transactions!D:D, ">0") -> 30 | D51: =SUMIFS(Stock_Transactions!D:D, Stock_Transactions!B:B, B51, Stock_Transactions!D:D, "<0") * -1 -> 30 | E51: =C51-D51 -> 0 | F51: =E51-G51-H51-I51-J51 -> 0 | G51: =SUMIF(Pending_Stock!C:C, B51, Pending_Stock!F:F) -> 0 | H51: =SUMIF(Pending_Stock!I:I, B51, Pending_Stock!L:L) -> 0 | I51: =SUMIF(ShipToDubai!C:C, B51, ShipToDubai!F:F) - (SUMIFS(Stock_Transactions!D:D, Stock_Transactions!B:B, B51, Stock_Transactions!D:D, "<0") * -1) -> 0 | J51: =SUMIF(ShipToDubai!C:C, B51, ShipToDubai!G:G) -> 0
A52: =A51+1 -> 50 | B52: APPLE AIRPODS PRO | C52: =SUMIFS(Stock_Transactions!D:D, Stock_Transactions!B:B, B52, Stock_Transactions!D:D, ">0") -> 12 | D52: =SUMIFS(Stock_Transactions!D:D, Stock_Transactions!B:B, B52, Stock_Transactions!D:D, "<0") * -1 -> 12 | E52: =C52-D52 -> 0 | F52: =E52-G52-H52-I52-J52 -> 0 | G52: =SUMIF(Pending_Stock!C:C, B52, Pending_Stock!F:F) -> 0 | H52: =SUMIF(Pending_Stock!I:I, B52, Pending_Stock!L:L) -> 0 | I52: =SUMIF(ShipToDubai!C:C, B52, ShipToDubai!F:F) - (SUMIFS(Stock_Transactions!D:D, Stock_Transactions!B:B, B52, Stock_Transactions!D:D, "<0") * -1) -> 0 | J52: =SUMIF(ShipToDubai!C:C, B52, ShipToDubai!G:G) -> 0
A53: =A52+1 -> 51 | B53: NORTON ANTIVIRUS | C53: =SUMIFS(Stock_Transactions!D:D, Stock_Transactions!B:B, B53, Stock_Transactions!D:D, ">0") -> 1 | D53: =SUMIFS(Stock_Transactions!D:D, Stock_Transactions!B:B, B53, Stock_Transactions!D:D, "<0") * -1 -> 0 | E53: =C53-D53 -> 1 | F53: =E53-G53-H53-I53-J53 -> 1 | G53: =SUMIF(Pending_Stock!C:C, B53, Pending_Stock!F:F) -> 0 | H53: =SUMIF(Pending_Stock!I:I, B53, Pending_Stock!L:L) -> 0 | I53: =SUMIF(ShipToDubai!C:C, B53, ShipToDubai!F:F) - (SUMIFS(Stock_Transactions!D:D, Stock_Transactions!B:B, B53, Stock_Transactions!D:D, "<0") * -1) -> 0 | J53: =SUMIF(ShipToDubai!C:C, B53, ShipToDubai!G:G) -> 0
A54: =A53+1 -> 52 | C54: =SUMIFS(Stock_Transactions!D:D, Stock_Transactions!B:B, B54, Stock_Transactions!D:D, ">0") -> 0 | D54: =SUMIFS(Stock_Transactions!D:D, Stock_Transactions!B:B, B54, Stock_Transactions!D:D, "<0") * -1 -> 0 | E54: =C54-D54 -> 0 | F54: =E54-G54-H54-I54-J54 -> 0 | G54: =SUMIF(Pending_Stock!C:C, B54, Pending_Stock!F:F) -> 0 | H54: =SUMIF(Pending_Stock!I:I, B54, Pending_Stock!L:L) -> 0 | I54: =SUMIF(ShipToDubai!C:C, B54, ShipToDubai!F:F) - (SUMIFS(Stock_Transactions!D:D, Stock_Transactions!B:B, B54, Stock_Transactions!D:D, "<0") * -1) -> 0 | J54: =SUMIF(ShipToDubai!C:C, B54, ShipToDubai!G:G) -> 0 | K54: Pakistan
A55: =A54+1 -> 53 | B55: Dragon Age Game CD | C55: =SUMIFS(Stock_Transactions!D:D, Stock_Transactions!B:B, B55, Stock_Transactions!D:D, ">0") -> 101 | D55: =SUMIFS(Stock_Transactions!D:D, Stock_Transactions!B:B, B55, Stock_Transactions!D:D, "<0") * -1 -> 30 | E55: =C55-D55 -> 71 | F55: =E55-G55-H55-I55-J55 -> 0 | G55: =SUMIF(Pending_Stock!C:C, B55, Pending_Stock!F:F) -> 20 | H55: =SUMIF(Pending_Stock!I:I, B55, Pending_Stock!L:L) -> 0 | I55: =SUMIF(ShipToDubai!C:C, B55, ShipToDubai!F:F) - (SUMIFS(Stock_Transactions!D:D, Stock_Transactions!B:B, B55, Stock_Transactions!D:D, "<0") * -1) -> 51 | J55: =SUMIF(ShipToDubai!C:C, B55, ShipToDubai!G:G) -> 0 | K55: refund | L55: ok
A56: =A55+1 -> 54 | B56: DJI OSMO POCKET 3 | C56: =SUMIFS(Stock_Transactions!D:D, Stock_Transactions!B:B, B56, Stock_Transactions!D:D, ">0") -> 49 | D56: =SUMIFS(Stock_Transactions!D:D, Stock_Transactions!B:B, B56, Stock_Transactions!D:D, "<0") * -1 -> 49 | E56: =C56-D56 -> 0 | F56: =E56-G56-H56-I56-J56 -> 0 | G56: =SUMIF(Pending_Stock!C:C, B56, Pending_Stock!F:F) -> 0 | H56: =SUMIF(Pending_Stock!I:I, B56, Pending_Stock!L:L) -> 0 | I56: =SUMIF(ShipToDubai!C:C, B56, ShipToDubai!F:F) - (SUMIFS(Stock_Transactions!D:D, Stock_Transactions!B:B, B56, Stock_Transactions!D:D, "<0") * -1) -> 0 | J56: =SUMIF(ShipToDubai!C:C, B56, ShipToDubai!G:G) -> 0 | L56: ok
A57: =A56+1 -> 55 | B57: DJI MAVIC PRO RC | C57: =SUMIFS(Stock_Transactions!D:D, Stock_Transactions!B:B, B57, Stock_Transactions!D:D, ">0") -> 47 | D57: =SUMIFS(Stock_Transactions!D:D, Stock_Transactions!B:B, B57, Stock_Transactions!D:D, "<0") * -1 -> 47 | E57: =C57-D57 -> 0 | F57: =E57-G57-H57-I57-J57 -> 0 | G57: =SUMIF(Pending_Stock!C:C, B57, Pending_Stock!F:F) -> 0 | H57: =SUMIF(Pending_Stock!I:I, B57, Pending_Stock!L:L) -> 0 | I57: =SUMIF(ShipToDubai!C:C, B57, ShipToDubai!F:F) - (SUMIFS(Stock_Transactions!D:D, Stock_Transactions!B:B, B57, Stock_Transactions!D:D, "<0") * -1) -> 0 | J57: =SUMIF(ShipToDubai!C:C, B57, ShipToDubai!G:G) -> 0
A58: =A57+1 -> 56 | B58: DJI MAVIC PRO RC COMBO | C58: =SUMIFS(Stock_Transactions!D:D, Stock_Transactions!B:B, B58, Stock_Transactions!D:D, ">0") -> 30 | D58: =SUMIFS(Stock_Transactions!D:D, Stock_Transactions!B:B, B58, Stock_Transactions!D:D, "<0") * -1 -> 30 | E58: =C58-D58 -> 0 | F58: =E58-G58-H58-I58-J58 -> 0 | G58: =SUMIF(Pending_Stock!C:C, B58, Pending_Stock!F:F) -> 0 | H58: =SUMIF(Pending_Stock!I:I, B58, Pending_Stock!L:L) -> 0 | I58: =SUMIF(ShipToDubai!C:C, B58, ShipToDubai!F:F) - (SUMIFS(Stock_Transactions!D:D, Stock_Transactions!B:B, B58, Stock_Transactions!D:D, "<0") * -1) -> 0 | J58: =SUMIF(ShipToDubai!C:C, B58, ShipToDubai!G:G) -> 0
A59: =A58+1 -> 57 | B59: NINJA BLAST BLENDER | C59: =SUMIFS(Stock_Transactions!D:D, Stock_Transactions!B:B, B59, Stock_Transactions!D:D, ">0") -> 62 | D59: =SUMIFS(Stock_Transactions!D:D, Stock_Transactions!B:B, B59, Stock_Transactions!D:D, "<0") * -1 -> 52 | E59: =C59-D59 -> 10 | F59: =E59-G59-H59-I59-J59 -> 0 | G59: =SUMIF(Pending_Stock!C:C, B59, Pending_Stock!F:F) -> 0 | H59: =SUMIF(Pending_Stock!I:I, B59, Pending_Stock!L:L) -> 0 | I59: =SUMIF(ShipToDubai!C:C, B59, ShipToDubai!F:F) - (SUMIFS(Stock_Transactions!D:D, Stock_Transactions!B:B, B59, Stock_Transactions!D:D, "<0") * -1) -> 10 | J59: =SUMIF(ShipToDubai!C:C, B59, ShipToDubai!G:G) -> 0 | L59: ok
A60: =A59+1 -> 58 | B60: INSTAX FLIM 20 PACK | C60: =SUMIFS(Stock_Transactions!D:D, Stock_Transactions!B:B, B60, Stock_Transactions!D:D, ">0") -> 1276 | D60: =SUMIFS(Stock_Transactions!D:D, Stock_Transactions!B:B, B60, Stock_Transactions!D:D, "<0") * -1 -> 1276 | E60: =C60-D60 -> 0 | F60: =E60-G60-H60-I60-J60 -> 0 | G60: =SUMIF(Pending_Stock!C:C, B60, Pending_Stock!F:F) -> 0 | H60: =SUMIF(Pending_Stock!I:I, B60, Pending_Stock!L:L) -> 0 | I60: =SUMIF(ShipToDubai!C:C, B60, ShipToDubai!F:F) - (SUMIFS(Stock_Transactions!D:D, Stock_Transactions!B:B, B60, Stock_Transactions!D:D, "<0") * -1) -> 0 | J60: =SUMIF(ShipToDubai!C:C, B60, ShipToDubai!G:G) -> 0 | L60: ok
A61: =A60+1 -> 59 | B61: INSTAX MINI 40 | C61: =SUMIFS(Stock_Transactions!D:D, Stock_Transactions!B:B, B61, Stock_Transactions!D:D, ">0") -> 6 | D61: =SUMIFS(Stock_Transactions!D:D, Stock_Transactions!B:B, B61, Stock_Transactions!D:D, "<0") * -1 -> 6 | E61: =C61-D61 -> 0 | F61: =E61-G61-H61-I61-J61 -> 0 | G61: =SUMIF(Pending_Stock!C:C, B61, Pending_Stock!F:F) -> 0 | H61: =SUMIF(Pending_Stock!I:I, B61, Pending_Stock!L:L) -> 0 | I61: =SUMIF(ShipToDubai!C:C, B61, ShipToDubai!F:F) - (SUMIFS(Stock_Transactions!D:D, Stock_Transactions!B:B, B61, Stock_Transactions!D:D, "<0") * -1) -> 0 | J61: =SUMIF(ShipToDubai!C:C, B61, ShipToDubai!G:G) -> 0
A62: =A61+1 -> 60 | B62: IPHONE 13 128 | C62: =SUMIFS(Stock_Transactions!D:D, Stock_Transactions!B:B, B62, Stock_Transactions!D:D, ">0") -> 13 | D62: =SUMIFS(Stock_Transactions!D:D, Stock_Transactions!B:B, B62, Stock_Transactions!D:D, "<0") * -1 -> 11 | E62: =C62-D62 -> 2 | F62: =E62-G62-H62-I62-J62 -> -1 | G62: =SUMIF(Pending_Stock!C:C, B62, Pending_Stock!F:F) -> 0 | H62: =SUMIF(Pending_Stock!I:I, B62, Pending_Stock!L:L) -> 0 | I62: =SUMIF(ShipToDubai!C:C, B62, ShipToDubai!F:F) - (SUMIFS(Stock_Transactions!D:D, Stock_Transactions!B:B, B62, Stock_Transactions!D:D, "<0") * -1) -> 3 | J62: =SUMIF(ShipToDubai!C:C, B62, ShipToDubai!G:G) -> 0
A63: =A62+1 -> 61 | B63: INSTAX Li PLAY | C63: =SUMIFS(Stock_Transactions!D:D, Stock_Transactions!B:B, B63, Stock_Transactions!D:D, ">0") -> 12 | D63: =SUMIFS(Stock_Transactions!D:D, Stock_Transactions!B:B, B63, Stock_Transactions!D:D, "<0") * -1 -> 12 | E63: =C63-D63 -> 0 | F63: =E63-G63-H63-I63-J63 -> 0 | G63: =SUMIF(Pending_Stock!C:C, B63, Pending_Stock!F:F) -> 0 | H63: =SUMIF(Pending_Stock!I:I, B63, Pending_Stock!L:L) -> 0 | I63: =SUMIF(ShipToDubai!C:C, B63, ShipToDubai!F:F) - (SUMIFS(Stock_Transactions!D:D, Stock_Transactions!B:B, B63, Stock_Transactions!D:D, "<0") * -1) -> 0 | J63: =SUMIF(ShipToDubai!C:C, B63, ShipToDubai!G:G) -> 0
A64: =A63+1 -> 62 | B64: INSTAX FLIM 10 PACK | C64: =SUMIFS(Stock_Transactions!D:D, Stock_Transactions!B:B, B64, Stock_Transactions!D:D, ">0") -> 47 | D64: =SUMIFS(Stock_Transactions!D:D, Stock_Transactions!B:B, B64, Stock_Transactions!D:D, "<0") * -1 -> 47 | E64: =C64-D64 -> 0 | F64: =E64-G64-H64-I64-J64 -> 0 | G64: =SUMIF(Pending_Stock!C:C, B64, Pending_Stock!F:F) -> 0 | H64: =SUMIF(Pending_Stock!I:I, B64, Pending_Stock!L:L) -> 0 | I64: =SUMIF(ShipToDubai!C:C, B64, ShipToDubai!F:F) - (SUMIFS(Stock_Transactions!D:D, Stock_Transactions!B:B, B64, Stock_Transactions!D:D, "<0") * -1) -> 0 | J64: =SUMIF(ShipToDubai!C:C, B64, ShipToDubai!G:G) -> 0
A65: =A64+1 -> 63 | B65: INSTAX MINI LINK 3 | C65: =SUMIFS(Stock_Transactions!D:D, Stock_Transactions!B:B, B65, Stock_Transactions!D:D, ">0") -> 1 | D65: =SUMIFS(Stock_Transactions!D:D, Stock_Transactions!B:B, B65, Stock_Transactions!D:D, "<0") * -1 -> 1 | E65: =C65-D65 -> 0 | F65: =E65-G65-H65-I65-J65 -> 0 | G65: =SUMIF(Pending_Stock!C:C, B65, Pending_Stock!F:F) -> 0 | H65: =SUMIF(Pending_Stock!I:I, B65, Pending_Stock!L:L) -> 0 | I65: =SUMIF(ShipToDubai!C:C, B65, ShipToDubai!F:F) - (SUMIFS(Stock_Transactions!D:D, Stock_Transactions!B:B, B65, Stock_Transactions!D:D, "<0") * -1) -> 0 | J65: =SUMIF(ShipToDubai!C:C, B65, ShipToDubai!G:G) -> 0
A66: =A65+1 -> 64 | B66: DJI OSMO Mobile 7 P | C66: =SUMIFS(Stock_Transactions!D:D, Stock_Transactions!B:B, B66, Stock_Transactions!D:D, ">0") -> 5 | D66: =SUMIFS(Stock_Transactions!D:D, Stock_Transactions!B:B, B66, Stock_Transactions!D:D, "<0") * -1 -> 5 | E66: =C66-D66 -> 0 | F66: =E66-G66-H66-I66-J66 -> 0 | G66: =SUMIF(Pending_Stock!C:C, B66, Pending_Stock!F:F) -> 0 | H66: =SUMIF(Pending_Stock!I:I, B66, Pending_Stock!L:L) -> 0 | I66: =SUMIF(ShipToDubai!C:C, B66, ShipToDubai!F:F) - (SUMIFS(Stock_Transactions!D:D, Stock_Transactions!B:B, B66, Stock_Transactions!D:D, "<0") * -1) -> 0 | J66: =SUMIF(ShipToDubai!C:C, B66, ShipToDubai!G:G) -> 0
A67: =A66+1 -> 65 | B67: DJI OSMO Action 5 pro | C67: =SUMIFS(Stock_Transactions!D:D, Stock_Transactions!B:B, B67, Stock_Transactions!D:D, ">0") -> 0 | D67: =SUMIFS(Stock_Transactions!D:D, Stock_Transactions!B:B, B67, Stock_Transactions!D:D, "<0") * -1 -> 0 | E67: =C67-D67 -> 0 | F67: =E67-G67-H67-I67-J67 -> 0 | G67: =SUMIF(Pending_Stock!C:C, B67, Pending_Stock!F:F) -> 0 | H67: =SUMIF(Pending_Stock!I:I, B67, Pending_Stock!L:L) -> 0 | I67: =SUMIF(ShipToDubai!C:C, B67, ShipToDubai!F:F) - (SUMIFS(Stock_Transactions!D:D, Stock_Transactions!B:B, B67, Stock_Transactions!D:D, "<0") * -1) -> 0 | J67: =SUMIF(ShipToDubai!C:C, B67, ShipToDubai!G:G) -> 0
A68: =A67+1 -> 66 | B68: IPHONE CABLE | C68: =SUMIFS(Stock_Transactions!D:D, Stock_Transactions!B:B, B68, Stock_Transactions!D:D, ">0") -> 108 | D68: =SUMIFS(Stock_Transactions!D:D, Stock_Transactions!B:B, B68, Stock_Transactions!D:D, "<0") * -1 -> 108 | E68: =C68-D68 -> 0 | F68: =E68-G68-H68-I68-J68 -> 0 | G68: =SUMIF(Pending_Stock!C:C, B68, Pending_Stock!F:F) -> 0 | H68: =SUMIF(Pending_Stock!I:I, B68, Pending_Stock!L:L) -> 0 | I68: =SUMIF(ShipToDubai!C:C, B68, ShipToDubai!F:F) - (SUMIFS(Stock_Transactions!D:D, Stock_Transactions!B:B, B68, Stock_Transactions!D:D, "<0") * -1) -> 0 | J68: =SUMIF(ShipToDubai!C:C, B68, ShipToDubai!G:G) -> 0
A69: =A68+1 -> 67 | B69: GOOGLE TV STREAMER | C69: =SUMIFS(Stock_Transactions!D:D, Stock_Transactions!B:B, B69, Stock_Transactions!D:D, ">0") -> 501 | D69: =SUMIFS(Stock_Transactions!D:D, Stock_Transactions!B:B, B69, Stock_Transactions!D:D, "<0") * -1 -> 500 | E69: =C69-D69 -> 1 | F69: =E69-G69-H69-I69-J69 -> 0 | G69: =SUMIF(Pending_Stock!C:C, B69, Pending_Stock!F:F) -> 0 | H69: =SUMIF(Pending_Stock!I:I, B69, Pending_Stock!L:L) -> 0 | I69: =SUMIF(ShipToDubai!C:C, B69, ShipToDubai!F:F) - (SUMIFS(Stock_Transactions!D:D, Stock_Transactions!B:B, B69, Stock_Transactions!D:D, "<0") * -1) -> 1 | J69: =SUMIF(ShipToDubai!C:C, B69, ShipToDubai!G:G) -> 0
A70: =A69+1 -> 68 | B70: CANON CAMERA | C70: =SUMIFS(Stock_Transactions!D:D, Stock_Transactions!B:B, B70, Stock_Transactions!D:D, ">0") -> 5 | D70: =SUMIFS(Stock_Transactions!D:D, Stock_Transactions!B:B, B70, Stock_Transactions!D:D, "<0") * -1 -> 5 | E70: =C70-D70 -> 0 | F70: =E70-G70-H70-I70-J70 -> 0 | G70: =SUMIF(Pending_Stock!C:C, B70, Pending_Stock!F:F) -> 0 | H70: =SUMIF(Pending_Stock!I:I, B70, Pending_Stock!L:L) -> 0 | I70: =SUMIF(ShipToDubai!C:C, B70, ShipToDubai!F:F) - (SUMIFS(Stock_Transactions!D:D, Stock_Transactions!B:B, B70, Stock_Transactions!D:D, "<0") * -1) -> 0 | J70: =SUMIF(ShipToDubai!C:C, B70, ShipToDubai!G:G) -> 0
A71: =A70+1 -> 69 | B71: DJI OSMO POCKET 3 COMBO | C71: =SUMIFS(Stock_Transactions!D:D, Stock_Transactions!B:B, B71, Stock_Transactions!D:D, ">0") -> 116 | D71: =SUMIFS(Stock_Transactions!D:D, Stock_Transactions!B:B, B71, Stock_Transactions!D:D, "<0") * -1 -> 113 | E71: =C71-D71 -> 3 | F71: =E71-G71-H71-I71-J71 -> 0 | G71: =SUMIF(Pending_Stock!C:C, B71, Pending_Stock!F:F) -> 0 | H71: =SUMIF(Pending_Stock!I:I, B71, Pending_Stock!L:L) -> 0 | I71: =SUMIF(ShipToDubai!C:C, B71, ShipToDubai!F:F) - (SUMIFS(Stock_Transactions!D:D, Stock_Transactions!B:B, B71, Stock_Transactions!D:D, "<0") * -1) -> 3 | J71: =SUMIF(ShipToDubai!C:C, B71, ShipToDubai!G:G) -> 0
A72: =A71+1 -> 70 | B72: CANON GX70 | C72: =SUMIFS(Stock_Transactions!D:D, Stock_Transactions!B:B, B72, Stock_Transactions!D:D, ">0") -> 2 | D72: =SUMIFS(Stock_Transactions!D:D, Stock_Transactions!B:B, B72, Stock_Transactions!D:D, "<0") * -1 -> 2 | E72: =C72-D72 -> 0 | F72: =E72-G72-H72-I72-J72 -> 0 | G72: =SUMIF(Pending_Stock!C:C, B72, Pending_Stock!F:F) -> 0 | H72: =SUMIF(Pending_Stock!I:I, B72, Pending_Stock!L:L) -> 0 | I72: =SUMIF(ShipToDubai!C:C, B72, ShipToDubai!F:F) - (SUMIFS(Stock_Transactions!D:D, Stock_Transactions!B:B, B72, Stock_Transactions!D:D, "<0") * -1) -> 0 | J72: =SUMIF(ShipToDubai!C:C, B72, ShipToDubai!G:G) -> 0
A73: =A72+1 -> 71 | B73: CANON SX740 | C73: =SUMIFS(Stock_Transactions!D:D, Stock_Transactions!B:B, B73, Stock_Transactions!D:D, ">0") -> 181 | D73: =SUMIFS(Stock_Transactions!D:D, Stock_Transactions!B:B, B73, Stock_Transactions!D:D, "<0") * -1 -> 181 | E73: =C73-D73 -> 0 | F73: =E73-G73-H73-I73-J73 -> -1 | G73: =SUMIF(Pending_Stock!C:C, B73, Pending_Stock!F:F) -> 0 | H73: =SUMIF(Pending_Stock!I:I, B73, Pending_Stock!L:L) -> 0 | I73: =SUMIF(ShipToDubai!C:C, B73, ShipToDubai!F:F) - (SUMIFS(Stock_Transactions!D:D, Stock_Transactions!B:B, B73, Stock_Transactions!D:D, "<0") * -1) -> 1 | J73: =SUMIF(ShipToDubai!C:C, B73, ShipToDubai!G:G) -> 0 | L73: ok
A74: =A73+1 -> 72 | B74: SONY GM II Lense | C74: =SUMIFS(Stock_Transactions!D:D, Stock_Transactions!B:B, B74, Stock_Transactions!D:D, ">0") -> 1 | D74: =SUMIFS(Stock_Transactions!D:D, Stock_Transactions!B:B, B74, Stock_Transactions!D:D, "<0") * -1 -> 1 | E74: =C74-D74 -> 0 | F74: =E74-G74-H74-I74-J74 -> 0 | G74: =SUMIF(Pending_Stock!C:C, B74, Pending_Stock!F:F) -> 0 | H74: =SUMIF(Pending_Stock!I:I, B74, Pending_Stock!L:L) -> 0 | I74: =SUMIF(ShipToDubai!C:C, B74, ShipToDubai!F:F) - (SUMIFS(Stock_Transactions!D:D, Stock_Transactions!B:B, B74, Stock_Transactions!D:D, "<0") * -1) -> 0 | J74: =SUMIF(ShipToDubai!C:C, B74, ShipToDubai!G:G) -> 0 | L74: ok
A75: =A74+1 -> 73 | B75: DJI MIC 2 | C75: =SUMIFS(Stock_Transactions!D:D, Stock_Transactions!B:B, B75, Stock_Transactions!D:D, ">0") -> 134 | D75: =SUMIFS(Stock_Transactions!D:D, Stock_Transactions!B:B, B75, Stock_Transactions!D:D, "<0") * -1 -> 134 | E75: =C75-D75 -> 0 | F75: =E75-G75-H75-I75-J75 -> 0 | G75: =SUMIF(Pending_Stock!C:C, B75, Pending_Stock!F:F) -> 0 | H75: =SUMIF(Pending_Stock!I:I, B75, Pending_Stock!L:L) -> 0 | I75: =SUMIF(ShipToDubai!C:C, B75, ShipToDubai!F:F) - (SUMIFS(Stock_Transactions!D:D, Stock_Transactions!B:B, B75, Stock_Transactions!D:D, "<0") * -1) -> 0 | J75: =SUMIF(ShipToDubai!C:C, B75, ShipToDubai!G:G) -> 0
A76: =A75+1 -> 74 | B76: RAYBAN WAYFARER | C76: =SUMIFS(Stock_Transactions!D:D, Stock_Transactions!B:B, B76, Stock_Transactions!D:D, ">0") -> 2 | D76: =SUMIFS(Stock_Transactions!D:D, Stock_Transactions!B:B, B76, Stock_Transactions!D:D, "<0") * -1 -> 2 | E76: =C76-D76 -> 0 | F76: =E76-G76-H76-I76-J76 -> 0 | G76: =SUMIF(Pending_Stock!C:C, B76, Pending_Stock!F:F) -> 0 | H76: =SUMIF(Pending_Stock!I:I, B76, Pending_Stock!L:L) -> 0 | I76: =SUMIF(ShipToDubai!C:C, B76, ShipToDubai!F:F) - (SUMIFS(Stock_Transactions!D:D, Stock_Transactions!B:B, B76, Stock_Transactions!D:D, "<0") * -1) -> 0 | J76: =SUMIF(ShipToDubai!C:C, B76, ShipToDubai!G:G) -> 0
A77: =A76+1 -> 75 | B77: Beats Power Pro Buds | C77: =SUMIFS(Stock_Transactions!D:D, Stock_Transactions!B:B, B77, Stock_Transactions!D:D, ">0") -> 4 | D77: =SUMIFS(Stock_Transactions!D:D, Stock_Transactions!B:B, B77, Stock_Transactions!D:D, "<0") * -1 -> 2 | E77: =C77-D77 -> 2 | F77: =E77-G77-H77-I77-J77 -> 0 | G77: =SUMIF(Pending_Stock!C:C, B77, Pending_Stock!F:F) -> 0 | H77: =SUMIF(Pending_Stock!I:I, B77, Pending_Stock!L:L) -> 0 | I77: =SUMIF(ShipToDubai!C:C, B77, ShipToDubai!F:F) - (SUMIFS(Stock_Transactions!D:D, Stock_Transactions!B:B, B77, Stock_Transactions!D:D, "<0") * -1) -> 2 | J77: =SUMIF(ShipToDubai!C:C, B77, ShipToDubai!G:G) -> 0
A78: =A77+1 -> 76 | B78: DJI MAVIC 4 PRO | C78: =SUMIFS(Stock_Transactions!D:D, Stock_Transactions!B:B, B78, Stock_Transactions!D:D, ">0") -> 49 | D78: =SUMIFS(Stock_Transactions!D:D, Stock_Transactions!B:B, B78, Stock_Transactions!D:D, "<0") * -1 -> 49 | E78: =C78-D78 -> 0 | F78: =E78-G78-H78-I78-J78 -> 0 | G78: =SUMIF(Pending_Stock!C:C, B78, Pending_Stock!F:F) -> 0 | H78: =SUMIF(Pending_Stock!I:I, B78, Pending_Stock!L:L) -> 0 | I78: =SUMIF(ShipToDubai!C:C, B78, ShipToDubai!F:F) - (SUMIFS(Stock_Transactions!D:D, Stock_Transactions!B:B, B78, Stock_Transactions!D:D, "<0") * -1) -> 0 | J78: =SUMIF(ShipToDubai!C:C, B78, ShipToDubai!G:G) -> 0 | L78: ok
A79: =A78+1 -> 77 | B79: DJI MAVIC 4 PRO COMBO | C79: =SUMIFS(Stock_Transactions!D:D, Stock_Transactions!B:B, B79, Stock_Transactions!D:D, ">0") -> 71 | D79: =SUMIFS(Stock_Transactions!D:D, Stock_Transactions!B:B, B79, Stock_Transactions!D:D, "<0") * -1 -> 68 | E79: =C79-D79 -> 3 | F79: =E79-G79-H79-I79-J79 -> 0 | G79: =SUMIF(Pending_Stock!C:C, B79, Pending_Stock!F:F) -> 0 | H79: =SUMIF(Pending_Stock!I:I, B79, Pending_Stock!L:L) -> 0 | I79: =SUMIF(ShipToDubai!C:C, B79, ShipToDubai!F:F) - (SUMIFS(Stock_Transactions!D:D, Stock_Transactions!B:B, B79, Stock_Transactions!D:D, "<0") * -1) -> 3 | J79: =SUMIF(ShipToDubai!C:C, B79, ShipToDubai!G:G) -> 0
A80: =A79+1 -> 78 | B80: Meta Quest 3 256 GB | C80: =SUMIFS(Stock_Transactions!D:D, Stock_Transactions!B:B, B80, Stock_Transactions!D:D, ">0") -> 2 | D80: =SUMIFS(Stock_Transactions!D:D, Stock_Transactions!B:B, B80, Stock_Transactions!D:D, "<0") * -1 -> 2 | E80: =C80-D80 -> 0 | F80: =E80-G80-H80-I80-J80 -> 0 | G80: =SUMIF(Pending_Stock!C:C, B80, Pending_Stock!F:F) -> 0 | H80: =SUMIF(Pending_Stock!I:I, B80, Pending_Stock!L:L) -> 0 | I80: =SUMIF(ShipToDubai!C:C, B80, ShipToDubai!F:F) - (SUMIFS(Stock_Transactions!D:D, Stock_Transactions!B:B, B80, Stock_Transactions!D:D, "<0") * -1) -> 0 | J80: =SUMIF(ShipToDubai!C:C, B80, ShipToDubai!G:G) -> 0
A81: =A80+1 -> 79 | B81: PS5 Pro | C81: =SUMIFS(Stock_Transactions!D:D, Stock_Transactions!B:B, B81, Stock_Transactions!D:D, ">0") -> 333 | D81: =SUMIFS(Stock_Transactions!D:D, Stock_Transactions!B:B, B81, Stock_Transactions!D:D, "<0") * -1 -> 329 | E81: =C81-D81 -> 4 | F81: =E81-G81-H81-I81-J81 -> 0 | G81: =SUMIF(Pending_Stock!C:C, B81, Pending_Stock!F:F) -> 0 | H81: =SUMIF(Pending_Stock!I:I, B81, Pending_Stock!L:L) -> 0 | I81: =SUMIF(ShipToDubai!C:C, B81, ShipToDubai!F:F) - (SUMIFS(Stock_Transactions!D:D, Stock_Transactions!B:B, B81, Stock_Transactions!D:D, "<0") * -1) -> 4 | J81: =SUMIF(ShipToDubai!C:C, B81, ShipToDubai!G:G) -> 0
A82: =A81+1 -> 80 | B82: PS5 Disc | C82: =SUMIFS(Stock_Transactions!D:D, Stock_Transactions!B:B, B82, Stock_Transactions!D:D, ">0") -> 288 | D82: =SUMIFS(Stock_Transactions!D:D, Stock_Transactions!B:B, B82, Stock_Transactions!D:D, "<0") * -1 -> 285 | E82: =C82-D82 -> 3 | F82: =E82-G82-H82-I82-J82 -> 1 | G82: =SUMIF(Pending_Stock!C:C, B82, Pending_Stock!F:F) -> 0 | H82: =SUMIF(Pending_Stock!I:I, B82, Pending_Stock!L:L) -> 0 | I82: =SUMIF(ShipToDubai!C:C, B82, ShipToDubai!F:F) - (SUMIFS(Stock_Transactions!D:D, Stock_Transactions!B:B, B82, Stock_Transactions!D:D, "<0") * -1) -> 2 | J82: =SUMIF(ShipToDubai!C:C, B82, ShipToDubai!G:G) -> 0 | L82: 4 extre
A83: =A82+1 -> 81 | B83: PS5 Digital | C83: =SUMIFS(Stock_Transactions!D:D, Stock_Transactions!B:B, B83, Stock_Transactions!D:D, ">0") -> 316 | D83: =SUMIFS(Stock_Transactions!D:D, Stock_Transactions!B:B, B83, Stock_Transactions!D:D, "<0") * -1 -> 316 | E83: =C83-D83 -> 0 | F83: =E83-G83-H83-I83-J83 -> 0 | G83: =SUMIF(Pending_Stock!C:C, B83, Pending_Stock!F:F) -> 0 | H83: =SUMIF(Pending_Stock!I:I, B83, Pending_Stock!L:L) -> 0 | I83: =SUMIF(ShipToDubai!C:C, B83, ShipToDubai!F:F) - (SUMIFS(Stock_Transactions!D:D, Stock_Transactions!B:B, B83, Stock_Transactions!D:D, "<0") * -1) -> 0 | J83: =SUMIF(ShipToDubai!C:C, B83, ShipToDubai!G:G) -> 0
A84: =A83+1 -> 82 | B84: CANON G7X Mark II | C84: =SUMIFS(Stock_Transactions!D:D, Stock_Transactions!B:B, B84, Stock_Transactions!D:D, ">0") -> 15 | D84: =SUMIFS(Stock_Transactions!D:D, Stock_Transactions!B:B, B84, Stock_Transactions!D:D, "<0") * -1 -> 15 | E84: =C84-D84 -> 0 | F84: =E84-G84-H84-I84-J84 -> 0 | G84: =SUMIF(Pending_Stock!C:C, B84, Pending_Stock!F:F) -> 0 | H84: =SUMIF(Pending_Stock!I:I, B84, Pending_Stock!L:L) -> 0 | I84: =SUMIF(ShipToDubai!C:C, B84, ShipToDubai!F:F) - (SUMIFS(Stock_Transactions!D:D, Stock_Transactions!B:B, B84, Stock_Transactions!D:D, "<0") * -1) -> 0 | J84: =SUMIF(ShipToDubai!C:C, B84, ShipToDubai!G:G) -> 0
A85: =A84+1 -> 83 | B85: CANON G7X Mark III | C85: =SUMIFS(Stock_Transactions!D:D, Stock_Transactions!B:B, B85, Stock_Transactions!D:D, ">0") -> 269 | D85: =SUMIFS(Stock_Transactions!D:D, Stock_Transactions!B:B, B85, Stock_Transactions!D:D, "<0") * -1 -> 265 | E85: =C85-D85 -> 4 | F85: =E85-G85-H85-I85-J85 -> 3 | G85: =SUMIF(Pending_Stock!C:C, B85, Pending_Stock!F:F) -> 0 | H85: =SUMIF(Pending_Stock!I:I, B85, Pending_Stock!L:L) -> 0 | I85: =SUMIF(ShipToDubai!C:C, B85, ShipToDubai!F:F) - (SUMIFS(Stock_Transactions!D:D, Stock_Transactions!B:B, B85, Stock_Transactions!D:D, "<0") * -1) -> 1 | J85: =SUMIF(ShipToDubai!C:C, B85, ShipToDubai!G:G) -> 0
A86: =A85+1 -> 84 | B86: 35 mm Lense | C86: =SUMIFS(Stock_Transactions!D:D, Stock_Transactions!B:B, B86, Stock_Transactions!D:D, ">0") -> 6 | D86: =SUMIFS(Stock_Transactions!D:D, Stock_Transactions!B:B, B86, Stock_Transactions!D:D, "<0") * -1 -> 6 | E86: =C86-D86 -> 0 | F86: =E86-G86-H86-I86-J86 -> 0 | G86: =SUMIF(Pending_Stock!C:C, B86, Pending_Stock!F:F) -> 0 | H86: =SUMIF(Pending_Stock!I:I, B86, Pending_Stock!L:L) -> 0 | I86: =SUMIF(ShipToDubai!C:C, B86, ShipToDubai!F:F) - (SUMIFS(Stock_Transactions!D:D, Stock_Transactions!B:B, B86, Stock_Transactions!D:D, "<0") * -1) -> 0 | J86: =SUMIF(ShipToDubai!C:C, B86, ShipToDubai!G:G) -> 0 | L86: ok
A87: =A86+1 -> 85 | B87: San Disk 64 GB SD card | C87: =SUMIFS(Stock_Transactions!D:D, Stock_Transactions!B:B, B87, Stock_Transactions!D:D, ">0") -> 5 | D87: =SUMIFS(Stock_Transactions!D:D, Stock_Transactions!B:B, B87, Stock_Transactions!D:D, "<0") * -1 -> 5 | E87: =C87-D87 -> 0 | F87: =E87-G87-H87-I87-J87 -> 0 | G87: =SUMIF(Pending_Stock!C:C, B87, Pending_Stock!F:F) -> 0 | H87: =SUMIF(Pending_Stock!I:I, B87, Pending_Stock!L:L) -> 0 | I87: =SUMIF(ShipToDubai!C:C, B87, ShipToDubai!F:F) - (SUMIFS(Stock_Transactions!D:D, Stock_Transactions!B:B, B87, Stock_Transactions!D:D, "<0") * -1) -> 0 | J87: =SUMIF(ShipToDubai!C:C, B87, ShipToDubai!G:G) -> 0 | L87: ok
A88: =A87+1 -> 86 | B88: Skyline V2 Pouch | C88: =SUMIFS(Stock_Transactions!D:D, Stock_Transactions!B:B, B88, Stock_Transactions!D:D, ">0") -> 6 | D88: =SUMIFS(Stock_Transactions!D:D, Stock_Transactions!B:B, B88, Stock_Transactions!D:D, "<0") * -1 -> 1 | E88: =C88-D88 -> 5 | F88: =E88-G88-H88-I88-J88 -> 0 | G88: =SUMIF(Pending_Stock!C:C, B88, Pending_Stock!F:F) -> 0 | H88: =SUMIF(Pending_Stock!I:I, B88, Pending_Stock!L:L) -> 0 | I88: =SUMIF(ShipToDubai!C:C, B88, ShipToDubai!F:F) - (SUMIFS(Stock_Transactions!D:D, Stock_Transactions!B:B, B88, Stock_Transactions!D:D, "<0") * -1) -> 5 | J88: =SUMIF(ShipToDubai!C:C, B88, ShipToDubai!G:G) -> 0 | L88: ok
A89: =A88+1 -> 87 | B89: DJI MINI 4k FLY MORE COMBO | C89: =SUMIFS(Stock_Transactions!D:D, Stock_Transactions!B:B, B89, Stock_Transactions!D:D, ">0") -> 72 | D89: =SUMIFS(Stock_Transactions!D:D, Stock_Transactions!B:B, B89, Stock_Transactions!D:D, "<0") * -1 -> 72 | E89: =C89-D89 -> 0 | F89: =E89-G89-H89-I89-J89 -> 0 | G89: =SUMIF(Pending_Stock!C:C, B89, Pending_Stock!F:F) -> 0 | H89: =SUMIF(Pending_Stock!I:I, B89, Pending_Stock!L:L) -> 0 | I89: =SUMIF(ShipToDubai!C:C, B89, ShipToDubai!F:F) - (SUMIFS(Stock_Transactions!D:D, Stock_Transactions!B:B, B89, Stock_Transactions!D:D, "<0") * -1) -> 0 | J89: =SUMIF(ShipToDubai!C:C, B89, ShipToDubai!G:G) -> 0 | L89: ok
A90: =A89+1 -> 88 | B90: DJI MINI 4 PRO | C90: =SUMIFS(Stock_Transactions!D:D, Stock_Transactions!B:B, B90, Stock_Transactions!D:D, ">0") -> 79 | D90: =SUMIFS(Stock_Transactions!D:D, Stock_Transactions!B:B, B90, Stock_Transactions!D:D, "<0") * -1 -> 64 | E90: =C90-D90 -> 15 | F90: =E90-G90-H90-I90-J90 -> 0 | G90: =SUMIF(Pending_Stock!C:C, B90, Pending_Stock!F:F) -> 0 | H90: =SUMIF(Pending_Stock!I:I, B90, Pending_Stock!L:L) -> 0 | I90: =SUMIF(ShipToDubai!C:C, B90, ShipToDubai!F:F) - (SUMIFS(Stock_Transactions!D:D, Stock_Transactions!B:B, B90, Stock_Transactions!D:D, "<0") * -1) -> 15 | J90: =SUMIF(ShipToDubai!C:C, B90, ShipToDubai!G:G) -> 0 | L90: ok
A91: =A90+1 -> 89 | B91: CANON IXUS 285 | C91: =SUMIFS(Stock_Transactions!D:D, Stock_Transactions!B:B, B91, Stock_Transactions!D:D, ">0") -> 33 | D91: =SUMIFS(Stock_Transactions!D:D, Stock_Transactions!B:B, B91, Stock_Transactions!D:D, "<0") * -1 -> 32 | E91: =C91-D91 -> 1 | F91: =E91-G91-H91-I91-J91 -> 0 | G91: =SUMIF(Pending_Stock!C:C, B91, Pending_Stock!F:F) -> 0 | H91: =SUMIF(Pending_Stock!I:I, B91, Pending_Stock!L:L) -> 0 | I91: =SUMIF(ShipToDubai!C:C, B91, ShipToDubai!F:F) - (SUMIFS(Stock_Transactions!D:D, Stock_Transactions!B:B, B91, Stock_Transactions!D:D, "<0") * -1) -> 1 | J91: =SUMIF(ShipToDubai!C:C, B91, ShipToDubai!G:G) -> 0
A92: =A91+1 -> 90 | B92: CANON LENSE | C92: =SUMIFS(Stock_Transactions!D:D, Stock_Transactions!B:B, B92, Stock_Transactions!D:D, ">0") -> 2 | D92: =SUMIFS(Stock_Transactions!D:D, Stock_Transactions!B:B, B92, Stock_Transactions!D:D, "<0") * -1 -> 2 | E92: =C92-D92 -> 0 | F92: =E92-G92-H92-I92-J92 -> 0 | G92: =SUMIF(Pending_Stock!C:C, B92, Pending_Stock!F:F) -> 0 | H92: =SUMIF(Pending_Stock!I:I, B92, Pending_Stock!L:L) -> 0 | I92: =SUMIF(ShipToDubai!C:C, B92, ShipToDubai!F:F) - (SUMIFS(Stock_Transactions!D:D, Stock_Transactions!B:B, B92, Stock_Transactions!D:D, "<0") * -1) -> 0 | J92: =SUMIF(ShipToDubai!C:C, B92, ShipToDubai!G:G) -> 0
A93: =A92+1 -> 91 | B93: Ipad Pro 13" W+C Black 256gb | C93: =SUMIFS(Stock_Transactions!D:D, Stock_Transactions!B:B, B93, Stock_Transactions!D:D, ">0") -> 98 | D93: =SUMIFS(Stock_Transactions!D:D, Stock_Transactions!B:B, B93, Stock_Transactions!D:D, "<0") * -1 -> 97 | E93: =C93-D93 -> 1 | F93: =E93-G93-H93-I93-J93 -> 0 | G93: =SUMIF(Pending_Stock!C:C, B93, Pending_Stock!F:F) -> 0 | H93: =SUMIF(Pending_Stock!I:I, B93, Pending_Stock!L:L) -> 0 | I93: =SUMIF(ShipToDubai!C:C, B93, ShipToDubai!F:F) - (SUMIFS(Stock_Transactions!D:D, Stock_Transactions!B:B, B93, Stock_Transactions!D:D, "<0") * -1) -> 1 | J93: =SUMIF(ShipToDubai!C:C, B93, ShipToDubai!G:G) -> 0 | L93: ok
A94: =A93+1 -> 92 | B94: Ipad Pro 13" W+C Black 512gb | C94: =SUMIFS(Stock_Transactions!D:D, Stock_Transactions!B:B, B94, Stock_Transactions!D:D, ">0") -> 16 | D94: =SUMIFS(Stock_Transactions!D:D, Stock_Transactions!B:B, B94, Stock_Transactions!D:D, "<0") * -1 -> 16 | E94: =C94-D94 -> 0 | F94: =E94-G94-H94-I94-J94 -> 0 | G94: =SUMIF(Pending_Stock!C:C, B94, Pending_Stock!F:F) -> 0 | H94: =SUMIF(Pending_Stock!I:I, B94, Pending_Stock!L:L) -> 0 | I94: =SUMIF(ShipToDubai!C:C, B94, ShipToDubai!F:F) - (SUMIFS(Stock_Transactions!D:D, Stock_Transactions!B:B, B94, Stock_Transactions!D:D, "<0") * -1) -> 0 | J94: =SUMIF(ShipToDubai!C:C, B94, ShipToDubai!G:G) -> 0
A95: =A94+1 -> 93 | B95: Ipad Pro 13" W+C 2TB | C95: =SUMIFS(Stock_Transactions!D:D, Stock_Transactions!B:B, B95, Stock_Transactions!D:D, ">0") -> 8 | D95: =SUMIFS(Stock_Transactions!D:D, Stock_Transactions!B:B, B95, Stock_Transactions!D:D, "<0") * -1 -> 7 | E95: =C95-D95 -> 1 | F95: =E95-G95-H95-I95-J95 -> 0 | G95: =SUMIF(Pending_Stock!C:C, B95, Pending_Stock!F:F) -> 0 | H95: =SUMIF(Pending_Stock!I:I, B95, Pending_Stock!L:L) -> 0 | I95: =SUMIF(ShipToDubai!C:C, B95, ShipToDubai!F:F) - (SUMIFS(Stock_Transactions!D:D, Stock_Transactions!B:B, B95, Stock_Transactions!D:D, "<0") * -1) -> 1 | J95: =SUMIF(ShipToDubai!C:C, B95, ShipToDubai!G:G) -> 0 | L95: ok
A96: =A95+1 -> 94 | B96: Ipad Air M3 128gb | C96: =SUMIFS(Stock_Transactions!D:D, Stock_Transactions!B:B, B96, Stock_Transactions!D:D, ">0") -> 1 | D96: =SUMIFS(Stock_Transactions!D:D, Stock_Transactions!B:B, B96, Stock_Transactions!D:D, "<0") * -1 -> 1 | E96: =C96-D96 -> 0 | F96: =E96-G96-H96-I96-J96 -> 0 | G96: =SUMIF(Pending_Stock!C:C, B96, Pending_Stock!F:F) -> 0 | H96: =SUMIF(Pending_Stock!I:I, B96, Pending_Stock!L:L) -> 0 | I96: =SUMIF(ShipToDubai!C:C, B96, ShipToDubai!F:F) - (SUMIFS(Stock_Transactions!D:D, Stock_Transactions!B:B, B96, Stock_Transactions!D:D, "<0") * -1) -> 0 | J96: =SUMIF(ShipToDubai!C:C, B96, ShipToDubai!G:G) -> 0
A97: =A96+1 -> 95 | B97: iPad Pro 11 256 Cellular Unlock | C97: =SUMIFS(Stock_Transactions!D:D, Stock_Transactions!B:B, B97, Stock_Transactions!D:D, ">0") -> 39 | D97: =SUMIFS(Stock_Transactions!D:D, Stock_Transactions!B:B, B97, Stock_Transactions!D:D, "<0") * -1 -> 39 | E97: =C97-D97 -> 0 | F97: =E97-G97-H97-I97-J97 -> 0 | G97: =SUMIF(Pending_Stock!C:C, B97, Pending_Stock!F:F) -> 0 | H97: =SUMIF(Pending_Stock!I:I, B97, Pending_Stock!L:L) -> 0 | I97: =SUMIF(ShipToDubai!C:C, B97, ShipToDubai!F:F) - (SUMIFS(Stock_Transactions!D:D, Stock_Transactions!B:B, B97, Stock_Transactions!D:D, "<0") * -1) -> 0 | J97: =SUMIF(ShipToDubai!C:C, B97, ShipToDubai!G:G) -> 0 | L97: ok
A98: =A97+1 -> 96 | B98: Apple Watch Ultra 2 49mm | C98: =SUMIFS(Stock_Transactions!D:D, Stock_Transactions!B:B, B98, Stock_Transactions!D:D, ">0") -> 84 | D98: =SUMIFS(Stock_Transactions!D:D, Stock_Transactions!B:B, B98, Stock_Transactions!D:D, "<0") * -1 -> 82 | E98: =C98-D98 -> 2 | F98: =E98-G98-H98-I98-J98 -> 0 | G98: =SUMIF(Pending_Stock!C:C, B98, Pending_Stock!F:F) -> 0 | H98: =SUMIF(Pending_Stock!I:I, B98, Pending_Stock!L:L) -> 0 | I98: =SUMIF(ShipToDubai!C:C, B98, ShipToDubai!F:F) - (SUMIFS(Stock_Transactions!D:D, Stock_Transactions!B:B, B98, Stock_Transactions!D:D, "<0") * -1) -> 2 | J98: =SUMIF(ShipToDubai!C:C, B98, ShipToDubai!G:G) -> 0 | L98: ok
A99: =A98+1 -> 97 | B99: iPhone16 Pro Max 256 | C99: =SUMIFS(Stock_Transactions!D:D, Stock_Transactions!B:B, B99, Stock_Transactions!D:D, ">0") -> 540 | D99: =SUMIFS(Stock_Transactions!D:D, Stock_Transactions!B:B, B99, Stock_Transactions!D:D, "<0") * -1 -> 528 | E99: =C99-D99 -> 12 | F99: =E99-G99-H99-I99-J99 -> -3 | G99: =SUMIF(Pending_Stock!C:C, B99, Pending_Stock!F:F) -> 0 | H99: =SUMIF(Pending_Stock!I:I, B99, Pending_Stock!L:L) -> 0 | I99: =SUMIF(ShipToDubai!C:C, B99, ShipToDubai!F:F) - (SUMIFS(Stock_Transactions!D:D, Stock_Transactions!B:B, B99, Stock_Transactions!D:D, "<0") * -1) -> 15 | J99: =SUMIF(ShipToDubai!C:C, B99, ShipToDubai!G:G) -> 0
A100: =A99+1 -> 98 | B100: Iphone 16 PM 512 GB | C100: =SUMIFS(Stock_Transactions!D:D, Stock_Transactions!B:B, B100, Stock_Transactions!D:D, ">0") -> 44 | D100: =SUMIFS(Stock_Transactions!D:D, Stock_Transactions!B:B, B100, Stock_Transactions!D:D, "<0") * -1 -> 42 | E100: =C100-D100 -> 2 | F100: =E100-G100-H100-I100-J100 -> 0 | G100: =SUMIF(Pending_Stock!C:C, B100, Pending_Stock!F:F) -> 0 | H100: =SUMIF(Pending_Stock!I:I, B100, Pending_Stock!L:L) -> 0 | I100: =SUMIF(ShipToDubai!C:C, B100, ShipToDubai!F:F) - (SUMIFS(Stock_Transactions!D:D, Stock_Transactions!B:B, B100, Stock_Transactions!D:D, "<0") * -1) -> 2 | J100: =SUMIF(ShipToDubai!C:C, B100, ShipToDubai!G:G) -> 0
...

Sheet GST
G2: GST
B3: from month to month | I3: from month to month
B4: Australia | I4: Newzeland
B5: Date | C5: Product Name | D5: Qty | E5: Per/Unit (AUD) | F5: Total (AUD) | G5: GST | I5: Date | J5: Product Name | K5: Qty | L5: Per/Unit | M5: Total | N5: GST
B6: 45701 | C6: Instax Wide 400 5units $188 WB | D6: 5 | E6: 188 | F6: =E6*D6 -> 940 | G6: =F6/11 -> 85.454545 | I6: 45672 | J6: Starlink v4 19Units @580 WB | K6: 19 | L6: 580 | M6: =L6*K6 -> 11020 | N6: =M6*13.04/100 -> 1437.008
B7: 45701 | C7: JBL Charge5 125Units $133.30 WB | D7: 125 | E7: 133.3 | F7: =E7*D7 -> 16662.5 | G7: =F7/11 -> 1514.7727 | M7: =L7*K7 -> 0 | N7: =M7*13.04/100 -> 0
F8: =E8*D8 -> 0 | G8: =F8/11 -> 0 | I8: 45695 | J8: Starlink Mini 500 Units $630 WB | K8: 500 | L8: 630 | M8: =L8*K8 -> 315000 | N8: =M8*13.04/100 -> 41076
F9: =E9*D9 -> 0 | G9: =F9/11 -> 0 | I9: 45695 | J9: JBL Charge 5 150Units $148 WB | K9: 150 | L9: 148 | M9: =L9*K9 -> 22200 | N9: =M9*13.04/100 -> 2894.88
B10: 45709 | C10: IMAC 1 unit $1919 WB Card | D10: 1 | E10: 1919 | F10: =E10*D10 -> 1919 | G10: =F10/11 -> 174.45455 | I10: 45695 | J10: JBL Charge 5 50Units $145 WB | K10: 50 | L10: 145 | M10: =L10*K10 -> 7250 | N10: =M10*13.04/100 -> 945.4
B11: 45709 | C11: IMAC 1 unit $1934 WB Card | D11: 1 | E11: 1934 | F11: =E11*D11 -> 1934 | G11: =F11/11 -> 175.81818 | I11: 45695 | J11: Google Chrome Cast 250Units $149 WB | K11: 250 | L11: 149 | M11: =L11*K11 -> 37250 | N11: =M11*13.04/100 -> 4857.4
B12: 45709 | C12: Macbook M4 with Airpods 4 NC 7 Units $2349 WB Card | D12: 7 | E12: 2349 | F12: =E12*D12 -> 16443 | G12: =F12/11 -> 1494.8182 | M12: =L12*K12 -> 0 | N12: =M12*13.04/100 -> 0
B13: 45709 | C13: Macbook M4 with Airpods 4 NC 1 Unit $2349 ARB Card | D13: 1 | E13: 2349 | F13: =E13*D13 -> 2349 | G13: =F13/11 -> 213.54545 | I13: 45705 | J13: Google Chrome Cast 250Units $149 WB | K13: 250 | L13: 149 | M13: =L13*K13 -> 37250 | N13: =M13*13.04/100 -> 4857.4
B14: 45709 | C14: Macbook M4 with Airpods 4 NC 1 Unit $ 2349 (apple Hornsby Pending collection) WB Card | D14: 1 | E14: 2349 | F14: =E14*D14 -> 2349 | G14: =F14/11 -> 213.54545 | M14: =L14*K14 -> 0 | N14: =M14*13.04/100 -> 0
B15: 45709 | C15: Instax wide 400 10 Units $ 188 (Harvey Norman Castle Hills Pending collection) | D15: 10 | E15: 188 | F15: =E15*D15 -> 1880 | G15: =F15/11 -> 170.90909 | I15: 45706 | J15: Starlink V4 200Units $549 WB | K15: 200 | L15: 549 | M15: =L15*K15 -> 109800 | N15: =M15*13.04/100 -> 14317.92
B16: 45709 | C16: Innstax mini Evo 1 unit $248 HN CH | D16: 1 | E16: 248 | F16: =E16*D16 -> 248 | G16: =F16/11 -> 22.545455 | I16: 45706 | J16: JBL Charge.5 6Units $145 WB | K16: 6 | L16: 145 | M16: =L16*K16 -> 870 | N16: =M16*13.04/100 -> 113.448
B17: 45709 | C17: Instax Li Play 1 Unit $203 HN CH | D17: 1 | E17: 203 | F17: =E17*D17 -> 203 | G17: =F17/11 -> 18.454545 | I17: 45706 | J17: PS5 15Units $695 ARB | K17: 15 | L17: 695 | M17: =L17*K17 -> 10425 | N17: =M17*13.04/100 -> 1359.42
B18: 45709 | C18: Instax mini 40 1 unit $143 HN CH | D18: 1 | E18: 143 | F18: =E18*D18 -> 143 | G18: =F18/11 -> 13 | M18: =L18*K18 -> 0 | N18: =M18*13.04/100 -> 0
B19: 45709 | C19: Instax mini 99 Bundle 1 unit $250 JBHIFI CH | D19: 1 | E19: 250 | F19: =E19*D19 -> 250 | G19: =F19/11 -> 22.727273 | I19: 45727 | J19: Starlink V4 ($80,000 Paid) | K19: 153 | L19: 520 | M19: =L19*K19 -> 79560 | N19: =M19*13.04/100 -> 10374.624
F20: =E20*D20 -> 0 | G20: =F20/11 -> 0 | I20: 45727 | J20: Google streamer (In System Google Chrome Cast) ($37,500 Paid) | K20: 250 | L20: 149 | M20: =L20*K20 -> 37250 | N20: =M20*13.04/100 -> 4857.4
F21: =E21*D21 -> 0 | G21: =F21/11 -> 0 | M21: =L21*K21 -> 0 | N21: =M21*13.04/100 -> 0
F22: =E22*D22 -> 0 | G22: =F22/11 -> 0 | I22: 45750 | J22: 10 PS5 Purchased in NZ $759 | K22: 10 | L22: 759 | M22: =L22*K22 -> 7590 | N22: =M22*13.04/100 -> 989.736
B23: 45710 | C23: Mac Book 4 Anwar Ali | D23: 3 | E23: 2364 | F23: =E23*D23 -> 7092 | G23: =F23/11 -> 644.72727 | M23: =L23*K23 -> 0 | N23: =M23*13.04/100 -> 0
B24: 45710 | C24: Mac Book 4 Noaman Mughal | D24: 10 | E24: 2349 | F24: =E24*D24 -> 23490 | G24: =F24/11 -> 2135.4545 | I24: 45784 | J24: Starlink V4 Noel Leeming | K24: 147 | L24: 520 | M24: =L24*K24 -> 76440 | N24: =M24*13.04/100 -> 9967.776
B25: 45711 | C25: Mac Book 4 Waheed NAB CR Card | D25: 1 | E25: 2349 | F25: =E25*D25 -> 2349 | G25: =F25/11 -> 213.54545 | I25: 45784 | J25: Instax Flim 20 pack Noel Leeming | K25: 500 | L25: 28.99 | M25: =L25*K25 -> 14495 | N25: =M25*13.04/100 -> 1890.148
B26: 45711 | C26: Mac Book 4 Waheed NAB CR Card | D26: 1 | E26: 2349 | F26: =E26*D26 -> 2349 | I26: 45784 | J26: Instax Mini Evo Noel Leeming | K26: 200 | L26: 328.99 | M26: =L26*K26 -> 65798 | N26: =M26*13.04/100 -> 8580.0592
B27: 45711 | C27: IMac4 Waheed NAB CR Card | D27: 1 | E27: 1919 | F27: =E27*D27 -> 1919 | G27: =F27/11 -> 174.45455 | I27: 45784 | J27: PS5 Astrobot Noel Leeming | K27: 10 | L27: 759 | M27: =L27*K27 -> 7590 | N27: =M27*13.04/100 -> 989.736
F28: =E28*D28 -> 0 | G28: =F28/11 -> 0 | I28: 45784 | J28: PS5 Astrobot Noel Leeming | K28: 10 | L28: 759 | M28: =L28*K28 -> 7590 | N28: =M28*13.04/100 -> 989.736
B29: 45714 | C29: Mac Book 4 AMGT Cards | D29: 4 | E29: 2349 | F29: =E29*D29 -> 9396 | G29: =F29/11 -> 854.18182 | I29: 45784 | J29: PS5 Astrobot Noel Leeming | K29: 2 | L29: 759 | M29: =L29*K29 -> 1518 | N29: =M29*13.04/100 -> 197.9472
B30: 45714 | C30: Mac Book 4 Waheed Card | D30: 3 | E30: 2349 | F30: =E30*D30 -> 7047 | G30: =F30/11 -> 640.63636 | I30: 45784 | J30: PS5 Astrobot Noel Leeming | K30: 2 | L30: 759 | M30: =L30*K30 -> 1518 | N30: =M30*13.04/100 -> 197.9472
F31: =E31*D31 -> 0 | G31: =F31/11 -> 0 | I31: 45784 | J31: PS5 Astrobot Noel Leeming | K31: 10 | L31: 759 | M31: =L31*K31 -> 7590 | N31: =M31*13.04/100 -> 989.736
B32: 45715 | C32: Mac Book 4 AMGT Cards | D32: 3 | E32: 2349 | F32: =E32*D32 -> 7047 | G32: =F32/11 -> 640.63636 | I32: 45784 | J32: Google Tv Streamer Noel Leeming | K32: 250 | L32: 149 | M32: =L32*K32 -> 37250 | N32: =M32*13.04/100 -> 4857.4
B33: 45715 | C33: Mac Book 4 Waheed Card | D33: 10 | E33: 2349 | F33: =E33*D33 -> 23490 | G33: =F33/11 -> 2135.4545 | I33: 45784 | J33: Instax Flim 20 pack Noel Leeming | K33: 200 | L33: 28.99 | M33: =L33*K33 -> 5798 | N33: =M33*13.04/100 -> 756.0592
F34: =E34*D34 -> 0 | G34: =F34/11 -> 0 | M34: =L34*K34 -> 0 | N34: =M34*13.04/100 -> 0
F35: =E35*D35 -> 0 | G35: =F35/11 -> 0 | M35: =L35*K35 -> 0 | N35: =M35*13.04/100 -> 0
B36: 45718 | C36: Mac Book Pro 14 inc M4 (Waheed GC) | D36: 1 | E36: 2349 | F36: =E36*D36 -> 2349 | G36: =F36/11 -> 213.54545 | I36: 45785 | J36: Canon Camera Noel Leeming | K36: 5 | L36: 755 | M36: =L36*K36 -> 3775 | N36: =M36*13.04/100 -> 492.26
B37: 45718 | C37: Mac Book Pro 14 inc M4 (Waheed GC) | D37: 1 | E37: 2364 | F37: =E37*D37 -> 2364 | G37: =F37/11 -> 214.90909 | I37: 45785 | J37: Osmo Pocket 3 Noel Leeming | K37: 5 | L37: 965 | M37: =L37*K37 -> 4825 | N37: =M37*13.04/100 -> 629.18
B38: 45719 | C38: Mac Book Pro 14 inc M4 (Waheed GC) | D38: 1 | E38: 2349 | F38: =E38*D38 -> 2349 | G38: =F38/11 -> 213.54545 | I38: 45785 | J38: Osmo Pocket 3 Creator Combo Noel Leeming | K38: 5 | L38: 1205 | M38: =L38*K38 -> 6025 | N38: =M38*13.04/100 -> 785.66
B39: 45719 | C39: Mac Book Pro 14 inc M4 (Waheed GC) | D39: 1 | E39: 2364 | F39: =E39*D39 -> 2364 | G39: =F39/11 -> 214.90909 | M39: =L39*K39 -> 0 | N39: =M39*13.04/100 -> 0
B40: 45720 | C40: Mac Book Pro 14 inc M4 (Waheed GC) | D40: 2 | E40: 2349 | F40: =E40*D40 -> 4698 | G40: =F40/11 -> 427.09091 | M40: =L40*K40 -> 0 | N40: =M40*13.04/100 -> 0
B41: 45720 | C41: Mac Book Pro 14 inc M4 (Waheed GC) | D41: 1 | E41: 2364 | F41: =E41*D41 -> 2364 | G41: =F41/11 -> 214.90909 | I41: 45805 | J41: Starlink V4 200 * $492 | K41: 200 | L41: 492 | M41: =L41*K41 -> 98400 | N41: =M41*13.04/100 -> 12831.36
B42: 45720 | C42: Mac Book Pro 14 inc M4 (Waheed ) | D42: 5 | E42: 2349 | F42: =E42*D42 -> 11745 | G42: =F42/11 -> 1067.7273 | I42: 45805 | J42: Mini EVO 100 * $329 | K42: 100 | L42: 329 | M42: =L42*K42 -> 32900 | N42: =M42*13.04/100 -> 4290.16
B43: 45721 | C43: Mac Book Pro 14 inc (Abdul Mujid Canada ) | D43: 1 | E43: 2349 | F43: =E43*D43 -> 2349 | G43: =F43/11 -> 213.54545 | I43: 45805 | J43: Canon 740 qty 10* $745 | K43: 20 | L43: 745 | M43: =L43*K43 -> 14900 | N43: =M43*13.04/100 -> 1942.96
B44: 45721 | C44: Mac Book Pro 14 inc M4 (Waheed GC) | D44: 3 | E44: 2349 | F44: =E44*D44 -> 7047 | G44: =F44/11 -> 640.63636 | M44: =L44*K44 -> 0 | N44: =M44*13.04/100 -> 0
B45: 45722 | C45: Mac Book Pro 14 inc M4 (Waheed GC) | D45: 3 | E45: 2364 | F45: =E45*D45 -> 7092 | G45: =F45/11 -> 644.72727 | I45: 45813 | J45: Starlink V4 200 * $492 | K45: 300 | L45: 492 | M45: =L45*K45 -> 147600 | N45: =M45*13.04/100 -> 19247.04
B46: 45722 | C46: Mac Book Pro 14 inc M4 (Waheed ) | D46: 1 | E46: 2349 | F46: =E46*D46 -> 2349 | G46: =F46/11 -> 213.54545 | I46: 45813 | J46: Google Streamer 250 * $149 | K46: 250 | L46: 149 | M46: =L46*K46 -> 37250 | N46: =M46*13.04/100 -> 4857.4
B47: 45723 | C47: Mac Book Pro 14 inc M4 (Waheed GC) | D47: 2 | E47: 2364 | F47: =E47*D47 -> 4728 | G47: =F47/11 -> 429.81818 | M47: =L47*K47 -> 0 | N47: =M47*13.04/100 -> 0
B48: 45724 | C48: Mac Book Pro 14 inc (Warda canada) | D48: 1 | E48: 2349 | F48: =E48*D48 -> 2349 | G48: =F48/11 -> 213.54545 | I48: 45831 | J48: Canon SX740 Photo Warehouse online Pending Delivery | K48: 4 | L48: 775 | M48: =L48*K48 -> 3100 | N48: =M48*13.04/100 -> 404.24
B49: 45724 | C49: Mac Book Pro 14 inc M4 (Waheed ) | D49: 5 | E49: 2349 | F49: =E49*D49 -> 11745 | G49: =F49/11 -> 1067.7273 | M49: =L49*K49 -> 0 | N49: =M49*13.04/100 -> 0
B50: 45727 | C50: Mac Book Pro 14 inc M4 (Waheed GC) | D50: 2 | E50: 2349 | F50: =E50*D50 -> 4698 | G50: =F50/11 -> 427.09091 | I50: 45831 | J50: Canon SX740 Photo Warehouse online Pending Delivery | K50: 4 | L50: 775 | M50: =L50*K50 -> 3100 | N50: =M50*13.04/100 -> 404.24
B51: 45727 | C51: Mac Book Pro 14 inc M4 (Waheed ) | D51: 2 | E51: 2349 | F51: =E51*D51 -> 4698 | G51: =F51/11 -> 427.09091 | M51: =L51*K51 -> 0 | N51: =M51*13.04/100 -> 0
B52: 45728 | C52: Mac Book Pro 14 inc M4 (Waheed GC) | D52: 2 | E52: 2349 | F52: =E52*D52 -> 4698 | G52: =F52/11 -> 427.09091 | I52: 45839 | J52: Mark II with memory card and pouch Photo WH | K52: 5 | L52: 1380 | M52: =L52*K52 -> 6900 | N52: =M52*13.04/100 -> 899.76
B53: 45729 | C53: Mac Book Air 13 inc (Waheed ) | D53: 9 | E53: 1549 | F53: =E53*D53 -> 13941 | G53: =F53/11 -> 1267.3636 | I53: 45839 | J53: Canon Mark II Photo WH | K53: 1 | L53: 1295 | M53: =L53*K53 -> 1295 | N53: =M53*13.04/100 -> 168.868
B54: 45729 | C54: Mac Book Air 13 inc (Abdul Rehman ) | D54: 2 | E54: 1549 | F54: =E54*D54 -> 3098 | G54: =F54/11 -> 281.63636 | I54: 45839 | J54: Canon Mark III Photo WH | K54: 1 | L54: 1375 | M54: =L54*K54 -> 1375
F55: =E55*D55 -> 0 | G55: =F55/11 -> 0 | I55: 45839 | J55: Lense Photo WH | K55: 1 | L55: 852 | M55: =L55*K55 -> 852 | N55: =M55*13.04/100 -> 111.1008
B56: 45730 | C56: PS5 JBHIFI (Roselands Pending collection) | D56: 5 | E56: 679 | F56: =E56*D56 -> 3395 | G56: =F56/11 -> 308.63636 | I56: 45839 | J56: SX740 Photo WH | K56: 4 | L56: 679 | M56: =L56*K56 -> 2716 | N56: =M56*13.04/100 -> 354.1664
B57: 45730 | C57: Instax Mini 99 Bundle JBHIFI Roselands Pending collection | D57: 8 | E57: 229 | F57: =E57*D57 -> 1832 | G57: =F57/11 -> 166.54545 | M57: =L57*K57 -> 0 | N57: =M57*13.04/100 -> 0
B58: 45730 | C58: PS5 jbhifi Bankstown collected | D58: 2 | E58: 679 | F58: =E58*D58 -> 1358 | G58: =F58/11 -> 123.45455 | I58: 45840 | J58: Mark II photogear | K58: 2 | L58: 1229 | M58: =L58*K58 -> 2458 | N58: =M58*13.04/100 -> 320.5232
B59: 45730 | C59: Instax Mini 99 Bundle | D59: 6 | E59: 235 | F59: =E59*D59 -> 1410 | G59: =F59/11 -> 128.18182 | I59: 45840 | J59: Lense photogear | K59: 1 | L59: 852 | M59: =L59*K59 -> 852 | N59: =M59*13.04/100 -> 111.1008
B60: 45731 | C60: PS5 JBHIFI Parramatta collected $679 | D60: 3 | E60: 679 | F60: =E60*D60 -> 2037 | G60: =F60/11 -> 185.18182 | I60: 45840 | J60: SX740 Progear | K60: 3 | L60: 765.71 | M60: =L60*K60 -> 2297.13 | N60: =M60*13.04/100 -> 299.54575
B61: 45731 | C61: 2 PS5 JBHIFI Merrylands $679 | D61: 2 | E61: 679 | F61: =E61*D61 -> 1358 | G61: =F61/11 -> 123.45455 | I61: 45840 | J61: G7X Mark III Silver Progear | K61: 1 | L61: 1345 | M61: =L61*K61 -> 1345 | N61: =M61*13.04/100 -> 175.388
F62: =E62*D62 -> 0 | G62: =F62/11 -> 0 | I62: 45840 | J62: SX740 Progear | K62: 3 | L62: 738 | M62: =L62*K62 -> 2214 | N62: =M62*13.04/100 -> 288.7056
B63: 45733 | C63: 5 PS5 $679 JBHIFI Maq Park | D63: 5 | E63: 679 | F63: =E63*D63 -> 3395 | G63: =F63/11 -> 308.63636 | I63: 45840 | J63: Lense Progear | K63: 1 | L63: 852 | M63: =L63*K63 -> 852 | N63: =M63*13.04/100 -> 111.1008
B64: 45733 | C64: 3 Instax Mini 99 Bundle $235 pending collection | D64: 3 | E64: 235 | F64: =E64*D64 -> 705 | G64: =F64/11 -> 64.090909 | I64: 45840 | J64: Sx740 Photo WH City | K64: 1 | L64: 775 | M64: =L64*K64 -> 775 | N64: =M64*13.04/100 -> 101.06
B65: 45733 | C65: 1 Instax Wide 400 $190 | D65: 1 | E65: 190 | F65: =E65*D65 -> 190 | G65: =F65/11 -> 17.272727 | I65: 45840 | J65: G7X Mark II Photo WH City | K65: 1 | L65: 1295 | M65: =L65*K65 -> 1295 | N65: =M65*13.04/100 -> 168.868
B66: 45733 | C66: 3 PS5 $679 JBHIFI NR | D66: 3 | E66: 679 | F66: =E66*D66 -> 2037 | G66: =F66/11 -> 185.18182 | I66: 45840 | J66: G7X Mark III Photo WH City | K66: 1 | L66: 1375 | M66: =L66*K66 -> 1375 | N66: =M66*13.04/100 -> 179.3
B67: 45733 | C67: 2 Instax mini 99 $229 JBHIFI NR | D67: 2 | E67: 229 | F67: =E67*D67 -> 458 | G67: =F67/11 -> 41.636364 | I67: 45840 | J67: Lense Photo WH City | K67: 1 | L67: 852 | M67: =L67*K67 -> 852 | N67: =M67*13.04/100 -> 111.1008
B68: 45733 | C68: 17 Starlink mini $575 AUD | D68: 17 | E68: 575 | F68: =E68*D68 -> 9775 | G68: =F68/11 -> 888.63636 | I68: 45840 | J68: G7X Mark II Rubber Monkey online Delivered Abdul Pending | K68: 1 | L68: 1228 | M68: =L68*K68 -> 1228 | N68: =M68*13.04/100 -> 160.1312
F69: =E69*D69 -> 0 | G69: =F69/11 -> 0 | I69: 45840 | J69: Sx740 Rubber Monkey online Delivered Abdul Pending | K69: 1 | L69: 750 | M69: =L69*K69 -> 750 | N69: =M69*13.04/100 -> 97.8
B70: 45734 | C70: PS5 $679 JBHIFI Parramatta | D70: 3 | E70: 679 | F70: =E70*D70 -> 2037 | G70: =F70/11 -> 185.18182 | M70: =L70*K70 -> 0 | N70: =M70*13.04/100 -> 0
F71: =E71*D71 -> 0 | G71: =F71/11 -> 0 | I71: 45841 | J71: G7X Mark II Auckland Camera centre | K71: 4 | L71: 1197 | M71: =L71*K71 -> 4788 | N71: =M71*13.04/100 -> 624.3552
B72: 45735 | C72: ps5 JBHIFI Homebush $679 | D72: 2 | E72: 679 | F72: =E72*D72 -> 1358 | G72: =F72/11 -> 123.45455 | I72: 45841 | J72: Lense Auckland Camera centre | K72: 1 | L72: 852 | M72: =L72*K72 -> 852 | N72: =M72*13.04/100 -> 111.1008
B73: 45735 | C73: PS5 JBHIFI Roselands | D73: 3 | E73: 679 | F73: =E73*D73 -> 2037 | G73: =F73/11 -> 185.18182 | I73: 45841 | J73: Deposit Lense Auckland Camera centre | K73: 1 | L73: 338 | M73: =L73*K73 -> 338 | N73: =M73*13.04/100 -> 44.0752
B74: 45735 | C74: Intax mini 99 bundle $229 JBHIFI Roselands | D74: 3 | E74: 229 | F74: =E74*D74 -> 687 | G74: =F74/11 -> 62.454545 | I74: 45840 | J74: Mark III photo wearhouse | K74: 1 | L74: 1375 | M74: =L74*K74 -> 1375 | N74: =M74*13.04/100 -> 179.3
B75: 45735 | C75: Ps5 JBHIFI Bankstown $679 | D75: 3 | E75: 679 | F75: =E75*D75 -> 2037 | G75: =F75/11 -> 185.18182 | I75: 45840 | J75: SX740 photo wearhouse | K75: 1 | L75: 775 | M75: =L75*K75 -> 775 | N75: =M75*13.04/100 -> 101.06
B76: 45735 | C76: PS5 EB GAMES $679 | D76: 2 | E76: 679 | F76: =E76*D76 -> 1358 | G76: =F76/11 -> 123.45455 | I76: 45841 | J76: Sx740 Harvey norman Mount Roskills Pending Collection | K76: 4 | L76: 766 | M76: =L76*K76 -> 3064 | N76: =M76*13.04/100 -> 399.5456
F77: =E77*D77 -> 0 | G77: =F77/11 -> 0 | M77: =L77*K77 -> 0 | N77: =M77*13.04/100 -> 0
B78: 45736 | C78: 1 PS5 $679 EB GAMES | D78: 1 | E78: 679 | F78: =E78*D78 -> 679 | G78: =F78/11 -> 61.727273 | M78: =L78*K78 -> 0 | N78: =M78*13.04/100 -> 0
B79: 45736 | C79: 1 AirPods eBay $163 | D79: 1 | E79: 163 | F79: =E79*D79 -> 163 | G79: =F79/11 -> 14.818182 | I79: 45844 | J79: V4 Standard Kit Noel Leeming | K79: 150 | L79: 494 | M79: =L79*K79 -> 74100 | N79: =M79*13.04/100 -> 9662.64
F80: =E80*D80 -> 0 | G80: =F80/11 -> 0 | M80: =L80*K80 -> 0 | N80: =M80*13.04/100 -> 0
B81: 45739 | C81: 1 MacBook Air 24/512 GB $2149 sky blue JBHIFI castle hills | D81: 1 | E81: 2149 | F81: =E81*D81 -> 2149 | G81: =F81/11 -> 195.36364 | I81: 45846 | J81: starlink V4 Noel Leeming | K81: 100 | L81: 494 | M81: =L81*K81 -> 49400 | N81: =M81*13.04/100 -> 6441.76
B82: 45739 | C82: MacBook Air 24/512 GB $2042 sky blue Office works castle hills pending collection | D82: 1 | E82: 2042 | F82: =E82*D82 -> 2042 | G82: =F82/11 -> 185.63636 | I82: 45848 | J82: Instax Wide 400 Noel Leeming | K82: 100 | L82: 229 | M82: =L82*K82 -> 22900 | N82: =M82*13.04/100 -> 2986.16
B83: 45739 | C83: 2 MacBook Air 24/512 GB $2090 sky blue Office works Northmead pending collection | D83: 2 | E83: 2090 | F83: =E83*D83 -> 4180 | G83: =F83/11 -> 380 | M83: =L83*K83 -> 0 | N83: =M83*13.04/100 -> 0
B84: 45739 | C84: 1 Instax mini Evo $275 office works Northmead | D84: 1 | E84: 275 | F84: =E84*D84 -> 275 | G84: =F84/11 -> 25 | I84: 45854 | J84: PS5 Console Noel Leeming | K84: 200 | L84: 728 | M84: =L84*K84 -> 145600 | N84: =M84*13.04/100 -> 18986.24
F85: =E85*D85 -> 0 | G85: =F85/11 -> 0 | I85: 45854 | J85: PS5 Controller Noel Leeming | K85: 80 | L85: 85 | M85: =L85*K85 -> 6800 | N85: =M85*13.04/100 -> 886.72
B86: 45740 | C86: 2 MacBook Air 24/512 GB $2090 sky blue Office works Auburn pending collection | D86: 2 | E86: 2090 | F86: =E86*D86 -> 4180 | G86: =F86/11 -> 380 | M86: =L86*K86 -> 0 | N86: =M86*13.04/100 -> 0
B87: 45740 | C87: 2 MacBook Air 24/512 GB $2090 sky blue Office works westRyde pending collection | D87: 2 | E87: 2090 | F87: =E87*D87 -> 4180 | G87: =F87/11 -> 380 | I87: 45861 | J87: G7X MARK III Black Progear Pending Collection | K87: 10 | L87: 1448.98 | M87: =L87*K87 -> 14489.8 | N87: =M87*13.04/100 -> 1889.4699
B88: 45740 | C88: 2 PS5 $695 Costco without Coupon | D88: 2 | E88: 695 | F88: =E88*D88 -> 1390 | G88: =F88/11 -> 126.36364 | I88: 45862 | J88: G7X MARK III Silver Progear Pending Collection | K88: 5 | L88: 1448.98 | M88: =L88*K88 -> 7244.9 | N88: =M88*13.04/100 -> 944.73496
F89: =E89*D89 -> 0 | G89: =F89/11 -> 0 | I89: 45863 | J89: Lenses Canon Progear Pending Collection | K89: 2 | L89: 852 | M89: =L89*K89 -> 1704 | N89: =M89*13.04/100 -> 222.2016
B90: 45742 | C90: 2 MacBook Air 24/512 GB $2090 sky blue Office works Northmead pending collection | D90: 2 | E90: 2090 | F90: =E90*D90 -> 4180 | G90: =F90/11 -> 380 | I90: 45862 | J90: Mark III Rubber Monkey online Pending Delivery Abdul NL | K90: 1 | L90: 1359 | M90: =L90*K90 -> 1359 | N90: =M90*13.04/100 -> 177.2136
B91: 45742 | C91: 1 MacBook Air 24/512 GB $2090 sky blue Office works West Ryde pending collection | D91: 1 | E91: 2090 | F91: =E91*D91 -> 2090 | G91: =F91/11 -> 190 | I91: 45865 | J91: SX740 Noel Leeming $4000 Deposit Paid | K91: 20 | L91: 720 | M91: =L91*K91 -> 14400 | N91: =M91*13.04/100 -> 1877.76
B92: 45742 | C92: 1 MacBook Air 24/512 GB $2090 Midnight Office works West Ryde pending collection | D92: 1 | E92: 2090 | F92: =E92*D92 -> 2090 | G92: =F92/11 -> 190 | I92: 29/072025 | J92: G7X MARK III Silver Auckland Camera centre | K92: 1 | L92: 1359 | M92: =L92*K92 -> 1359 | N92: =M92*13.04/100 -> 177.2136
B93: 45742 | C93: 2 MacBook Air 24/512 GB $2090 sky blue Office works North Ryde pending collection | D93: 2 | E93: 2090 | F93: =E93*D93 -> 4180 | G93: =F93/11 -> 380 | M93: =L93*K93 -> 0 | N93: =M93*13.04/100 -> 0
B94: 45742 | C94: 2 MacBook Air 24/512 GB $2090 sky blue Office works Five Dock pending collection | D94: 2 | E94: 2090 | F94: =E94*D94 -> 4180 | G94: =F94/11 -> 380 | I94: 45831 | J94: StarLink Mini (OLD Purchsing) | K94: 3 | L94: 550 | M94: =L94*K94 -> 1650 | N94: =M94*13.04/100 -> 215.16
B95: 45742 | C95: 2 MacBook Air 24/512 GB $2090 sky blue Office works Auburn pending collection | D95: 2 | E95: 2090 | F95: =E95*D95 -> 4180 | G95: =F95/11 -> 380 | I95: 45864 | J95: SX740 progear Deposit/ Pending Stock | K95: 10 | L95: 738 | M95: =L95*K95 -> 7380 | N95: =M95*13.04/100 -> 962.352
B96: 45742 | C96: 2 PS5 slim Astra Bot $669 EB Games | D96: 2 | E96: 669 | F96: =E96*D96 -> 1338 | G96: =F96/11 -> 121.63636 | I96: 45864 | J96: SX740 photogear Deposit/ Pending Stock | K96: 10 | L96: 738 | M96: =L96*K96 -> 7380 | N96: =M96*13.04/100 -> 962.352
F97: =E97*D97 -> 0 | G97: =F97/11 -> 0 | M97: =L97*K97 -> 0 | N97: =M97*13.04/100 -> 0
B98: 45742 | C98: PS5 Astro BOT JBHIFI Castle Hills | D98: 1 | E98: 699 | F98: =E98*D98 -> 699 | G98: =F98/11 -> 63.545455 | I98: 45873 | J98: Instax mini EVO Black Noel Leeming Pending Delivery | K98: 50 | L98: 329 | M98: =L98*K98 -> 16450 | N98: =M98*13.04/100 -> 2145.08
B99: 45742 | C99: Mac Book Air M4 24/512Midnight JBHIFI Castle Hills | D99: 1 | E99: 2149 | F99: =E99*D99 -> 2149 | G99: =F99/11 -> 195.36364 | I99: 45874 | J99: G7x Mark III Black Auckland Camera | K99: 1 | L99: 1449 | M99: =L99*K99 -> 1449 | N99: =M99*13.04/100 -> 188.9496
B100: 45742 | C100: Mac Book Air M4 24/512Midnight | D100: 5 | E100: 2199 | F100: =E100*D100 -> 10995 | G100: =F100/11 -> 999.54545 | I100: 45874 | J100: G7x Mark III Black Photo Warehouse Online | K100: 1 | L100: 1449 | M100: =L100*K100 -> 1449 | N100: =M100*13.04/100 -> 188.9496
B101: 45742 | C101: Iphone 16 Pro max 256 GB Desert | D101: 2 | E101: 1880.99 | F101: =E101*D101 -> 3761.98 | G101: =F101/11 -> 341.99818 | I101: 45874 | J101: G7x Mark III Black Progear Online | K101: 2 | L101: 1449 | M101: =L101*K101 -> 2898 | N101: =M101*13.04/100 -> 377.8992
...

Sheet Pending_Stock
B2: Australia | H2: Newzeland
B3: Purchase Date | C3: Product Name | D3: Qty (Total) | E3: Qty Received | F3: Qty Pending | H3: Purchase Date | I3: Product Name | J3: Qty (Total) | K3: Qty Received | L3: Qty Pending
B4: 45617 | C4: STARLINK MINI | D4: 1 | E4: 1 | F4: =D4-E4 -> 0 | H4: 45695 | I4: JBL CHARGE 5 | J4: 17 | K4: 17 | L4: =J4-K4 -> 0
B5: 45612 | C5: JBL CHARGE 5 | D5: 3 | E5: 3 | F5: =D5-E5 -> 0 | H5: 500 stock | I5: STARLINK MINI | J5: 100 | K5: 100 | L5: =J5-K5 -> 0
B6: 45644 | C6: JBL CHARGE 5 | D6: 32 | E6: 32 | F6: =D6-E6 -> 0 | L6: =J6-K6 -> 0 | N6: Formula for fetching Pending products quantity name wise from Australia table
B7: 45652 | C7: JBL CHARGE 5 | D7: 40 | E7: 40 | F7: =D7-E7 -> 0 | H7: 45831 | I7: CANON SX740 | J7: 4 | K7: 4 | L7: =J7-K7 -> 0 | N7: "=SUMIF(Pending_Stock!C:C, A2, Pending_Stock!F:F)"
B8: 45652 | C8: JBL CHARGE 5 | D8: 75 | E8: 75 | F8: =D8-E8 -> 0 | L8: =J8-K8 -> 0
B9: 45652 | C9: ESSENTIAL FLIP | D9: 10 | E9: 10 | F9: =D9-E9 -> 0 | H9: 45870 | I9: CANON G7X Mark III | J9: 10 | K9: 10 | L9: =J9-K9 -> 0
B10: 45652 | C10: MACBOOK M4 | D10: 1 | E10: 1 | F10: =D10-E10 -> 0 | H10: 45870 | I10: CANON G7X Mark III | J10: 5 | K10: 5 | L10: =J10-K10 -> 0 | N10: Formula for fetching Pending products quantity name wise from Newzeland table
B11: 45652 | C11: STARLINK HIGH.P KIT | D11: 11 | E11: 11 | F11: =D11-E11 -> 0 | H11: 45870 | I11: CANON LENSE | J11: 2 | K11: 2 | L11: =J11-K11 -> 0 | N11: =SUMIF(Pending_Stock!I:I, A3, Pending_Stock!L:L)'
F12: =D12-E12 -> 0 | H12: 45870 | I12: CANON G7X Mark III | J12: 1 | K12: 1 | L12: =J12-K12 -> 0
B13: 45709 | C13: MACBOOK M4 | D13: 1 | E13: 1 | F13: =D13-E13 -> 0 | H13: 45870 | I13: CANON SX740 | J13: 20 | K13: 20 | L13: =J13-K13 -> 0
B14: 45709 | C14: AIRPODS | D14: 1 | E14: 1 | F14: =D14-E14 -> 0 | H14: 45870 | I14: CANON G7X Mark III | J14: 1 | K14: 1 | L14: =J14-K14 -> 0
B15: 45709 | C15: INSTAX WIDE 400 | D15: 10 | E15: 10 | F15: =D15-E15 -> 0 | L15: =J15-K15 -> 0
F16: =D16-E16 -> 0 | H16: 45864 | I16: CANON SX740 | J16: 10 | K16: 10 | L16: =J16-K16 -> 0
B17: 45730 | C17: PS5 | D17: 5 | E17: 5 | F17: =D17-E17 -> 0 | H17: 45864 | I17: CANON SX740 | J17: 10 | K17: 10 | L17: =J17-K17 -> 0
B18: 45730 | C18: INSTAX MINI 99 BUNDEL | D18: 8 | E18: 8 | F18: =D18-E18 -> 0 | L18: =J18-K18 -> 0
F19: =D19-E19 -> 0 | H19: 45880 | I19: INSTAX MINI EVO | J19: 50 | K19: 50 | L19: =J19-K19 -> 0
B20: 45733 | C20: INSTAX MINI 99 BUNDEL | D20: 3 | E20: 3 | F20: =D20-E20 -> 0 | L20: =J20-K20 -> 0
F21: =D21-E21 -> 0 | H21: 45889 | I21: CANON SX740 | J21: 0 | L21: =J21-K21 -> 0 | M21: double purchase
B22: 45739 | C22: Macbook Air 24/512 GB | D22: 1 | E22: 1 | F22: =D22-E22 -> 0 | H22: 45889 | I22: CANON SX740 | J22: 0 | L22: =J22-K22 -> 0 | M22: double purchase
B23: 45739 | C23: Macbook Air 24/512 GB | D23: 2 | E23: 2 | F23: =D23-E23 -> 0 | H23: 45889 | I23: CANON SX740 | J23: 1 | K23: 1 | L23: =J23-K23 -> 0
B24: 45740 | C24: Macbook Air 24/512 GB | D24: 2 | E24: 2 | F24: =D24-E24 -> 0 | H24: 45889 | I24: CANON SX740 | J24: 4 | K24: 4 | L24: =J24-K24 -> 0
B25: 45740 | C25: Macbook Air 24/512 GB | D25: 2 | E25: 2 | F25: =D25-E25 -> 0 | H25: 45895 | I25: INSTAX MINI EVO | J25: 50 | K25: 50 | L25: =J25-K25 -> 0
F26: =D26-E26 -> 0 | H26: 45895 | I26: INSTAX MINI EVO | J26: 50 | K26: 50 | L26: =J26-K26 -> 0
B27: 45742 | C27: Macbook Air 24/512 GB | D27: 10 | E27: 10 | F27: =D27-E27 -> 0 | H27: 45957 | I27: CANON G7X Mark III | J27: 1 | K27: 1 | L27: =J27-K27 -> 0
B28: 45742 | C28: PS5 | D28: 2 | E28: 2 | F28: =D28-E28 -> 0 | H28: 45957 | I28: CANON G7X Mark III | J28: 2 | K28: 2 | L28: =J28-K28 -> 0
F29: =D29-E29 -> 0 | H29: 45958 | I29: CANON G7X Mark III | J29: 10 | K29: 10 | L29: =J29-K29 -> 0
B30: 45743 | C30: Macbook Air 24/512 GB | D30: 10 | E30: 10 | F30: =D30-E30 -> 0 | H30: 45958 | I30: CANON SX740 | J30: 3 | K30: 3 | L30: =J30-K30 -> 0
B31: 45743 | C31: Macbook Pro 16/512 | D31: 2 | E31: 2 | F31: =D31-E31 -> 0 | H31: 45958 | I31: CANON G7X Mark III | J31: 6 | K31: 6 | L31: =J31-K31 -> 0
F32: =D32-E32 -> 0 | H32: 45958 | I32: CANON G7X Mark III | J32: 1 | K32: 1 | L32: =J32-K32 -> 0
B33: 45744 | C33: Macbook Air 24/512 GB | D33: 2 | E33: 2 | F33: =D33-E33 -> 0 | H33: 45990 | I33: CANON G7X Mark III | J33: 1 | K33: 1 | L33: =J33-K33 -> 0
B34: 45744 | C34: Macbook Pro 16/512 | D34: 1 | E34: 1 | F34: =D34-E34 -> 0 | H34: 45990 | I34: CANON G7X Mark III | J34: 1 | K34: 1 | L34: =J34-K34 -> 0
B35: 45744 | C35: INSTAX MINI EVO | D35: 4 | E35: 4 | F35: =D35-E35 -> 0 | H35: 45990 | I35: CANON G7X Mark III | J35: 3 | K35: 3 | L35: =J35-K35 -> 0
B36: 45744 | C36: INSTAX MINI 12 | D36: 3 | E36: 3 | F36: =D36-E36 -> 0 | H36: 45990 | I36: CANON G7X Mark III | J36: 10 | K36: 10 | L36: =J36-K36 -> 0
F37: =D37-E37 -> 0 | H37: 45990 | I37: CANON G7X Mark III | J37: 12 | K37: 12 | L37: =J37-K37 -> 0
B38: 45745 | C38: Macbook Air 24/512 GB | D38: 2 | E38: 2 | F38: =D38-E38 -> 0 | H38: 45966 | I38: CANON G7X Mark III | J38: 10 | K38: 10 | L38: =J38-K38 -> 0
B39: 45745 | C39: Macbook Pro 16/512 | D39: 2 | E39: 2 | F39: =D39-E39 -> 0 | H39: 45966 | I39: CANON G7X Mark III | J39: 1 | K39: 1 | L39: =J39-K39 -> 0
B40: 45745 | C40: PS5 | D40: 1 | E40: 1 | F40: =D40-E40 -> 0 | H40: 45966 | I40: CANON SX740 | J40: 3 | K40: 3 | L40: =J40-K40 -> 0
B41: 45749 | C41: Macbook Pro 16/1TB | D41: 4 | E41: 4 | F41: =D41-E41 -> 0 | H41: 45966 | I41: CANON G7X Mark III | J41: 2 | K41: 2 | L41: =J41-K41 -> 0
B42: 45749 | C42: Macbook Air 24/512 GB | D42: 9 | E42: 9 | F42: =D42-E42 -> 0 | H42: 45966 | I42: CANON G7X Mark III | J42: 2 | K42: 2 | L42: =J42-K42 -> 0
B43: 45749 | C43: PS5 | D43: 1 | E43: 1 | F43: =D43-E43 -> 0 | H43: 46001 | I43: INSTAX FLIM 20 PACK | J43: 500 | K43: 500 | L43: =J43-K43 -> 0
B44: 45749 | C44: Meta Quest 3 512 | D44: 1 | E44: 1 | F44: =D44-E44 -> 0 | H44: 46001 | I44: INSTAX MINI EVO | J44: 100 | K44: 100 | L44: =J44-K44 -> 0
F45: =D45-E45 -> 0 | H45: 46001 | I45: INSTAX MINI EVO | J45: 100 | K45: 100 | L45: =J45-K45 -> 0
B46: 45747 | C46: INSTAX MINI EVO | D46: 10 | E46: 10 | F46: =D46-E46 -> 0 | H46: 46008 | I46: CANON SX740 | J46: 2 | K46: 2 | L46: =J46-K46 -> 0
B47: 45747 | C47: INSTAX MINI 12 | D47: 10 | E47: 10 | F47: =D47-E47 -> 0 | H47: 46013 | I47: CANON G7X Mark III | J47: 5 | K47: 5 | L47: =J47-K47 -> 0
F48: =D48-E48 -> 0 | H48: 46020 | I48: CANON G7X Mark III | J48: 4 | K48: 4 | L48: =J48-K48 -> 0
B49: 45750 | C49: PS5 | D49: 1 | E49: 1 | F49: =D49-E49 -> 0 | H49: 46078 | I49: CANON G7X Mark III | J49: 3 | K49: 3 | L49: =J49-K49 -> 0
F50: =D50-E50 -> 0 | H50: 46113 | I50: STARLINK V4 | J50: 10 | K50: 10 | L50: =J50-K50 -> 0
B51: 45751 | C51: Macbook Pro 16/512 | D51: 1 | E51: 1 | F51: =D51-E51 -> 0 | H51: 46113 | I51: CANON G7X Mark III | J51: 8 | K51: 8 | L51: =J51-K51 -> 0
F52: =D52-E52 -> 0 | H52: 46113 | I52: CANON G7X Mark III | J52: 5 | K52: 5 | L52: =J52-K52 -> 0
F53: =D53-E53 -> 0 | H53: 46113 | I53: CANON SX740 | J53: 4 | K53: 4 | L53: =J53-K53 -> 0
B54: 45757 | C54: PS5 | D54: 8 | E54: 8 | F54: =D54-E54 -> 0 | H54: 46114 | I54: CANON G7X Mark III | J54: 2 | K54: 2 | L54: =J54-K54 -> 0
B55: 45757 | C55: PS5 | D55: 2 | E55: 2 | F55: =D55-E55 -> 0 | H55: 46113 | I55: CANON G7X Mark III | J55: 4 | K55: 4 | L55: =J55-K55 -> 0
F56: =D56-E56 -> 0 | H56: 46113 | I56: CANON G7X Mark III | J56: 3 | K56: 3 | L56: =J56-K56 -> 0
B57: 45759 | C57: Macbook Air 24/512 GB | D57: 2 | E57: 2 | F57: =D57-E57 -> 0 | H57: 46113 | I57: CANON G7X Mark III | J57: 1 | K57: 1 | L57: =J57-K57 -> 0
B58: 45759 | C58: PS5 | D58: 1 | E58: 1 | F58: =D58-E58 -> 0 | H58: 46114 | I58: CANON G7X Mark III | J58: 3 | K58: 3 | L58: =J58-K58 -> 0
B59: 45759 | C59: PLAY STATION PORTAL | D59: 3 | E59: 3 | F59: =D59-E59 -> 0 | H59: 46114 | I59: CANON G7X Mark III | J59: 3 | K59: 3 | L59: =J59-K59 -> 0
F60: =D60-E60 -> 0 | H60: 46149 | I60: Minelab Gold Monster 2000 | J60: 2 | K60: 2 | L60: =J60-K60 -> 0
B61: 45759 | C61: Macbook Air 24/512 GB | D61: 15 | E61: 15 | F61: =D61-E61 -> 0 | H61: 46152 | I61: CANON G7X Mark III | J61: 4 | K61: 4 | L61: =J61-K61 -> 0
B62: 45759 | C62: Macbook Air 24/512 GB | D62: 10 | E62: 10 | F62: =D62-E62 -> 0 | H62: 46153 | I62: Instax Mini 13 | J62: 8 | K62: 8 | L62: =J62-K62 -> 0
B63: 45759 | C63: Macbook Air 24/512 GB | D63: 5 | E63: 5 | F63: =D63-E63 -> 0 | H63: 46154 | I63: CANON G7X Mark III | J63: 4 | K63: 4 | L63: =J63-K63 -> 0
F64: =D64-E64 -> 0 | H64: 46154 | I64: Minelab GPZ 8000 | J64: 1 | K64: 1 | L64: =J64-K64 -> 0
B65: 45759 | C65: Macbook Air 15 24/512 GB | D65: 10 | E65: 10 | F65: =D65-E65 -> 0 | H65: 46156 | I65: Minelab 1000 | J65: 12 | K65: 12 | L65: =J65-K65 -> 0
F66: =D66-E66 -> 0 | H66: 46156 | I66: CANON G7X Mark III | J66: 4 | K66: 4 | L66: =J66-K66 -> 0
B67: 45759 | C67: Dragon Age Game CD | D67: 20 | F67: =D67-E67 -> 20 | G67: p | H67: 46156 | I67: CANON G7X Mark III | J67: 4 | K67: 4 | L67: =J67-K67 -> 0
F68: =D68-E68 -> 0 | H68: 46158 | I68: Minelab GPZ 8000 | J68: 1 | K68: 1 | L68: =J68-K68 -> 0
B69: 45760 | C69: PS5 | D69: 18 | E69: 18 | F69: =D69-E69 -> 0 | H69: 46158 | I69: Instax Mini 13 | J69: 40 | K69: 40 | L69: =J69-K69 -> 0
B70: 45760 | C70: Macbook Air 15 24/512 GB | D70: 5 | E70: 5 | F70: =D70-E70 -> 0 | H70: 46158 | I70: Instax Mini 13 | J70: 40 | K70: 40 | L70: =J70-K70 -> 0
B71: 45760 | C71: PS5 | D71: 10 | E71: 10 | F71: =D71-E71 -> 0 | H71: 46160 | I71: CANON G7X Mark III | J71: 4 | K71: 4 | L71: =J71-K71 -> 0
F72: =D72-E72 -> 0 | H72: 46162 | I72: Instax Mini 13 | J72: 8 | K72: 8 | L72: =J72-K72 -> 0
B73: 45760 | C73: Dragon Age Game CD | D73: 20 | E73: 20 | F73: =D73-E73 -> 0 | H73: 46171 | I73: CANON G7X Mark III | J73: 2 | K73: 2 | L73: =J73-K73 -> 0
B74: 45760 | C74: PS5 | D74: 3 | E74: 3 | F74: =D74-E74 -> 0 | H74: 46171 | I74: CANON G7X Mark III | J74: 1 | K74: 1 | L74: =J74-K74 -> 0
F75: =D75-E75 -> 0 | H75: 46171 | I75: CANON G7X Mark III | J75: 9 | K75: 9 | L75: =J75-K75 -> 0
B76: 45762 | C76: Macbook Air 15 24/512 GB | D76: 2 | E76: 2 | F76: =D76-E76 -> 0 | H76: 46178 | I76: CANON G7X Mark III | J76: 4 | K76: 4 | L76: =J76-K76 -> 0
B77: 45762 | C77: Macbook Air 15 24/512 GB | D77: 1 | E77: 1 | F77: =D77-E77 -> 0 | H77: 46178 | I77: CANON G7X Mark III | J77: 4 | K77: 4 | L77: =J77-K77 -> 0
B78: 45762 | C78: Macbook Air 24/512 GB | D78: 2 | E78: 2 | F78: =D78-E78 -> 0
F79: =D79-E79 -> 0
B80: 45763 | C80: DJI OSMO Action 5 pro | D80: 2 | E80: 2 | F80: =D80-E80 -> 0 | G80: refund
B81: 45763 | C81: DJI OSMO POCKET 3 | D81: 4 | E81: 4 | F81: =D81-E81 -> 0 | G81: p
B82: 45763 | C82: DJI OSMO Mobile 7 P | D82: 2 | E82: 2 | F82: =D82-E82 -> 0 | G82: refund
F83: =D83-E83 -> 0
B84: 45769 | C84: RAYBAN GLASSES | D84: 5 | E84: 5 | F84: =D84-E84 -> 0
B85: 45769 | C85: RAYBAN GLASSES | D85: 1 | E85: 1 | F85: =D85-E85 -> 0
B86: 45769 | C86: Macbook Air 24/512 GB | D86: 9 | E86: 9 | F86: =D86-E86 -> 0
F87: =D87-E87 -> 0
B88: 45793 | C88: DJI MAVIC PRO RC | D88: 12 | E88: 12 | F88: =D88-E88 -> 0
B89: 45793 | C89: DJI MAVIC PRO RC COMBO | D89: 10 | E89: 10 | F89: =D89-E89 -> 0
F90: =D90-E90 -> 0
B91: 45794 | C91: RAYBAN WAYFARER | D91: 2 | E91: 2 | F91: =D91-E91 -> 0
F92: =D92-E92 -> 0
B93: 45794 | C93: CANON SX740 | D93: 4 | E93: 4 | F93: =D93-E93 -> 0
B94: 45795 | C94: DJI MIC 2 | D94: 2 | E94: 2 | F94: =D94-E94 -> 0
B95: 45795 | C95: DJI MIC 2 | D95: 30 | E95: 30 | F95: =D95-E95 -> 0
F96: =D96-E96 -> 0
F97: =D97-E97 -> 0
F98: =D98-E98 -> 0
B99: 45826 | C99: PS5 | D99: 1 | E99: 1 | F99: =D99-E99 -> 0
B100: 45826 | C100: SONY GM II Lense | D100: 1 | E100: 1 | F100: =D100-E100 -> 0
B101: 45832 | C101: PS5 | D101: 2 | E101: 2 | F101: =D101-E101 -> 0
...

Sheet ShipToDubai
C3: Shipping To Dubai
B4: Shipping Date | C4: Product Name | D4: Qty Shipped | E4: Status | F4: Qty Received | G4: Qty Remaining
B5: 20/02/2025 | C5: STARLINK V4 | D5: 201 | E5: Opening | F5: 201 | G5: =D5-F5 -> 0 | K5: HOLD STOCK AMGT
B6: 20/02/2025 | C6: STARLINK MINI | D6: 200 | E6: Opening | F6: 200 | G6: =D6-F6 -> 0 | K6: Product Name | L6: Qty
B7: 20/02/2025 | C7: JBL CHARGE 5 | D7: 17 | E7: Opening | F7: 17 | G7: =D7-F7 -> 0 | K7: PRINTER | L7: 1
B8: 20/02/2025 | C8: CHROME CAST | D8: 309 | E8: Opening | F8: 309 | G8: =D8-F8 -> 0
B9: 20/02/2025 | C9: PS5 | D9: 15 | E9: Opening | F9: 15 | G9: =D9-F9 -> 0 | K9: MACBOOK M3 | L9: 2
B10: 20/02/2025 | C10: BREVILLE COFFEE MACHINE | D10: 2 | E10: Opening | F10: 2 | G10: =D10-F10 -> 0 | K10: COFFEE MACHINE | L10: 1
B11: 20/02/2025 | C11: DELONGI COFFEE MACHINE | D11: 2 | E11: Opening | F11: 2 | G11: =D11-F11 -> 0 | K11: DYSON | L11: 2
B12: 20/02/2025 | C12: APPLE I MAC | D12: 5 | E12: Opening | F12: 5 | G12: =D12-F12 -> 0
B13: 20/02/2025 | C13: DYSON | D13: 2 | E13: Opening | F13: 2 | G13: =D13-F13 -> 0
B14: 20/02/2025 | C14: MACBOOK M3 | D14: 2 | E14: Opening | F14: 2 | G14: =D14-F14 -> 0
B15: 20/02/2025 | C15: STARLINK HIGH.P KIT | D15: 10 | E15: Opening | F15: 10 | G15: =D15-F15 -> 0
B16: 20/02/2025 | C16: APPLE WATCH ULTRA | D16: 1 | E16: Opening | F16: 1 | G16: =D16-F16 -> 0
B17: 20/02/2025 | C17: PRINTER | D17: 1 | E17: Opening | F17: 1 | G17: =D17-F17 -> 0
B18: 20/02/2025 | C18: DJI MAVIC PRO 3 DRONE | D18: 2 | E18: Opening | F18: 2 | G18: =D18-F18 -> 0
G19: =D19-F19 -> 0
B20: 45711 | C20: MACBOOK M4 | D20: 23 | E20: Received | F20: 23 | G20: =D20-F20 -> 0
B21: 45711 | C21: JBL CHARGE 5 | D21: 188 | E21: Received | F21: 188 | G21: =D21-F21 -> 0
B22: 45711 | C22: APPLE I MAC | D22: 2 | E22: Received | F22: 2 | G22: =D22-F22 -> 0
B23: 45711 | C23: AIRPODS | D23: 21 | E23: Received | F23: 21 | G23: =D23-F23 -> 0
B24: 45711 | C24: INSTAX WIDE 400 | D24: 5 | E24: Received | F24: 5 | G24: =D24-F24 -> 0
B25: 45711 | C25: INSTAX MINI EVO | D25: 1 | E25: Received | F25: 1 | G25: =D25-F25 -> 0
B26: 45711 | C26: INSTAX Li PLAY | D26: 1 | E26: Received | F26: 1 | G26: =D26-F26 -> 0
B27: 45711 | C27: INSTAX MINI 40 | D27: 1 | E27: Received | F27: 1 | G27: =D27-F27 -> 0
B28: 45711 | C28: INSTAX MINI 99 | D28: 1 | E28: Received | F28: 1 | G28: =D28-F28 -> 0
G29: =D29-F29 -> 0
B30: 45719 | C30: Meta Quest 3 512 | D30: 13 | E30: Purchased in Dubai | F30: 13 | G30: =D30-F30 -> 0
B31: 45719 | C31: iPhone16 Pro Max 256 | D31: 20 | E31: Purchased in Dubai | F31: 20 | G31: =D31-F31 -> 0
B32: 45719 | C32: iPad Pro 11 256 Cellular Unlock | D32: 4 | E32: Purchased in Dubai | F32: 4 | G32: =D32-F32 -> 0
B33: 45719 | C33: AIRPODS | D33: 4 | E33: Purchased in Dubai | F33: 4 | G33: =D33-F33 -> 0
B34: 45719 | C34: iPad Pro 11 256 Wifi Only | D34: 14 | E34: Purchased in Dubai | F34: 14 | G34: =D34-F34 -> 0
B35: 45719 | C35: iPad Air 13 128 Wifi Only | D35: 2 | E35: Purchased in Dubai | F35: 2 | G35: =D35-F35 -> 0
B36: 45719 | C36: iPad Air 13 256 Wifi Only | D36: 1 | E36: Purchased in Dubai | F36: 1 | G36: =D36-F36 -> 0
G37: =D37-F37 -> 0
B38: 45728 | C38: iPhone16 Pro 256 | D38: 2 | E38: Cell Wear Usa Purchase | F38: 2 | G38: =D38-F38 -> 0
B39: 45728 | C39: iPhone16 Pro 128 | D39: 1 | E39: Cell Wear Usa Purchase | F39: 1 | G39: =D39-F39 -> 0
B40: 45728 | C40: Meta Quest 3 512 | D40: 2 | E40: Cell Wear Usa Purchase | F40: 2 | G40: =D40-F40 -> 0
B41: 45728 | C41: Ps5 Controller Dual sense | D41: 12 | E41: Cell Wear Usa Purchase | F41: 12 | G41: =D41-F41 -> 0
B42: 45728 | C42: Beats Fit Pro | D42: 17 | E42: Cell Wear Usa Purchase | F42: 17 | G42: =D42-F42 -> 0
B43: 45728 | C43: Beats Studio Buds | D43: 7 | E43: Cell Wear Usa Purchase | F43: 7 | G43: =D43-F43 -> 0
B44: 45728 | C44: iPhone 15 Pro 256 | D44: 1 | E44: Cell Wear Usa Purchase | F44: 1 | G44: =D44-F44 -> 0
B45: 45728 | C45: iPhone 16 128 | D45: 1 | E45: Cell Wear Usa Purchase | F45: 1 | G45: =D45-F45 -> 0
B46: 45728 | C46: iPhone 14 Pro Max 128 | D46: 1 | E46: Cell Wear Usa Purchase | F46: 1 | G46: =D46-F46 -> 0
B47: 45728 | C47: Samsung Galaxy S25 Plus 256 | D47: 1 | E47: Cell Wear Usa Purchase | F47: 1 | G47: =D47-F47 -> 0
B48: 45728 | C48: iPhone16 Pro Max 256 | D48: 1 | E48: Cell Wear Usa Purchase | F48: 1 | G48: =D48-F48 -> 0
G49: =D49-F49 -> 0
B50: 45730 | C50: MACBOOK M4 | D50: 55 | E50: Received | F50: 55 | G50: =D50-F50 -> 0
B51: 45730 | C51: Macbook Air M4 13 inch | D51: 11 | E51: Received | F51: 11 | G51: =D51-F51 -> 0
B52: 45730 | C52: APPLE I MAC | D52: 1 | E52: Received | F52: 1 | G52: =D52-F52 -> 0
B53: 45730 | C53: AIRPODS | D53: 68 | E53: Received | F53: 68 | G53: =D53-F53 -> 0
B54: 45730 | C54: PS5 | D54: 2 | E54: Received | F54: 2 | G54: =D54-F54 -> 0
B55: 45730 | C55: INSTAX WIDE 400 | D55: 1 | E55: Received | F55: 1 | G55: =D55-F55 -> 0
B56: 45730 | C56: STARLINK MINI | D56: 17 | E56: Received | F56: 17 | G56: =D56-F56 -> 0
B57: 45730 | C57: INSTAX MINI 99 | D57: 1 | E57: Received | F57: 1 | G57: =D57-F57 -> 0
B58: 45730 | C58: CHROME CAST | D58: 250 | E58: Received | F58: 250 | G58: =D58-F58 -> 0
B59: 45730 | C59: STARLINK MINI | D59: 100 | E59: Received | F59: 100 | G59: =D59-F59 -> 0
B60: 45730 | C60: STARLINK V4 | D60: 153 | E60: Received | F60: 153 | G60: =D60-F60 -> 0
B61: 45730 | C61: INSTAX MINI 99 BUNDEL | D61: 6 | E61: Received | F61: 6 | G61: =D61-F61 -> 0
... B85: 45754 | C85: PS5 | D85: 10 | E85: Directly Purchased in Dubai | F85: 10 | G85: =D85-F85 -> 0
G86: =D86-F86 -> 0
B87: 45758 | C87: RAYBAN GLASSES | D87: 37 | E87: Directly Purchased in Dubai | F87: 37 | G87: =D87-F87 -> 0
B88: 45758 | C88: Meta Quest 3 512 | D88: 9 | E88: Purchase Owais Houston | F88: 9 | G88: =D88-F88 -> 0
B89: 45758 | C89: SONY BUDS | D89: 18 | E89: Purchase Owais Houston | F89: 18 | G89: =D89-F89 -> 0
B90: 45758 | C90: PLAY STATION PORTAL | D90: 1 | E90: Purchase Owais Houston | F90: 1 | G90: =D90-F90 -> 0
B91: 45758 | C91: PS5 SSD 2TB | D91: 30 | E91: Purchase Owais Houston | F91: 30 | G91: =D91-F91 -> 0
B92: 45758 | C92: APPLE AIRPODS PRO | D92: 12 | E92: Purchase Owais Houston | F92: 12 | G92: =D92-F92 -> 0
B93: 45758 | C93: AIRPODS | D93: 22 | E93: Purchase Owais Houston | F93: 22 | G93: =D93-F93 -> 0
B94: 45758 | C94: APPLE I MAC | D94: 2 | E94: Sale Ret from Shehzad | F94: 2 | G94: =D94-F94 -> 0
B95: 45761 | C95: Meta Quest 3 512 | D95: 5 | E95: Purchase from Blue Zone | F95: 5 | G95: =D95-F95 -> 0
B96: 45761 | C96: Meta Quest 3s 256 | D96: 3 | E96: Purchase from Shehzad | F96: 3 | G96: =D96-F96 -> 0
G97: =D97-F97 -> 0
B98: 45764 | C98: INSTAX FLIM 20 PACK | D98: 31 | E98: Received | F98: 31 | G98: =D98-F98 -> 0
B99: 45764 | C99: PLAY STATION PORTAL | D99: 2 | E99: Received | F99: 2 | G99: =D99-F99 -> 0
B100: 45764 | C100: DJI OSMO POCKET 3 | D100: 1 | E100: Received | F100: 1 | G100: =D100-F100 -> 0
B101: 45764 | C101: INSTAX MINI 40 | D101: 5 | E101: Received | F101: 5 | G101: =D101-F101 -> 0
B102: 45764 | C102: INSTAX MINI 12 | D102: 15 | E102: Received | F102: 15 | G102: =D102-F102 -> 0 | H102: 1 piece extra sent
B103: 45764 | C103: Meta Quest 3s 128 | D103: 1 | E103: Received | F103: 1 | G103: =D103-F103 -> 0
B104: 45764 | C104: PS5 | D104: 57 | E104: Received | F104: 57 | G104: =D104-F104 -> 0
B105: 45764 | C105: INSTAX MINI EVO | D105: 14 | E105: Received | F105: 14 | G105: =D105-F105 -> 0
B106: 45764 | C106: INSTAX Li PLAY | D106: 9 | E106: Received | F106: 9 | G106: =D106-F106 -> 0
B107: 45764 | C107: Dragon Age Game CD | D107: 48 | E107: Received | F107: 48 | G107: =D107-F107 -> 0
B108: 45764 | C108: PS5 | D108: 5 | E108: Purchase from BZS Trading | F108: 5 | G108: =D108-F108 -> 0
B109: 45762 | C109: IPHONE 13 128 | D109: 2 | E109: Directly Purchased in Dubai | F109: 2 | G109: =D109-F109 -> 0
B110: 45764 | C110: IPHONE 16 128 | D110: 4 | E110: Directly Purchased in Dubai | F110: 4 | G110: =D110-F110 -> 0
B111: 45764 | C111: DJI MAVIC PRO RC | D111: 4 | E111: Received | F111: 4 | G111: =D111-F111 -> 0
B112: 45764 | C112: DJI MAVIC PRO RC COMBO | D112: 1 | E112: Received | F112: 1 | G112: =D112-F112 -> 0
B113: 45764 | C113: MACBOOK M4 | D113: 1 | E113: Received | F113: 1 | G113: =D113-F113 -> 0
B114: 45764 | C114: Macbook Pro 16/512 | D114: 1 | E114: Received | F114: 1 | G114: =D114-F114 -> 0
... B123: 45771 | C123: iPhone16 Pro Max 256 | D123: 2 | E123: Purchase cash in Dubai | F123: 2 | G123: =D123-F123 -> 0
G124: =D124-F124 -> 0
B125: 45775 | C125: RAYBAN GLASSES | D125: 53 | E125: Received on 30-April | F125: 53 | G125: =D125-F125 -> 0
B126: 45775 | C126: AIRPODS | D126: 5 | E126: Received on 30-April | F126: 5 | G126: =D126-F126 -> 0
B127: 45775 | C127: INSTAX MINI 12 | D127: 18 | E127: Received on 30-April | F127: 18 | G127: =D127-F127 -> 0
B128: 45775 | C128: DJI MAVIC PRO RC | D128: 15 | E128: Received on 30-April | F128: 15 | G128: =D128-F128 -> 0
B129: 45775 | C129: DJI MAVIC PRO RC COMBO | D129: 11 | E129: Received on 30-April | F129: 11 | G129: =D129-F129 -> 0
B130: 45775 | C130: INSTAX MINI EVO | D130: 6 | E130: Received on 30-April | F130: 6 | G130: =D130-F130 -> 0
B131: 45775 | C131: INSTAX Li PLAY | D131: 2 | E131: Received on 30-April | F131: 2 | G131: =D131-F131 -> 0
B132: 45775 | C132: INSTAX MINI LINK 3 | D132: 1 | E132: Received on 30-April | F132: 1 | G132: =D132-F132 -> 0
B133: 45775 | C133: DJI OSMO Mobile 7 P | D133: 5 | E133: Received on 30-April | F133: 5 | G133: =D133-F133 -> 0
...

Sheet Monthly Sales
A1: {=A1:K74} -> 0
B2: Date | C2: Product Name | D2: Qty | E2: Per Unit Sale | F2: Per unit Purchase | G2: Per Unit Profit | H2: Total Sale | I2: Total Purhcase | J2: Total Profit
B3: 45718 | C3: STARLINK MINI | D3: 5 | E3: 1180 | F3: 1199.7871 | G3: =E3-F3 -> -19.78712 | H3: =E3*D3 -> 5900 | I3: =F3*D3 -> 5998.9356 | J3: =H3-I3 -> -98.9356
B4: 45722 | C4: MACBOOK M4 | D4: 20 | E4: 4900 | F4: 5019.6 | G4: =E4-F4 -> -119.6 | H4: =E4*D4 -> 98000 | I4: =F4*D4 -> 100392 | J4: =H4-I4 -> -2392
B5: 45722 | C5: STARLINK MINI | D5: 50 | E5: 1140 | F5: 1199.7871 | G5: =E5-F5 -> -59.78712 | H5: =E5*D5 -> 57000 | I5: =F5*D5 -> 59989.356 | J5: =H5-I5 -> -2989.356
B6: 45723 | C6: STARLINK MINI | D6: 44 | E6: 1135 | F6: 1199.7871 | G6: =E6-F6 -> -64.78712 | H6: =E6*D6 -> 49940 | I6: =F6*D6 -> 52790.633 | J6: =H6-I6 -> -2850.6333
B7: 45728 | C7: STARLINK MINI | D7: 2 | E7: 1135 | F7: 1199.7871 | G7: =E7-F7 -> -64.78712 | H7: =E7*D7 -> 2270 | I7: =F7*D7 -> 2399.5742 | J7: =H7-I7 -> -129.57424
B8: 45729 | C8: STARLINK MINI | D8: 30 | E8: 1125 | F8: 1199.7871 | G8: =E8-F8 -> -74.78712 | H8: =E8*D8 -> 33750 | I8: =F8*D8 -> 35993.614 | J8: =H8-I8 -> -2243.6136
B9: 45729 | C9: APPLE WATCH ULTRA | D9: 1 | E9: 2150 | F9: 2250 | G9: =E9-F9 -> -100 | H9: =E9*D9 -> 2150 | I9: =F9*D9 -> 2250 | J9: =H9-I9 -> -100
B10: 45733 | C10: MACBOOK M4 | D10: 2 | E10: 4930 | F10: 5019.6 | G10: =E10-F10 -> -89.6 | H10: =E10*D10 -> 9860 | I10: =F10*D10 -> 10039.2 | J10: =H10-I10 -> -179.2
B11: 45734 | C11: MACBOOK M4 | D11: 31 | E11: 4900 | F11: 5019.6 | G11: =E11-F11 -> -119.6 | H11: =E11*D11 -> 151900 | I11: =F11*D11 -> 155607.6 | J11: =H11-I11 -> -3707.6
B12: 45734 | C12: STARLINK MINI | D12: 3 | E12: 1115 | F12: 1199.7871 | G12: =E12-F12 -> -84.78712 | H12: =E12*D12 -> 3345 | I12: =F12*D12 -> 3599.3614 | J12: =H12-I12 -> -254.36136
B13: 45738 | C13: STARLINK MINI | D13: 4 | E13: 1120 | F13: 1199.7871 | G13: =E13-F13 -> -79.78712 | H13: =E13*D13 -> 4480 | I13: =F13*D13 -> 4799.1485 | J13: =H13-I13 -> -319.14848
B14: 45742 | C14: MACBOOK M4 | D14: 2 | E14: 4890 | F14: 5019.6 | G14: =E14-F14 -> -129.6 | H14: =E14*D14 -> 9780 | I14: =F14*D14 -> 10039.2 | J14: =H14-I14 -> -259.2
... B19: 45744 | C19: MACBOOK M4 | D19: 2 | E19: 4870 | F19: 5019.6 | G19: =E19-F19 -> -149.6 | H19: =E19*D19 -> 9740 | I19: =F19*D19 -> 10039.2 | J19: =H19-I19 -> -299.2
I20: Total Loss | J20: =SUM(J3:J19) -> -33070.257
B21: Date | C21: Product Name | D21: Qty | E21: Per Unit Sale | F21: Per unit Purchase | G21: Per Unit Profit | H21: Total Sale | I21: Total Purhcase | J21: Total Profit
B22: 45717 | C22: STARLINK V4 | D22: 3 | E22: 1175 | F22: 1045.5288 | G22: =E22-F22 -> 129.47122 | H22: =E22*D22 -> 3525 | I22: =F22*D22 -> 3136.5863 | J22: =H22-I22 -> 388.41367
B23: 45717 | C23: STARLINK V4 | D23: 7 | E23: 1175 | F23: 1045.5288 | G23: =E23-F23 -> 129.47122 | H23: =E23*D23 -> 8225 | I23: =F23*D23 -> 7318.7014 | J23: =H23-I23 -> 906.29857
B24: 45717 | C24: STARLINK V4 | D24: 10 | E24: 1180 | F24: 1045.5288 | G24: =E24-F24 -> 134.47122 | H24: =E24*D24 -> 11800 | I24: =F24*D24 -> 10455.288 | J24: =H24-I24 -> 1344.7122
B25: 45717 | C25: STARLINK V4 | D25: 15 | E25: 1175 | F25: 1045.5288 | G25: =E25-F25 -> 129.47122 | H25: =E25*D25 -> 17625 | I25: =F25*D25 -> 15682.932 | J25: =H25-I25 -> 1942.0684
B26: 45717 | C26: STARLINK V4 | D26: 7 | E26: 1175 | F26: 1045.5288 | G26: =E26-F26 -> 129.47122 | H26: =E26*D26 -> 8225 | I26: =F26*D26 -> 7318.7014 | J26: =H26-I26 -> 906.29857
D27: 0 | F27: 0 | G27: =E27-F27 -> 0 | H27: =E27*D27 -> 0 | I27: =F27*D27 -> 0 | J27: =H27-I27 -> 0
B28: 45719 | C28: STARLINK V4 | D28: 8 | E28: 1170 | F28: 1045.5288 | G28: =E28-F28 -> 124.47122 | H28: =E28*D28 -> 9360 | I28: =F28*D28 -> 8364.2302 | J28: =H28-I28 -> 995.76979
B29: 45719 | C29: AIRPODS | D29: 21 | E29: 540 | F29: 0 | G29: =E29-F29 -> 540 | H29: =E29*D29 -> 11340 | I29: =F29*D29 -> 0 | J29: =H29-I29 -> 11340
B30: 45719 | C30: CHROME CAST | D30: 100 | E30: 310 | F30: 283.75918 | G30: =E30-F30 -> 26.240824 | H30: =E30*D30 -> 31000 | I30: =F30*D30 -> 28375.918 | J30: =H30-I30 -> 2624.0824
B31: 45722 | C31: MACBOOK M4 | D31: 3 | E31: 6150 | F31: 5019.6 | G31: =E31-F31 -> 1130.4 | H31: =E31*D31 -> 18450 | I31: =F31*D31 -> 15058.8 | J31: =H31-I31 -> 3391.2
B32: 45722 | C32: iPad Pro 11 256 Wifi Only | D32: 13 | E32: 3120 | F32: 2940.3 | G32: =E32-F32 -> 179.7 | H32: =E32*D32 -> 40560 | I32: =F32*D32 -> 38223.9 | J32: =H32-I32 -> 2336.1
B33: 45722 | C33: iPad Pro 11 256 Cellular Unlock | D33: 4 | E33: 3800 | F33: 3630 | G33: =E33-F33 -> 170 | H33: =E33*D33 -> 15200 | I33: =F33*D33 -> 14520 | J33: =H33-I33 -> 680
B34: 45722 | C34: iPhone16 Pro Max 256 | D34: 17 | E34: 2860 | F34: 2766.06 | G34: =E34-F34 -> 93.94 | H34: =E34*D34 -> 48620 | I34: =F34*D34 -> 47023.02 | J34: =H34-I34 -> 1596.98
B35: 45722 | C35: iPhone16 Pro Max 256 | D35: 2 | E35: 2805 | F35: 2766.06 | G35: =E35-F35 -> 38.94 | H35: =E35*D35 -> 5610 | I35: =F35*D35 -> 5532.12 | J35: =H35-I35 -> 77.88
B36: 45723 | C36: BREVILLE COFFEE MACHINE | D36: 1 | E36: 325 | F36: 250 | G36: =E36-F36 -> 75 | H36: =E36*D36 -> 325 | I36: =F36*D36 -> 250 | J36: =H36-I36 -> 75
B37: 45723 | C37: CHROME CAST | D37: 20 | E37: 315 | F37: 283.75918 | G37: =E37-F37 -> 31.240824 | H37: =E37*D37 -> 6300 | I37: =F37*D37 -> 5675.1835 | J37: =H37-I37 -> 624.81648
B38: 45723 | C38: CHROME CAST | D38: 102 | E38: 310 | F38: 283.75918 | G38: =E38-F38 -> 26.240824 | H38: =E38*D38 -> 31620 | I38: =F38*D38 -> 28943.436 | J38: =H38-I38 -> 2676.564
D39: 0 | F39: 0 | G39: =E39-F39 -> 0 | H39: =E39*D39 -> 0 | I39: =F39*D39 -> 0 | J39: =H39-I39 -> 0
B40: 45729 | C40: JBL CHARGE 5 | D40: 188 | E40: 320 | F40: 276.14148 | G40: =E40-F40 -> 43.85852 | H40: =E40*D40 -> 60160 | I40: =F40*D40 -> 51914.598 | J40: =H40-I40 -> 8245.4018
B41: 45729 | C41: Meta Quest 3 512 | D41: 13 | E41: 1730 | F41: 1542.75 | G41: =E41-F41 -> 187.25 | H41: =E41*D41 -> 22490 | I41: =F41*D41 -> 20055.75 | J41: =H41-I41 -> 2434.25
B42: 45729 | C42: Ps5 Controller Dual sense | D42: 10 | E42: 205 | F42: 163.35 | G42: =E42-F42 -> 41.65 | H42: =E42*D42 -> 2050 | I42: =F42*D42 -> 1633.5 | J42: =H42-I42 -> 416.5
B43: 45729 | C43: AIRPODS | D43: 4 | E43: 545 | F43: 429 | G43: =E43-F43 -> 116 | H43: =E43*D43 -> 2180 | I43: =F43*D43 -> 1716 | J43: =H43-I43 -> 464
B44: 45729 | C44: Meta Quest 3 512 | D44: 1 | E44: 1730 | F44: 1524.6 | G44: =E44-F44 -> 205.4 | H44: =E44*D44 -> 1730 | I44: =F44*D44 -> 1524.6 | J44: =H44-I44 -> 205.4
B45: 45729 | C45: Beats Fit Pro | D45: 17 | E45: 380 | F45: 283.14 | G45: =E45-F45 -> 96.86 | H45: =E45*D45 -> 6460 | I45: =F45*D45 -> 4813.38 | J45: =H45-I45 -> 1646.62
B46: 45729 | C46: Beats Studio Buds | D46: 6 | E46: 220 | F46: 174.24 | G46: =E46-F46 -> 45.76 | H46: =E46*D46 -> 1320 | I46: =F46*D46 -> 1045.44 | J46: =H46-I46 -> 274.56
B47: 45729 | C47: Meta Quest 3 512 | D47: 1 | E47: 1730 | F47: 1524.6 | G47: =E47-F47 -> 205.4 | H47: =E47*D47 -> 1730 | I47: =F47*D47 -> 1524.6 | J47: =H47-I47 -> 205.4
D48: 0 | F48: 0 | G48: =E48-F48 -> 0 | H48: =E48*D48 -> 0 | I48: =F48*D48 -> 0 | J48: =H48-I48 -> 0
B49: 45730 | C49: DELONGI COFFEE MACHINE | D49: 1 | E49: 325 | F49: 241 | G49: =E49-F49 -> 84 | H49: =E49*D49 -> 325 | I49: =F49*D49 -> 241 | J49: =H49-I49 -> 84
B50: 45731 | C50: iPhone16 Pro Max 256 | D50: 1 | E50: 2880 | F50: 2880 | G50: =E50-F50 -> 0 | H50: =E50*D50 -> 2880 | I50: =F50*D50 -> 2880 | J50: =H50-I50 -> 0
B51: 45731 | C51: INSTAX WIDE 400 | D51: 5 | E51: 510 | F51: 396.50909 | G51: =E51-F51 -> 113.49091 | H51: =E51*D51 -> 2550 | I51: =F51*D51 -> 1982.5455 | J51: =H51-I51 -> 567.45455
B52: 45731 | C52: INSTAX MINI EVO | D52: 1 | E52: 680 | F52: 524.18182 | G52: =E52-F52 -> 155.81818 | H52: =E52*D52 -> 680 | I52: =F52*D52 -> 524.18182 | J52: =H52-I52 -> 155.81818
B53: 45731 | C53: INSTAX Li PLAY | D53: 1 | E53: 470 | F53: 429.06364 | G53: =E53-F53 -> 40.936364 | H53: =E53*D53 -> 470 | I53: =F53*D53 -> 429.06364 | J53: =H53-I53 -> 40.936364
B54: 45731 | C54: INSTAX MINI 40 | D54: 1 | E54: 330 | F54: 302.24545 | G54: =E54-F54 -> 27.754545 | H54: =E54*D54 -> 330 | I54: =F54*D54 -> 302.24545 | J54: =H54-I54 -> 27.754545
B55: 45731 | C55: INSTAX MINI 99 | D55: 1 | E55: 545 | F55: 528.40909 | G55: =E55-F55 -> 16.590909 | H55: =E55*D55 -> 545 | I55: =F55*D55 -> 528.40909 | J55: =H55-I55 -> 16.590909
B56: 45731 | C56: Macbook Air M4 13 inch | D56: 11 | E56: 3350 | F56: 3309.2273 | G56: =E56-F56 -> 40.772727 | H56: =E56*D56 -> 36850 | I56: =F56*D56 -> 36401.5 | J56: =H56-I56 -> 448.5
B57: 45731 | C57: MACBOOK M4 | D57: 2 | E57: 6350 | F57: 5019.6 | G57: =E57-F57 -> 1330.4 | H57: =E57*D57 -> 12700 | I57: =F57*D57 -> 10039.2 | J57: =H57-I57 -> 2660.8
B58: 45733 | C58: PS5 | D58: 2 | E58: 1680 | F58: 1323.5747 | G58: =E58-F58 -> 356.42532 | H58: =E58*D58 -> 3360 | I58: =F58*D58 -> 2647.1494 | J58: =H58-I58 -> 712.85064
B59: 45733 | C59: AIRPODS | D59: 5 | E59: 4930 | F59: 0 | G59: =E59-F59 -> 4930 | H59: =E59*D59 -> 24650 | I59: =F59*D59 -> 0 | J59: =H59-I59 -> 24650
B60: 45734 | C60: AIRPODS | D60: 63 | E60: 550 | F60: 0 | G60: =E60-F60 -> 550 | H60: =E60*D60 -> 34650 | I60: =F60*D60 -> 0 | J60: =H60-I60 -> 34650
... B69: 45742 | C69: STARLINK V4 | D69: 25 | E69: 1140 | F69: 967.69088 | G69: =E69-F69 -> 172.30912 | H69: =E69*D69 -> 28500 | I69: =F69*D69 -> 24192.272 | J69: =H69-I69 -> 4307.728
D70: 0 | F70: 0 | G70: =E70-F70 -> 0 | H70: =E70*D70 -> 0 | I70: =F70*D70 -> 0 | J70: =H70-I70 -> 0
B71: 45743 | C71: STARLINK V4 | D71: 9 | E71: 1140 | F71: 967.69088 | G71: =E71-F71 -> 172.30912 | H71: =E71*D71 -> 10260 | I71: =F71*D71 -> 8709.2179 | J71: =H71-I71 -> 1550.7821
B72: 45743 | C72: APPLE AIR TAG 1 PACK | D72: 5 | E72: 80 | F72: 76.5 | G72: =E72-F72 -> 3.5 | H72: =E72*D72 -> 400 | I72: =F72*D72 -> 382.5 | J72: =H72-I72 -> 17.5
B73: 45743 | C73: STARLINK V4 | D73: 4 | E73: 1140 | F73: 967.69088 | G73: =E73-F73 -> 172.30912 | H73: =E73*D73 -> 4560 | I73: =F73*D73 -> 3870.7635 | J73: =H73-I73 -> 689.23648
D74: 0 | F74: 0 | G74: =E74-F74 -> 0 | H74: =E74*D74 -> 0 | I74: =F74*D74 -> 0 | J74: =H74-I74 -> 0
B75: 45744 | C75: STARLINK V4 | D75: 4 | E75: 1140 | F75: 967.69088 | G75: =E75-F75 -> 172.30912 | H75: =E75*D75 -> 4560 | I75: =F75*D75 -> 3870.7635 | J75: =H75-I75 -> 689.23648
B76: 45744 | C76: STARLINK MINI | D76: 63 | E76: 1030 | F76: 1025 | G76: =E76-F76 -> 5 | H76: =E76*D76 -> 64890 | I76: =F76*D76 -> 64575 | J76: =H76-I76 -> 315
B77: 45744 | C77: STARLINK MINI | D77: 26 | E77: 1030 | F77: 1025 | G77: =E77-F77 -> 5 | H77: =E77*D77 -> 26780 | I77: =F77*D77 -> 26650 | J77: =H77-I77 -> 130
B78: 45744 | C78: STARLINK V4 | D78: 3 | E78: 1140 | F78: 967.69088 | G78: =E78-F78 -> 172.30912 | H78: =E78*D78 -> 3420 | I78: =F78*D78 -> 2903.0726 | J78: =H78-I78 -> 516.92736
B79: 45744 | C79: INSTAX MINI 99 BUNDEL | D79: 7 | E79: 635 | F79: 502.04545 | G79: =E79-F79 -> 132.95455 | H79: =E79*D79 -> 4445 | I79: =F79*D79 -> 3514.3182 | J79: =H79-I79 -> 930.68182
B80: 45744 | C80: INSTAX MINI 99 | D80: 1 | E80: 595 | F80: 489.22727 | G80: =E80-F80 -> 105.77273 | H80: =E80*D80 -> 595 | I80: =F80*D80 -> 489.22727 | J80: =H80-I80 -> 105.77273
B81: 45744 | C81: INSTAX WIDE 400 | D81: 1 | E81: 510 | F81: 405.90909 | G81: =E81-F81 -> 104.09091 | H81: =E81*D81 -> 510 | I81: =F81*D81 -> 405.90909 | J81: =H81-I81 -> 104.09091
B82: 45744 | C82: APPLE AIR TAG 1 PACK | D82: 269 | E82: 77.5 | F82: 76.5 | G82: =E82-F82 -> 1 | H82: =E82*D82 -> 20847.5 | I82: =F82*D82 -> 20578.5 | J82: =H82-I82 -> 269
B83: 45744 | C83: MACBOOK M4 | D83: 1 | E83: 5050 | F83: 5019.6 | G83: =E83-F83 -> 30.4 | H83: =E83*D83 -> 5050 | I83: =F83*D83 -> 5019.6 | J83: =H83-I83 -> 30.4
B84: 45745 | C84: STARLINK V4 | D84: 5 | E84: 1140 | F84: 967.69088 | G84: =E84-F84 -> 172.30912 | H84: =E84*D84 -> 5700 | I84: =F84*D84 -> 4838.4544 | J84: =H84-I84 -> 861.5456
I86: Total Profit | J86: =SUM(J22:J85) -> 125058.08
D99: Products Sold in Loss for the Month of March-2025
B101: Date | C101: Product Name | D101: Qty | E101: Per Unit Sale | F101: Per unit Purchase | G101: Per Unit Profit | H101: Total Sale | I101: Total Purhcase | J101: Total Profit
B102: 45718 | C102: STARLINK MINI | D102: 5 | E102: 1180 | F102: 1199.7871 | G102: =E102-F102 -> -19.78712 | H102: =E102*D102 -> 5900 | I102: =F102*D102 -> 5998.9356 | J102: =H102-I102 -> -98.9356
B103: 45722 | C103: STARLINK MINI | D103: 50 | E103: 1140 | F103: 1199.7871 | G103: =E103-F103 -> -59.78712 | H103: =E103*D103 -> 57000 | I103: =F103*D103 -> 59989.356 | J103: =H103-I103 -> -2989.356
B104: 45723 | C104: STARLINK MINI | D104: 44 | E104: 1135 | F104: 1199.7871 | G104: =E104-F104 -> -64.78712 | H104: =E104*D104 -> 49940 | I104: =F104*D104 -> 52790.633 | J104: =H104-I104 -> -2850.6333
B105: 45728 | C105: STARLINK MINI | D105: 2 | E105: 1135 | F105: 1199.7871 | G105: =E105-F105 -> -64.78712 | H105: =E105*D105 -> 2270 | I105: =F105*D105 -> 2399.5742 | J105: =H105-I105 -> -129.57424
B106: 45729 | C106: STARLINK MINI | D106: 30 | E106: 1125 | F106: 1199.7871 | G106: =E106-F106 -> -74.78712 | H106: =E106*D106 -> 33750 | I106: =F106*D106 -> 35993.614 | J106: =H106-I106 -> -2243.6136
B107: 45734 | C107: STARLINK MINI | D107: 3 | E107: 1115 | F107: 1199.7871 | G107: =E107-F107 -> -84.78712 | H107: =E107*D107 -> 3345 | I107: =F107*D107 -> 3599.3614 | J107: =H107-I107 -> -254.36136
B108: 45738 | C108: STARLINK MINI | D108: 4 | E108: 1120 | F108: 1199.7871 | G108: =E108-F108 -> -79.78712 | H108: =E108*D108 -> 4480 | I108: =F108*D108 -> 4799.1485 | J108: =H108-I108 -> -319.14848
B109: 45742 | C109: STARLINK MINI | D109: 25 | E109: 1050 | F109: 1199.7871 | G109: =E109-F109 -> -149.78712 | H109: =E109*D109 -> 26250 | I109: =F109*D109 -> 29994.678 | J109: =H109-I109 -> -3744.678
B110: 45742 | C110: STARLINK MINI | D110: 1 | E110: 1080 | F110: 1199.7871 | G110: =E110-F110 -> -119.78712 | H110: =E110*D110 -> 1080 | I110: =F110*D110 -> 1199.7871 | J110: =H110-I110 -> -119.78712
B111: 45743 | C111: STARLINK MINI | D111: 20 | E111: 1040 | F111: 1199.7871 | G111: =E111-F111 -> -159.78712 | H111: =E111*D111 -> 20800 | I111: =F111*D111 -> 23995.742 | J111: =H111-I111 -> -3195.7424
B112: 45743 | C112: STARLINK MINI | D112: 60 | E112: 1030 | F112: 1199.7871 | G112: =E112-F112 -> -169.78712 | H112: =E112*D112 -> 61800 | I112: =F112*D112 -> 71987.227 | J112: =H112-I112 -> -10187.227
B113: 45744 | C113: MACBOOK M4 | D113: 2 | E113: 4870 | F113: 5019.6 | G113: =E113-F113 -> -149.6 | H113: =E113*D113 -> 9740 | I113: =F113*D113 -> 10039.2 | J113: =H113-I113 -> -299.2
... B118: 45742 | C118: MACBOOK M4 | D118: 2 | E118: 4890 | F118: 5019.6 | G118: =E118-F118 -> -129.6 | H118: =E118*D118 -> 9780 | I118: =F118*D118 -> 10039.2 | J118: =H118-I118 -> -259.2
J120: =SUM(J102:J119) -> -33070.257

Sheet Pending Things
D2: cell wear payment | G2: 3.67 AED | H2: done
D3: AR to waheed bhai Payment 13 march 25 | G3: done
D4: AR 20,000 PKR for karachi Expense | G4: done
D5: AR personal zakat maintenance
D9: Instax Mini Bundle (not purchased but shipped) | G9: 6 | H9: done
D10: Instax Mini (confirm Model pls) (not purchased but shipped) | G10: 1 | H10: done
D11: Instax wide 400 (not purchased but shipped) | G11: 1 | H11: done
D13: Make Standard Rules Document for Purchasing
D14: Make Database for Maintaining all products last purchase
D21: Stock value 22-March-2025
G22: ITEM | H22: QTY | I22: PRICE w/o GST | J22: Total Price w/o GST
G23: v4 | H23: 173 | I23: 1045.8 | J23: =I23*H23 -> 180923.4
G24: mini | H24: 120 | I24: 1241 | J24: =I24*H24 -> 148920
G25: ps5 | H25: 37 | I25: 1465.8 | J25: =I25*H25 -> 54234.6
G26: airpods | H26: 4 | I26: 345 | J26: =I26*H26 -> 1380
G27: imac | H27: 1 | I27: 4099.75 | J27: =I27*H27 -> 4099.75
G28: Macbook 3 | H28: 2 | I28: 4735 | J28: =I28*H28 -> 9470
G29: Macbook 4 | H29: 7 | I29: 5034.77 | J29: =I29*H29 -> 35243.39
G30: jbl charge 5 | H30: 130 | I30: 288.75 | J30: =I30*H30 -> 37537.5
G31: Essential Flip | H31: 10 | I31: 150.35 | J31: =I31*H31 -> 1503.5
G32: Chrome Cast | H32: 257 | I32: 299.46 | J32: =I32*H32 -> 76961.22
G33: mini 99 bundel | H33: 20 | I33: 493.91 | J33: =I33*H33 -> 9878.2
G34: printer | H34: 1 | I34: 673 | J34: =I34*H34 -> 673
... G51: insatax Camera | H51: 1 | I51: 205 | J51: =I51*H51 -> 205
J52: =SUM(J23:J51) -> 644026.8
I56: 1653942 | J56: 1892972 | L56: =I56-J56 -> -239030
G58: 1653942
D63: Bus Pending Purchasing
D64: 20 pcs
D65: 133$
D66: Purchase from owais usa
D68: return 16 pro max fform stock | G68: done
D70: remove jbl charge 5 from stock | G70: Done
D72: sell instax camera to Waheed Bhai | G72: Done
G78: 1363956 | I78: 1195290
G81: =G78-I78 -> 168666
D86: TODO
D88: Carry charges to AR | G88: DONE
D89: 12 and 13 april AUS purchasing | G89: DONE
D91: Talley Raaz Ledger
D96: Add Magatop last 3 invoice | G96: done
D97: megatop payment | G97: done
D98: hajj payment through Raaz to waheed bhai | G98: done
D99: 28,385 AUD through Raaz to Waheed Bhai | G99: Waiting for confirmation | I99: issue solved
D106: 16-april entries and send report | G106: done
D110: 11 piece macbook air 24/512 not purchases but shipped | G110: 5 solved 4 need to be purchased | J110: 2 piece problem remeining
D112: 1 piece Extra macbook air 24/512 shipped but not purchased | G112: solved
D114: PS5 quantity Changed | G114: done
D118: 1 piece Ipad 11 pro 256 wifi short problem
D121: Australia GST received @ 2.33
D126: Star Link V4 = 1 units | G126: 1
D127: Chrome Cast = 5 units | G127: 5
D129: Dyson = 2 units | G129: 2
D131: Starlink H.P kit = 16 units | G131: 16
D133: Printer = 1 unit | G133: 1
D134: Ipad 11 pro Wifi 256 = 1 unit (Missing) | G134: 1
D136: Macbook M3 = 2 units (OLD) | G136: 2
D137: MacBook Air 13 inch 24/512 = 35 units | G137: 35
D138: MacBook Air 15 M3 24/512 = 13 units | G138: 13
D139: Macbook Air 15 M4 24/512 GB = 13 units | G139: 13
D141: Rayban Glasses = 39 units | G141: 39
D142: PlayStation Portal = 3 units | G142: 3
D144: Game CDs = 78 Units
D145: IPHONE 13 128 gb : 5 units (Purchased for karachi Office)
D147: INSTAX FLIM 20 PACK = 26 units
D148: INSTAX FLIM 10 PACK = 37 units in duabai 25 (12 short)
D150: NINJA BLAST BLENDER = 2 units
D151: Beats Studio Buds = 1 unit
D153: IPHONE CABLE: 108 units
D164: Mock interviews with HRs (Saim) | G164: brand ambassadors from each university | J164: ashar
D165: Workshop for Linkedin Optimization (Saim)
D168: gaming
D169: CS ,Fifa, takken, Chess
D172: Hackaton | G172: top 5 will give HR interview | I172: Maaz
D173: speed coding
D175: Cyber Security
D176: hack the box | G176: Quiz | I176: Khuzaima
D177: Try Hack ME | G177: 2nd competetion
D178: Bug Bounty (Khuzaima)
D180: Final yar project representation | G180: Abdul rehman
D182: ideas pitching competition | G182: Maaz
D184: AI
D185: kagggle | G185: single round | H185: Ashar
D186: judgment
D188: photography
D189: videography
D192: google form with points kis ko kia aata hay
D196: Dib Card entries
D198: Rehmey mamu entries for last 3 days | G198: ok
D200: owais houston ledger
D202: waheed bhai entries
D206: 647,000 PKR @80 from Ahsan to Raaz Pending | G206: Done
D208: pro max 512 DT | G208: 1
D209: pro max 512 BT | G209: 1
D210: pro max 256 DT | G210: 10
D211: pro max 256 BT | G211: 6
D212: pro max 256 NT | G212: 4
D213: pro max 1tb DT | G213: 1
D215: 16 plus 128 pink | G215: 4
D216: 16 plus 128 white | G216: 3
...

Sheet Karachi Sale
A2: March 18,2025 | B2: 16 pro 256 gb | C2: sale bilal G49 | D2: 195000 | E2: d | G2: 10872.611
A3: March 20,2025 | C3: 100,000 in AR A/c | E3: d
A4: March 22,2025 | C4: 95,000 in AR A/C | E4: d
A5: March 25,2025 | B5: 16 pro 256 gb | C5: Sale Zurain Johar | D5: 215000 | E5: d
A6: March 25,2025 | C6: from Zurain to abdul rehman | D6: 10000 | E6: d
A7: March 25,2025 | C7: from Abubaker to Abdul Rehman | D7: 125000 | E7: d
A8: March 26,2025 | C8: from Abubaker to Abdul Rehman | D8: 80000 | E8: d
A9: March 30,2025 | B9: 16 pro Max 256 | C9: Sale Waqas Mt | D9: 258000 | E9: d
A10: April 04,2025 | C10: from Waqas to Abdul Rehman | D10: 150000
A11: April 05,2025 | C11: from Waqas to Abdul Rehman | D11: 58000
A12: April 08,2025 | C12: from Waqas to Abdul Rehman | D12: 50000
A13: April 10,2025 | B13: 16 pro 128 gb | C13: Sale Waqas Mt | D13: 185500 | E13: d
A14: April 12,2025 | C14: from Waqas to Abdul Rehman | D14: 185500
B18: PRODUCT NAME | C18: QTY IN AUSTRALIA | D18: QTY IN NEWZEALAND | E18: QTY IN USA
B19: STARLINK V4 | C19: 15
B20: PS5 | C20: 1
B21: INSTAX WIDE 400 | C21: 10
B22: INSTAX MINI EVO | D22: 50
B23: Meta Quest 3 512 | C23: 1
B24: Meta Quest 3s 128 | C24: 1
B25: Ps5 Controller Dual sense | E25: 1
B26: iPhone 16 128 | E26: 1
B27: Macbook Air 24/512 GB | C27: 1
B28: Macbook Air 15 24/512 GB | C28: 1
B29: Dragon Age Game CD | C29: 20
B30: DJI OSMO Mobile 7 P | C30: 2
B31: DJI OSMO Action 5 pro | C31: 2
B32: CANON SX740 | C32: 1 | D32: 35
B33: DJI MAVIC 4 PRO | C33: 1
B34: DJI MAVIC 4 PRO COMBO | C34: 1
B35: PS5 Pro | C35: 3 | E35: 1
B36: CANON G7X Mark III | C36: 1
B37: DJI MINI 4k FLY MORE COMBO | C37: 20
B38: Ipad Pro 13" W+C Black 256gb | E38: 7
B39: iPad Pro 11 256 Cellular Unlock | E39: 12
B40: Apple Watch Ultra 2 49mm | E40: 1
B41: iPhone16 Pro Max 256 | E41: 46
B42: iPhone16 Pro 256 | E42: 20
B43: Ipad 11 Gen 128gb wifi | E43: 1
B44: Ipad 11 Gen 128gb W+C | E44: 2
B45: Iphone 17 pro max 256gb | C45: 6
F52: IPAD AIR 13 M3 256GB | G52: 1 | H52: 2600 | I52: =G52*H52 -> 2600
F53: IPAD PRO 13 M4 256 W+C | G53: 1 | H53: 3600 | I53: =G53*H53 -> 3600
F54: MACBOOK M4 MAX CHIP 16'' 36-1TB | G54: 2 | H54: 9944.3 | I54: =G54*H54 -> 19888.6
F55: IPAD AIR 11" M3 128GB | G55: 1 | H55: 2154 | I55: =G55*H55 -> 2154
F56: MACBOOK AIR M2 13''16-256 | G56: 1 | H56: 2405.3 | I56: =G56*H56 -> 2405.3
B57: Item | C57: Qty Not Purchased but sold | F57: I WATCH SE GEN 2 40MM | G57: 3 | H57: 717 | I57: =G57*H57 -> 2151
B58: iPad Air 13 128 Wifi Only | C58: -1 | F58: MACBOOK M4 PRO 14'' 24-512 | G58: 1 | H58: 7241.7 | I58: =G58*H58 -> 7241.7
B59: CANON SX740 | C59: -2 | F59: APPLE WATCH ULTRA 2 49MM | G59: 5 | H59: 2050 | I59: =G59*H59 -> 10250
B60: Ipad Pro 13" W+C Black 512gb | C60: -1 | F60: IPAD A16 128 W+C | G60: 2 | H60: 1041 | I60: =G60*H60 -> 2082
B61: Samsung Galaxy S25 plus 256 | C61: -1 | F61: APPLE SERIES 10 46MM 4G | G61: 2 | H61: 1250 | I61: =G61*H61 -> 2500
B62: Iphone 16 PM 1TB | C62: -1 | F62: APPLE WATCH ULTRA 2 49MM | G62: 1 | H62: 2050 | I62: =G62*H62 -> 2050
B63: Ipad A16 WIFI Only | C63: -1 | F63: APPLE SERIES 10 42MM 4G | G63: 2 | H63: 1150 | I63: =G63*H63 -> 2300
B64: Ipad Pro 13'' M4 256gb wifi | C64: -2 | I64: =SUM(I52:I63) -> 59222.6
B65: Iphone Air 17 256gb | C65: -4
B66: Ipad Air 11'' M3 256gb | C66: -1
B67: Apple Watch SE 3 40mm | C67: -1
B68: Sandisk Portable G-Drive 6TB | C68: -1
B69: WD-Black P10 G-Drive 4TB | C69: -1
B70: WD-Black P10 G-Drive 5TB | C70: -4
B71: Rad 700i Radar & Detector | C71: -2
B72: Ipad pro 11'' M4 256gb wifi | C72: -1
B73: Ipad pro 11'' M4 512gb wifi | C73: -1

Sheet Sheet2
B2: 45813 | C2: Starlink V4 200 * $492 | D2: 300 | E2: 492 | F2: =E2*D2 -> 147600 | G2: =F2*13.04/100 -> 19247.04
B3: 45813 | C3: Google Streamer 250 * $149 | D3: 250 | E3: 149 | F3: =E3*D3 -> 37250 | G3: =F3*13.04/100 -> 4857.4
F4: =E4*D4 -> 0 | G4: =F4*13.04/100 -> 0
B5: 45831 | C5: Canon SX740 Photo Warehouse online Pending Delivery | D5: 4 | E5: 775 | F5: =E5*D5 -> 3100 | G5: =F5*13.04/100 -> 404.24
F6: =E6*D6 -> 0 | G6: =F6*13.04/100 -> 0
B7: 45831 | C7: Canon SX740 Photo Warehouse online Pending Delivery | D7: 4 | E7: 775 | F7: =E7*D7 -> 3100 | G7: =F7*13.04/100 -> 404.24
F8: =E8*D8 -> 0 | G8: =F8*13.04/100 -> 0
B9: 45839 | C9: Mark II with memory card and pouch Photo WH | D9: 5 | E9: 1380 | F9: =E9*D9 -> 6900 | G9: =F9*13.04/100 -> 899.76
B10: 45839 | C10: Canon Mark II Photo WH | D10: 1 | E10: 1295 | F10: =E10*D10 -> 1295 | G10: =F10*13.04/100 -> 168.868
B11: 45839 | C11: Canon Mark III Photo WH | D11: 1 | E11: 1375 | F11: =E11*D11 -> 1375
B12: 45839 | C12: Lense Photo WH | D12: 1 | E12: 852 | F12: =E12*D12 -> 852 | G12: =F12*13.04/100 -> 111.1008
B13: 45839 | C13: SX740 Photo WH | D13: 4 | E13: 679 | F13: =E13*D13 -> 2716 | G13: =F13*13.04/100 -> 354.1664
F14: =E14*D14 -> 0 | G14: =F14*13.04/100 -> 0
B15: 45840 | C15: Mark II photogear | D15: 2 | E15: 1229 | F15: =E15*D15 -> 2458 | G15: =F15*13.04/100 -> 320.5232
B16: 45840 | C16: Lense photogear | D16: 1 | E16: 852 | F16: =E16*D16 -> 852 | G16: =F16*13.04/100 -> 111.1008
B17: 45840 | C17: SX740 Progear | D17: 3 | E17: 765.71 | F17: =E17*D17 -> 2297.13 | G17: =F17*13.04/100 -> 299.54575
B18: 45840 | C18: G7X Mark III Silver Progear | D18: 1 | E18: 1345 | F18: =E18*D18 -> 1345 | G18: =F18*13.04/100 -> 175.388
B19: 45840 | C19: SX740 Progear | D19: 3 | E19: 738 | F19: =E19*D19 -> 2214 | G19: =F19*13.04/100 -> 288.7056
B20: 45840 | C20: Lense Progear | D20: 1 | E20: 852 | F20: =E20*D20 -> 852 | G20: =F20*13.04/100 -> 111.1008
B21: 45840 | C21: Sx740 Photo WH City | D21: 1 | E21: 775 | F21: =E21*D21 -> 775 | G21: =F21*13.04/100 -> 101.06
B22: 45840 | C22: G7X Mark II Photo WH City | D22: 1 | E22: 1295 | F22: =E22*D22 -> 1295 | G22: =F22*13.04/100 -> 168.868
B23: 45840 | C23: G7X Mark III Photo WH City | D23: 1 | E23: 1375 | F23: =E23*D23 -> 1375 | G23: =F23*13.04/100 -> 179.3
B24: 45840 | C24: Lense Photo WH City | D24: 1 | E24: 852 | F24: =E24*D24 -> 852 | G24: =F24*13.04/100 -> 111.1008
B25: 45840 | C25: G7X Mark II Rubber Monkey online Delivered Abdul Pending | D25: 1 | E25: 1228 | F25: =E25*D25 -> 1228 | G25: =F25*13.04/100 -> 160.1312
B26: 45840 | C26: Sx740 Rubber Monkey online Delivered Abdul Pending | D26: 1 | E26: 750 | F26: =E26*D26 -> 750 | G26: =F26*13.04/100 -> 97.8
F27: =E27*D27 -> 0 | G27: =F27*13.04/100 -> 0
B28: 45841 | C28: G7X Mark II Auckland Camera centre | D28: 4 | E28: 1197 | F28: =E28*D28 -> 4788 | G28: =F28*13.04/100 -> 624.3552
B29: 45841 | C29: Lense Auckland Camera centre | D29: 1 | E29: 852 | F29: =E29*D29 -> 852 | G29: =F29*13.04/100 -> 111.1008
B30: 45841 | C30: Deposit Lense Auckland Camera centre | D30: 1 | E30: 338 | F30: =E30*D30 -> 338 | G30: =F30*13.04/100 -> 44.0752
B31: 45840 | C31: Mark III photo wearhouse | D31: 1 | E31: 1375 | F31: =E31*D31 -> 1375 | G31: =F31*13.04/100 -> 179.3
B32: 45840 | C32: SX740 photo wearhouse | D32: 1 | E32: 775 | F32: =E32*D32 -> 775 | G32: =F32*13.04/100 -> 101.06
B33: 45841 | C33: Sx740 Harvey norman Mount Roskills Pending Collection | D33: 4 | E33: 766 | F33: =E33*D33 -> 3064 | G33: =F33*13.04/100 -> 399.5456
F34: =E34*D34 -> 0 | G34: =F34*13.04/100 -> 0
F35: =E35*D35 -> 0 | G35: =F35*13.04/100 -> 0
B36: 45844 | C36: V4 Standard Kit Noel Leeming | D36: 150 | E36: 494 | F36: =E36*D36 -> 74100 | G36: =F36*13.04/100 -> 9662.64
F37: =E37*D37 -> 0 | G37: =F37*13.04/100 -> 0
B38: 45846 | C38: starlink V4 Noel Leeming | D38: 100 | E38: 494 | F38: =E38*D38 -> 49400 | G38: =F38*13.04/100 -> 6441.76
B39: 45848 | C39: Instax Wide 400 Noel Leeming | D39: 100 | E39: 229 | F39: =E39*D39 -> 22900 | G39: =F39*13.04/100 -> 2986.16
F40: =E40*D40 -> 0 | G40: =F40*13.04/100 -> 0
B41: 45854 | C41: PS5 Console Noel Leeming | D41: 200 | E41: 728 | F41: =E41*D41 -> 145600 | G41: =F41*13.04/100 -> 18986.24
B42: 45854 | C42: PS5 Controller Noel Leeming | D42: 80 | E42: 85 | F42: =E42*D42 -> 6800 | G42: =F42*13.04/100 -> 886.72
F43: =E43*D43 -> 0 | G43: =F43*13.04/100 -> 0
B44: 45861 | C44: G7X MARK III Black Progear Pending Collection | D44: 10 | E44: 1448.98 | F44: =E44*D44 -> 14489.8 | G44: =F44*13.04/100 -> 1889.4699
B45: 45862 | C45: G7X MARK III Silver Progear Pending Collection | D45: 5 | E45: 1448.98 | F45: =E45*D45 -> 7244.9 | G45: =F45*13.04/100 -> 944.73496
B46: 45863 | C46: Lenses Canon Progear Pending Collection | D46: 2 | E46: 852 | F46: =E46*D46 -> 1704 | G46: =F46*13.04/100 -> 222.2016
B47: 45862 | C47: Mark III Rubber Monkey online Pending Delivery Abdul NL | D47: 1 | E47: 1359 | F47: =E47*D47 -> 1359 | G47: =F47*13.04/100 -> 177.2136
B48: 45865 | C48: SX740 Noel Leeming $4000 Deposit Paid | D48: 20 | E48: 720 | F48: =E48*D48 -> 14400 | G48: =F48*13.04/100 -> 1877.76
B49: 29/072025 | C49: G7X MARK III Silver Auckland Camera centre | D49: 1 | E49: 1359 | F49: =E49*D49 -> 1359 | G49: =F49*13.04/100 -> 177.2136
F50: =E50*D50 -> 0 | G50: =F50*13.04/100 -> 0
B51: 45831 | C51: StarLink Mini (OLD Purchsing) | D51: 3 | E51: 550 | F51: =E51*D51 -> 1650 | G51: =F51*13.04/100 -> 215.16
B52: 45864 | C52: SX740 progear Deposit/ Pending Stock | D52: 10 | E52: 738 | F52: =E52*D52 -> 7380 | G52: =F52*13.04/100 -> 962.352
B53: 45864 | C53: SX740 photogear Deposit/ Pending Stock | D53: 10 | E53: 738 | F53: =E53*D53 -> 7380 | G53: =F53*13.04/100 -> 962.352
G54: =SUM(G2:G53) -> 76422.854

Sheet Sheet1
C1: CREDIT CARD DIB
B2: Date | C2: Details | D2: Amount
B3: 45574 | C3: Chemist WareHouse AUD 246.86 | D3: 644.74 | E3: Waheed Bhai | F3: ok
B4: 45576 | C4: Smart Care AUS 5.0 AUD | D4: 12.9 | E4: Waheed Bhai | F4: ok
B5: 45586 | C5: Bunnings Group LTD 549 AUD | D5: 1355.87 | E5: Waheed Bhai | F5: ok
B6: 45631 | C6: Bunnings -9453(NZD 4.00) | D6: 9.01 | E6: Waheed Bhai | F6: ok
B7: 45754 | C7: Office Works 0234(AUD 2089.99) | D7: 4967.1 | E7: Waheed Bhai | F7: ok
B8: 45754 | C8: Office Works 0234(AUD 2089.99) | D8: 4967.1 | E8: Waheed Bhai | F8: ok
B9: 45755 | C9: The Good Guys AUD 2203 | D9: 5235.6 | E9: Waheed Bhai | F9: ok
B10: 45792 | C10: AGODA.COM SOFITEL SH, GB | D10: 745.87 | E10: Waheed Bhai | F10: ok
B12: 45698 | C12: TST* FILLI CAFÉ 2 USD 3.24 | D12: 12.34 | E12: Expense | F12: ok
B13: 45698 | C13: ASHRAS KITCHEN USD 7.02 | D13: 26.74 | E13: Expense | F13: ok
B14: 45698 | C14: ASHRAS KITCHEN USD 22.19 | D14: 84.54 | E14: Expense | F14: ok
B15: 45698 | C15: COMFPRT INNS USD 134.79 | D15: 513.48 | E15: Expense | F15: ok
... B41: 45798 | C41: DU Apple Pay, AE | D41: 208.95 | E41: Expense | F41: ok
C42: TOTAL | D42: =SUM(D3:D41) -> 24973.38
C48: DIB
B49: Date | C49: Details | D49: Amount
B50: 45616 | C50: DU Apple Pay, AE | D50: 168.51 | F50: ok
B51: 45616 | C51: Dubai Electricity AE | D51: 272.23 | F51: ok
B52: 45626 | C52: POS PURCHASE JB HIFI HILL ST AUCKLAND | D52: 1444.82 | F52: ok
B53: 45631 | C53: POS PURCHASE HARVEY NORMAN NORTH RYDE | D53: 2576.28 | F53: ok
B54: 45661 | C54: INHOUSE CHEQUE DEBIT | D54: 5675 | F54: ok
B55: 45721 | C55: INHOUSE CHEQUE DEBIT | D55: 5675 | F55: ok
B56: 45778 | C56: INHOUSE CHEQUE DEBIT | D56: 5675 | F56: ok
C57: TOTAL | D57: =SUM(D50:D56) -> 21486.84

Sheet profit distribution
B3: Net Income | C3: 220128.88
B4: 5 % of Net | C4: =C3*0.05 -> 11006.444
B6: remaining Amount | C6: =C3-C4 -> 209122.44
A7: profit 1 | B7: 40 percent | C7: =C6*0.4 -> 83648.974
A8: profit 2 | B8: 60 percent | C8: =C6-C7 -> 125473.46
B10: 33.33 percent of profit 2 | C10: =C8/3 -> 41824.487
B13: Total (Investment )
B14: 979471
B15: 728047
B16: 107767
B17: =SUM(B14:B16) -> 1815285
B20: Investor | C20: Investment (AED) | D20: Ratio (Investment ÷ Total) | E20: Profit Share (AED)
B21: Waheed Bhai | C21: 1290232 | D21: 1290232 ÷ 21,96,890 = 0.5872 | E21: 83,648.93 × 0.5872 = 49,118.65
B22: Abdul Rehman Bhai | C22: 784896 | D22: 784896 ÷ 21,96,890 = 0.3572 | E22: 83,648.93 × 0.3572 = 29,879.39
B23: Faisal Bhai | C23: 121762 | D23: 121762 ÷ 21,96,890 = 0.0554 | E23: 83,648.93 × 0.0554 = 4,634.15
D26: Waheed Bhai | E26: 20% + investment profit | F26: 90943.14
D27: Abdul Rehman Bhai | E27: 20% + investment profit | F27: 71703.88
D28: Faisal Bhai | E28: 20% + investment profit | F28: 46458.64
B30: Formula for finding Investment Profit
B32: investment amount / total investment = percentage for profit
